Workbook

Sheet Data Input
A1: MARLINE DATA INPUT — Single Source of Truth for All Portfolio Data
A2: COLOR LEGEND: | C2: Blue = Manual Input | E2: Red = YCharts Add-In (auto) | G2: Orange = DWA Import (paste) | I2: Light Blue = Market Data (auto) | K2: Black = Computed Formula
A4: PORTFOLIO ASSUMPTIONS
A5: Risk-Free Rate | B5: =IFERROR(ycps("^TNX","price")/100,0.045) -> 0.045 | C5: Auto from YCharts 10Y Treasury yield or manual override
A6: Benchmark Return | B6: =IFERROR(ycps("SPY","one_year_return"),0.1) -> 0.1 | C6: Auto from YCharts SPY 1Y return or manual
A7: Benchmark Vol | B7: =IFERROR(ycps("SPY","one_year_volatility"),0.16) -> 0.16 | C7: Auto from YCharts SPY 1Y volatility or manual
A8: Portfolio Value | B8: 100000 | C8: Total AUM — update monthly
A9: Rebalance Band (±%) | B9: 0.05 | C9: Drift threshold to trigger rebalance
A10: Max Single Asset | B10: 0.3 | C10: Position concentration limit
A11: Min Single Asset | B11: 0.02 | C11: Minimum meaningful position
A12: Max Equity | B12: 0.7 | C12: Total equity allocation cap
A13: Min Fixed Income | B13: 0.1 | C13: Minimum bond allocation floor
A14: Max Alternatives | B14: 0.25 | C14: Alternatives + MF + hedge cap
A17: LIVE MARKET DATA — YCharts Auto-Refresh
A18: S&P 500 Price | B18: =IFERROR(ycps("SPY","price"),"") | C18: SPY last price
A19: S&P 500 1Y Return | B19: =IFERROR(ycps("SPY","one_year_return"),"") | C19: Benchmark trailing 1Y
A20: Nasdaq 100 1Y Return | B20: =IFERROR(ycps("QQQ","one_year_return"),"") | C20: Growth benchmark
A21: VIX Level | B21: =IFERROR(ycps("^VIX","price"),18) -> 18 | C21: CBOE Volatility Index — feeds Buffered ETF regime
A22: 10-Year Treasury Yield | B22: =IFERROR(ycps("^TNX","price")/100,0.045) -> 0.045 | C22: Risk-free rate proxy
A23: 2-Year Treasury Yield | B23: =IFERROR(ycps("^IRX","price")/100,0.04) -> 0.04 | C23: Short-term rate
A24: Yield Curve Spread | B24: =B22-B23 -> 0.005 | C24: 10Y minus 2Y — inversion = recession risk
A25: US Dollar Index | B25: =IFERROR(ycps("UUP","price"),"") | C25: Dollar strength
A26: Gold Price | B26: =IFERROR(ycps("GLD","price"),"") | C26: Safe haven gauge
A27: High Yield Spread | B27: =IFERROR(ycps("HYG","dividend_yield")-ycps("AGG","dividend_yield"),"") | C27: Credit stress indicator
A28: Market Breadth (SPY RSI) | B28: =IFERROR(50+ycps("SPY","one_month_return")*300,50) -> 50 | C28: Breadth proxy 0-100
A29: Put/Call Ratio Proxy | B29: =IFERROR(100-B28,50) -> 50 | C29: Sentiment (inverse of breadth)
A32: FSM THRESHOLDS
A33: Fully Invested ≥ | B33: 0.7
A34: Caution ≥ | B34: 0.5
A35: Defensive ≥ | B35: 0.3
A36: Risk Off < | B36: 0.3
A38: CASH TRIGGER THRESHOLDS
A39: MMPR50 Trigger < | B39: 0.4
A40: MMPR70 Trigger < | B40: 0.25
A41: PR4050 Trigger < | B41: 45
A42: PR4080 Trigger < | B42: 40
A44: COMPOSITE SIGNAL WEIGHTS
A45: Trend Weight | B45: 0.3
A46: Technical Weight | B46: 0.25
A47: Fundamental Weight | B47: 0.25
A48: DWA Weight | B48: 0.2
A49: Weights Total | B49: =SUM(B45:B48) -> 1 | C49: Must = 100%
A52: PORTFOLIO HOLDINGS — Master Ticker Data (All sheets reference this)
A53: Red cells = YCharts YCPS() auto-refresh | Orange cells = paste from DWA export | Black = formulas
A54: Ticker | B54: Class | C54: Type | D54: Price | E54: 1Y Return | F54: 3Y Ann Rtn | G54: 5Y Ann Rtn | H54: Volatility | I54: Max DD 3Y | J54: Beta 5Y | K54: Div Yield | L54: Fwd P/E | M54: 1M Return | N54: 3M Return | O54: 6M Return | P54: 12M Return | Q54: DWA RS Score | R54: DWA RS Rating | S54: DWA Signal | T54: DWA Matrix | U54: DWA Sector RS | V54: Sharpe | W54: Sortino | X54: Info Ratio | Y54: Treynor | Z54: Trend Score | AA54: Technical Score | AB54: Fundamental Score | AC54: Composite Score | AD54: Target Wt | AE54: Current Wt | AF54: Drift | AG54: Action
A55: Manual | B55: Manual | C55: Manual | D55: YCharts Auto | E55: YCharts Auto | F55: YCharts Auto | G55: YCharts Auto | H55: YCharts Auto | I55: YCharts Auto | J55: YCharts Auto | K55: YCharts Auto | L55: YCharts Auto | M55: YCharts Auto | N55: YCharts Auto | O55: YCharts Auto | P55: YCharts Auto | Q55: DWA Paste | R55: DWA Paste | S55: DWA Paste | T55: DWA Paste | U55: DWA Paste | V55: Computed | W55: Computed | X55: Computed | Y55: Computed | Z55: Computed | AA55: Computed | AB55: Computed | AC55: Computed | AD55: Manual | AE55: Manual | AF55: Computed | AG55: Computed
A56: SPY | B56: US Eq | C56: ETF | D56: =IFERROR(ycps("SPY","price"),"") | E56: =IFERROR(ycps("SPY","one_year_return"),"") | F56: =IFERROR(ycps("SPY","three_year_annualized_return"),"") | G56: =IFERROR(ycps("SPY","five_year_annualized_return"),"") | H56: =IFERROR(ycps("SPY","one_year_volatility"),"") | I56: =IFERROR(ycps("SPY","max_drawdown_3_year"),"") | J56: =IFERROR(ycps("SPY","beta_5_year"),"") | K56: =IFERROR(ycps("SPY","dividend_yield"),"") | L56: =IFERROR(ycps("SPY","forward_pe_ratio"),"") | M56: =IFERROR(ycps("SPY","one_month_return"),"") | N56: =IFERROR(ycps("SPY","three_month_return"),"") | O56: =IFERROR(ycps("SPY","six_month_return"),"") | P56: =IFERROR(ycps("SPY","one_year_return"),"") | V56: =IFERROR(IF(H56="","",IF(H56=0,0,(E56-$B$5)/H56)),"") | W56: =IFERROR(IF(V56="","",V56*1.3),"") | X56: =IFERROR(IF(H56="","",IF(H56=0,0,(E56-$B$6)/H56)),"") | Y56: =IFERROR(IF(OR(J56="",J56=0),"",((E56-$B$5)/J56)),"") | Z56: =IFERROR(IF(P56="",0,MIN(100,MAX(0,ROUND(50+P56*150+IF(E56>0,15,0)+IF(J56>0,5,-5),0)))),0) -> 0 | AA56: =IFERROR(IF(M56="",0,MIN(100,MAX(0,ROUND(50+M56*200+IF(AND(M56>0,N56>0),10,-5)+IF(H56<0.2,10,-5),0)))),0) -> 0 | AB56: =IFERROR(IF(OR(E56="",H56=""),0,MIN(100,MAX(0,ROUND(30+IF(H56>0,E56/H56,0)*40+IF(ABS(J56)<0.5,15,0)+IF(E56>0.08,10,0),0)))),0) -> 0 | AC56: =IFERROR(ROUND(Z56*$B$45+AA56*$B$46+AB56*$B$47+IF(Q56<>"",Q56,MIN(100,MAX(0,ROUND(50+(M56*0.4+N56*0.3+O56*0.2+P56*0.1)*200,0))))*$B$48,0),0) -> 0 | AD56: 0.08 | AE56: 0.09 | AF56: =AE56-AD56 -> 0.01 | AG56: =IF(ABS(AF56)>$B$9,"REBALANCE",IF(AND(AC56>=60,AF56<0),"ADD",IF(AND(AC56<40,AF56>0),"TRIM","HOLD"))) -> TRIM
A57: QQQ | B57: US Eq | C57: ETF | D57: =IFERROR(ycps("QQQ","price"),"") | E57: =IFERROR(ycps("QQQ","one_year_return"),"") | F57: =IFERROR(ycps("QQQ","three_year_annualized_return"),"") | G57: =IFERROR(ycps("QQQ","five_year_annualized_return"),"") | H57: =IFERROR(ycps("QQQ","one_year_volatility"),"") | I57: =IFERROR(ycps("QQQ","max_drawdown_3_year"),"") | J57: =IFERROR(ycps("QQQ","beta_5_year"),"") | K57: =IFERROR(ycps("QQQ","dividend_yield"),"") | L57: =IFERROR(ycps("QQQ","forward_pe_ratio"),"") | M57: =IFERROR(ycps("QQQ","one_month_return"),"") | N57: =IFERROR(ycps("QQQ","three_month_return"),"") | O57: =IFERROR(ycps("QQQ","six_month_return"),"") | P57: =IFERROR(ycps("QQQ","one_year_return"),"") | V57: =IFERROR(IF(H57="","",IF(H57=0,0,(E57-$B$5)/H57)),"") | W57: =IFERROR(IF(V57="","",V57*1.3),"") | X57: =IFERROR(IF(H57="","",IF(H57=0,0,(E57-$B$6)/H57)),"") | Y57: =IFERROR(IF(OR(J57="",J57=0),"",((E57-$B$5)/J57)),"") | Z57: =IFERROR(IF(P57="",0,MIN(100,MAX(0,ROUND(50+P57*150+IF(E57>0,15,0)+IF(J57>0,5,-5),0)))),0) -> 0 | AA57: =IFERROR(IF(M57="",0,MIN(100,MAX(0,ROUND(50+M57*200+IF(AND(M57>0,N57>0),10,-5)+IF(H57<0.2,10,-5),0)))),0) -> 0 | AB57: =IFERROR(IF(OR(E57="",H57=""),0,MIN(100,MAX(0,ROUND(30+IF(H57>0,E57/H57,0)*40+IF(ABS(J57)<0.5,15,0)+IF(E57>0.08,10,0),0)))),0) -> 0 | AC57: =IFERROR(ROUND(Z57*$B$45+AA57*$B$46+AB57*$B$47+IF(Q57<>"",Q57,MIN(100,MAX(0,ROUND(50+(M57*0.4+N57*0.3+O57*0.2+P57*0.1)*200,0))))*$B$48,0),0) -> 0 | AD57: 0.07 | AE57: 0.065 | AF57: =AE57-AD57 -> -0.005 | AG57: =IF(ABS(AF57)>$B$9,"REBALANCE",IF(AND(AC57>=60,AF57<0),"ADD",IF(AND(AC57<40,AF57>0),"TRIM","HOLD"))) -> HOLD
A58: IWM | B58: US Eq | C58: ETF | D58: =IFERROR(ycps("IWM","price"),"") | E58: =IFERROR(ycps("IWM","one_year_return"),"") | F58: =IFERROR(ycps("IWM","three_year_annualized_return"),"") | G58: =IFERROR(ycps("IWM","five_year_annualized_return"),"") | H58: =IFERROR(ycps("IWM","one_year_volatility"),"") | I58: =IFERROR(ycps("IWM","max_drawdown_3_year"),"") | J58: =IFERROR(ycps("IWM","beta_5_year"),"") | K58: =IFERROR(ycps("IWM","dividend_yield"),"") | L58: =IFERROR(ycps("IWM","forward_pe_ratio"),"") | M58: =IFERROR(ycps("IWM","one_month_return"),"") | N58: =IFERROR(ycps("IWM","three_month_return"),"") | O58: =IFERROR(ycps("IWM","six_month_return"),"") | P58: =IFERROR(ycps("IWM","one_year_return"),"") | V58: =IFERROR(IF(H58="","",IF(H58=0,0,(E58-$B$5)/H58)),"") | W58: =IFERROR(IF(V58="","",V58*1.3),"") | X58: =IFERROR(IF(H58="","",IF(H58=0,0,(E58-$B$6)/H58)),"") | Y58: =IFERROR(IF(OR(J58="",J58=0),"",((E58-$B$5)/J58)),"") | Z58: =IFERROR(IF(P58="",0,MIN(100,MAX(0,ROUND(50+P58*150+IF(E58>0,15,0)+IF(J58>0,5,-5),0)))),0) -> 0 | AA58: =IFERROR(IF(M58="",0,MIN(100,MAX(0,ROUND(50+M58*200+IF(AND(M58>0,N58>0),10,-5)+IF(H58<0.2,10,-5),0)))),0) -> 0 | AB58: =IFERROR(IF(OR(E58="",H58=""),0,MIN(100,MAX(0,ROUND(30+IF(H58>0,E58/H58,0)*40+IF(ABS(J58)<0.5,15,0)+IF(E58>0.08,10,0),0)))),0) -> 0 | AC58: =IFERROR(ROUND(Z58*$B$45+AA58*$B$46+AB58*$B$47+IF(Q58<>"",Q58,MIN(100,MAX(0,ROUND(50+(M58*0.4+N58*0.3+O58*0.2+P58*0.1)*200,0))))*$B$48,0),0) -> 0 | AD58: 0.04 | AE58: 0.04 | AF58: =AE58-AD58 -> 0 | AG58: =IF(ABS(AF58)>$B$9,"REBALANCE",IF(AND(AC58>=60,AF58<0),"ADD",IF(AND(AC58<40,AF58>0),"TRIM","HOLD"))) -> HOLD
A59: EFA | B59: Intl | C59: ETF | D59: =IFERROR(ycps("EFA","price"),"") | E59: =IFERROR(ycps("EFA","one_year_return"),"") | F59: =IFERROR(ycps("EFA","three_year_annualized_return"),"") | G59: =IFERROR(ycps("EFA","five_year_annualized_return"),"") | H59: =IFERROR(ycps("EFA","one_year_volatility"),"") | I59: =IFERROR(ycps("EFA","max_drawdown_3_year"),"") | J59: =IFERROR(ycps("EFA","beta_5_year"),"") | K59: =IFERROR(ycps("EFA","dividend_yield"),"") | L59: =IFERROR(ycps("EFA","forward_pe_ratio"),"") | M59: =IFERROR(ycps("EFA","one_month_return"),"") | N59: =IFERROR(ycps("EFA","three_month_return"),"") | O59: =IFERROR(ycps("EFA","six_month_return"),"") | P59: =IFERROR(ycps("EFA","one_year_return"),"") | V59: =IFERROR(IF(H59="","",IF(H59=0,0,(E59-$B$5)/H59)),"") | W59: =IFERROR(IF(V59="","",V59*1.3),"") | X59: =IFERROR(IF(H59="","",IF(H59=0,0,(E59-$B$6)/H59)),"") | Y59: =IFERROR(IF(OR(J59="",J59=0),"",((E59-$B$5)/J59)),"") | Z59: =IFERROR(IF(P59="",0,MIN(100,MAX(0,ROUND(50+P59*150+IF(E59>0,15,0)+IF(J59>0,5,-5),0)))),0) -> 0 | AA59: =IFERROR(IF(M59="",0,MIN(100,MAX(0,ROUND(50+M59*200+IF(AND(M59>0,N59>0),10,-5)+IF(H59<0.2,10,-5),0)))),0) -> 0 | AB59: =IFERROR(IF(OR(E59="",H59=""),0,MIN(100,MAX(0,ROUND(30+IF(H59>0,E59/H59,0)*40+IF(ABS(J59)<0.5,15,0)+IF(E59>0.08,10,0),0)))),0) -> 0 | AC59: =IFERROR(ROUND(Z59*$B$45+AA59*$B$46+AB59*$B$47+IF(Q59<>"",Q59,MIN(100,MAX(0,ROUND(50+(M59*0.4+N59*0.3+O59*0.2+P59*0.1)*200,0))))*$B$48,0),0) -> 0 | AD59: 0.05 | AE59: 0.06 | AF59: =AE59-AD59 -> 0.01 | AG59: =IF(ABS(AF59)>$B$9,"REBALANCE",IF(AND(AC59>=60,AF59<0),"ADD",IF(AND(AC59<40,AF59>0),"TRIM","HOLD"))) -> TRIM
A60: EEM | B60: Intl | C60: ETF | D60: =IFERROR(ycps("EEM","price"),"") | E60: =IFERROR(ycps("EEM","one_year_return"),"") | F60: =IFERROR(ycps("EEM","three_year_annualized_return"),"") | G60: =IFERROR(ycps("EEM","five_year_annualized_return"),"") | H60: =IFERROR(ycps("EEM","one_year_volatility"),"") | I60: =IFERROR(ycps("EEM","max_drawdown_3_year"),"") | J60: =IFERROR(ycps("EEM","beta_5_year"),"") | K60: =IFERROR(ycps("EEM","dividend_yield"),"") | L60: =IFERROR(ycps("EEM","forward_pe_ratio"),"") | M60: =IFERROR(ycps("EEM","one_month_return"),"") | N60: =IFERROR(ycps("EEM","three_month_return"),"") | O60: =IFERROR(ycps("EEM","six_month_return"),"") | P60: =IFERROR(ycps("EEM","one_year_return"),"") | V60: =IFERROR(IF(H60="","",IF(H60=0,0,(E60-$B$5)/H60)),"") | W60: =IFERROR(IF(V60="","",V60*1.3),"") | X60: =IFERROR(IF(H60="","",IF(H60=0,0,(E60-$B$6)/H60)),"") | Y60: =IFERROR(IF(OR(J60="",J60=0),"",((E60-$B$5)/J60)),"") | Z60: =IFERROR(IF(P60="",0,MIN(100,MAX(0,ROUND(50+P60*150+IF(E60>0,15,0)+IF(J60>0,5,-5),0)))),0) -> 0 | AA60: =IFERROR(IF(M60="",0,MIN(100,MAX(0,ROUND(50+M60*200+IF(AND(M60>0,N60>0),10,-5)+IF(H60<0.2,10,-5),0)))),0) -> 0 | AB60: =IFERROR(IF(OR(E60="",H60=""),0,MIN(100,MAX(0,ROUND(30+IF(H60>0,E60/H60,0)*40+IF(ABS(J60)<0.5,15,0)+IF(E60>0.08,10,0),0)))),0) -> 0 | AC60: =IFERROR(ROUND(Z60*$B$45+AA60*$B$46+AB60*$B$47+IF(Q60<>"",Q60,MIN(100,MAX(0,ROUND(50+(M60*0.4+N60*0.3+O60*0.2+P60*0.1)*200,0))))*$B$48,0),0) -> 0 | AD60: 0.03 | AE60: 0.025 | AF60: =AE60-AD60 -> -0.005 | AG60: =IF(ABS(AF60)>$B$9,"REBALANCE",IF(AND(AC60>=60,AF60<0),"ADD",IF(AND(AC60<40,AF60>0),"TRIM","HOLD"))) -> HOLD
A61: AGG | B61: Bond | C61: ETF | D61: =IFERROR(ycps("AGG","price"),"") | E61: =IFERROR(ycps("AGG","one_year_return"),"") | F61: =IFERROR(ycps("AGG","three_year_annualized_return"),"") | G61: =IFERROR(ycps("AGG","five_year_annualized_return"),"") | H61: =IFERROR(ycps("AGG","one_year_volatility"),"") | I61: =IFERROR(ycps("AGG","max_drawdown_3_year"),"") | J61: =IFERROR(ycps("AGG","beta_5_year"),"") | K61: =IFERROR(ycps("AGG","dividend_yield"),"") | L61: N/A | M61: =IFERROR(ycps("AGG","one_month_return"),"") | N61: =IFERROR(ycps("AGG","three_month_return"),"") | O61: =IFERROR(ycps("AGG","six_month_return"),"") | P61: =IFERROR(ycps("AGG","one_year_return"),"") | V61: =IFERROR(IF(H61="","",IF(H61=0,0,(E61-$B$5)/H61)),"") | W61: =IFERROR(IF(V61="","",V61*1.3),"") | X61: =IFERROR(IF(H61="","",IF(H61=0,0,(E61-$B$6)/H61)),"") | Y61: =IFERROR(IF(OR(J61="",J61=0),"",((E61-$B$5)/J61)),"") | Z61: =IFERROR(IF(P61="",0,MIN(100,MAX(0,ROUND(50+P61*150+IF(E61>0,15,0)+IF(J61>0,5,-5),0)))),0) -> 0 | AA61: =IFERROR(IF(M61="",0,MIN(100,MAX(0,ROUND(50+M61*200+IF(AND(M61>0,N61>0),10,-5)+IF(H61<0.2,10,-5),0)))),0) -> 0 | AB61: =IFERROR(IF(OR(E61="",H61=""),0,MIN(100,MAX(0,ROUND(30+IF(H61>0,E61/H61,0)*40+IF(ABS(J61)<0.5,15,0)+IF(E61>0.08,10,0),0)))),0) -> 0 | AC61: =IFERROR(ROUND(Z61*$B$45+AA61*$B$46+AB61*$B$47+IF(Q61<>"",Q61,MIN(100,MAX(0,ROUND(50+(M61*0.4+N61*0.3+O61*0.2+P61*0.1)*200,0))))*$B$48,0),0) -> 0 | AD61: 0.1 | AE61: 0.1 | AF61: =AE61-AD61 -> 0 | AG61: =IF(ABS(AF61)>$B$9,"REBALANCE",IF(AND(AC61>=60,AF61<0),"ADD",IF(AND(AC61<40,AF61>0),"TRIM","HOLD"))) -> HOLD
A62: TLT | B62: Bond | C62: ETF | D62: =IFERROR(ycps("TLT","price"),"") | E62: =IFERROR(ycps("TLT","one_year_return"),"") | F62: =IFERROR(ycps("TLT","three_year_annualized_return"),"") | G62: =IFERROR(ycps("TLT","five_year_annualized_return"),"") | H62: =IFERROR(ycps("TLT","one_year_volatility"),"") | I62: =IFERROR(ycps("TLT","max_drawdown_3_year"),"") | J62: =IFERROR(ycps("TLT","beta_5_year"),"") | K62: =IFERROR(ycps("TLT","dividend_yield"),"") | L62: N/A | M62: =IFERROR(ycps("TLT","one_month_return"),"") | N62: =IFERROR(ycps("TLT","three_month_return"),"") | O62: =IFERROR(ycps("TLT","six_month_return"),"") | P62: =IFERROR(ycps("TLT","one_year_return"),"") | V62: =IFERROR(IF(H62="","",IF(H62=0,0,(E62-$B$5)/H62)),"") | W62: =IFERROR(IF(V62="","",V62*1.3),"") | X62: =IFERROR(IF(H62="","",IF(H62=0,0,(E62-$B$6)/H62)),"") | Y62: =IFERROR(IF(OR(J62="",J62=0),"",((E62-$B$5)/J62)),"") | Z62: =IFERROR(IF(P62="",0,MIN(100,MAX(0,ROUND(50+P62*150+IF(E62>0,15,0)+IF(J62>0,5,-5),0)))),0) -> 0 | AA62: =IFERROR(IF(M62="",0,MIN(100,MAX(0,ROUND(50+M62*200+IF(AND(M62>0,N62>0),10,-5)+IF(H62<0.2,10,-5),0)))),0) -> 0 | AB62: =IFERROR(IF(OR(E62="",H62=""),0,MIN(100,MAX(0,ROUND(30+IF(H62>0,E62/H62,0)*40+IF(ABS(J62)<0.5,15,0)+IF(E62>0.08,10,0),0)))),0) -> 0 | AC62: =IFERROR(ROUND(Z62*$B$45+AA62*$B$46+AB62*$B$47+IF(Q62<>"",Q62,MIN(100,MAX(0,ROUND(50+(M62*0.4+N62*0.3+O62*0.2+P62*0.1)*200,0))))*$B$48,0),0) -> 0 | AD62: 0.05 | AE62: 0.06 | AF62: =AE62-AD62 -> 0.01 | AG62: =IF(ABS(AF62)>$B$9,"REBALANCE",IF(AND(AC62>=60,AF62<0),"ADD",IF(AND(AC62<40,AF62>0),"TRIM","HOLD"))) -> TRIM
A63: GLD | B63: Alt | C63: ETF | D63: =IFERROR(ycps("GLD","price"),"") | E63: =IFERROR(ycps("GLD","one_year_return"),"") | F63: =IFERROR(ycps("GLD","three_year_annualized_return"),"") | G63: =IFERROR(ycps("GLD","five_year_annualized_return"),"") | H63: =IFERROR(ycps("GLD","one_year_volatility"),"") | I63: =IFERROR(ycps("GLD","max_drawdown_3_year"),"") | J63: =IFERROR(ycps("GLD","beta_5_year"),"") | K63: =IFERROR(ycps("GLD","dividend_yield"),"") | L63: N/A | M63: =IFERROR(ycps("GLD","one_month_return"),"") | N63: =IFERROR(ycps("GLD","three_month_return"),"") | O63: =IFERROR(ycps("GLD","six_month_return"),"") | P63: =IFERROR(ycps("GLD","one_year_return"),"") | V63: =IFERROR(IF(H63="","",IF(H63=0,0,(E63-$B$5)/H63)),"") | W63: =IFERROR(IF(V63="","",V63*1.3),"") | X63: =IFERROR(IF(H63="","",IF(H63=0,0,(E63-$B$6)/H63)),"") | Y63: =IFERROR(IF(OR(J63="",J63=0),"",((E63-$B$5)/J63)),"") | Z63: =IFERROR(IF(P63="",0,MIN(100,MAX(0,ROUND(50+P63*150+IF(E63>0,15,0)+IF(J63>0,5,-5),0)))),0) -> 0 | AA63: =IFERROR(IF(M63="",0,MIN(100,MAX(0,ROUND(50+M63*200+IF(AND(M63>0,N63>0),10,-5)+IF(H63<0.2,10,-5),0)))),0) -> 0 | AB63: =IFERROR(IF(OR(E63="",H63=""),0,MIN(100,MAX(0,ROUND(30+IF(H63>0,E63/H63,0)*40+IF(ABS(J63)<0.5,15,0)+IF(E63>0.08,10,0),0)))),0) -> 0 | AC63: =IFERROR(ROUND(Z63*$B$45+AA63*$B$46+AB63*$B$47+IF(Q63<>"",Q63,MIN(100,MAX(0,ROUND(50+(M63*0.4+N63*0.3+O63*0.2+P63*0.1)*200,0))))*$B$48,0),0) -> 0 | AD63: 0.08 | AE63: 0.075 | AF63: =AE63-AD63 -> -0.005 | AG63: =IF(ABS(AF63)>$B$9,"REBALANCE",IF(AND(AC63>=60,AF63<0),"ADD",IF(AND(AC63<40,AF63>0),"TRIM","HOLD"))) -> HOLD
A64: VNQ | B64: REIT | C64: ETF | D64: =IFERROR(ycps("VNQ","price"),"") | E64: =IFERROR(ycps("VNQ","one_year_return"),"") | F64: =IFERROR(ycps("VNQ","three_year_annualized_return"),"") | G64: =IFERROR(ycps("VNQ","five_year_annualized_return"),"") | H64: =IFERROR(ycps("VNQ","one_year_volatility"),"") | I64: =IFERROR(ycps("VNQ","max_drawdown_3_year"),"") | J64: =IFERROR(ycps("VNQ","beta_5_year"),"") | K64: =IFERROR(ycps("VNQ","dividend_yield"),"") | L64: =IFERROR(ycps("VNQ","forward_pe_ratio"),"") | M64: =IFERROR(ycps("VNQ","one_month_return"),"") | N64: =IFERROR(ycps("VNQ","three_month_return"),"") | O64: =IFERROR(ycps("VNQ","six_month_return"),"") | P64: =IFERROR(ycps("VNQ","one_year_return"),"") | V64: =IFERROR(IF(H64="","",IF(H64=0,0,(E64-$B$5)/H64)),"") | W64: =IFERROR(IF(V64="","",V64*1.3),"") | X64: =IFERROR(IF(H64="","",IF(H64=0,0,(E64-$B$6)/H64)),"") | Y64: =IFERROR(IF(OR(J64="",J64=0),"",((E64-$B$5)/J64)),"") | Z64: =IFERROR(IF(P64="",0,MIN(100,MAX(0,ROUND(50+P64*150+IF(E64>0,15,0)+IF(J64>0,5,-5),0)))),0) -> 0 | AA64: =IFERROR(IF(M64="",0,MIN(100,MAX(0,ROUND(50+M64*200+IF(AND(M64>0,N64>0),10,-5)+IF(H64<0.2,10,-5),0)))),0) -> 0 | AB64: =IFERROR(IF(OR(E64="",H64=""),0,MIN(100,MAX(0,ROUND(30+IF(H64>0,E64/H64,0)*40+IF(ABS(J64)<0.5,15,0)+IF(E64>0.08,10,0),0)))),0) -> 0 | AC64: =IFERROR(ROUND(Z64*$B$45+AA64*$B$46+AB64*$B$47+IF(Q64<>"",Q64,MIN(100,MAX(0,ROUND(50+(M64*0.4+N64*0.3+O64*0.2+P64*0.1)*200,0))))*$B$48,0),0) -> 0 | AD64: 0.05 | AE64: 0.05 | AF64: =AE64-AD64 -> 0 | AG64: =IF(ABS(AF64)>$B$9,"REBALANCE",IF(AND(AC64>=60,AF64<0),"ADD",IF(AND(AC64<40,AF64>0),"TRIM","HOLD"))) -> HOLD
A65: XLK | B65: US Eq | C65: ETF | D65: =IFERROR(ycps("XLK","price"),"") | E65: =IFERROR(ycps("XLK","one_year_return"),"") | F65: =IFERROR(ycps("XLK","three_year_annualized_return"),"") | G65: =IFERROR(ycps("XLK","five_year_annualized_return"),"") | H65: =IFERROR(ycps("XLK","one_year_volatility"),"") | I65: =IFERROR(ycps("XLK","max_drawdown_3_year"),"") | J65: =IFERROR(ycps("XLK","beta_5_year"),"") | K65: =IFERROR(ycps("XLK","dividend_yield"),"") | L65: =IFERROR(ycps("XLK","forward_pe_ratio"),"") | M65: =IFERROR(ycps("XLK","one_month_return"),"") | N65: =IFERROR(ycps("XLK","three_month_return"),"") | O65: =IFERROR(ycps("XLK","six_month_return"),"") | P65: =IFERROR(ycps("XLK","one_year_return"),"") | V65: =IFERROR(IF(H65="","",IF(H65=0,0,(E65-$B$5)/H65)),"") | W65: =IFERROR(IF(V65="","",V65*1.3),"") | X65: =IFERROR(IF(H65="","",IF(H65=0,0,(E65-$B$6)/H65)),"") | Y65: =IFERROR(IF(OR(J65="",J65=0),"",((E65-$B$5)/J65)),"") | Z65: =IFERROR(IF(P65="",0,MIN(100,MAX(0,ROUND(50+P65*150+IF(E65>0,15,0)+IF(J65>0,5,-5),0)))),0) -> 0 | AA65: =IFERROR(IF(M65="",0,MIN(100,MAX(0,ROUND(50+M65*200+IF(AND(M65>0,N65>0),10,-5)+IF(H65<0.2,10,-5),0)))),0) -> 0 | AB65: =IFERROR(IF(OR(E65="",H65=""),0,MIN(100,MAX(0,ROUND(30+IF(H65>0,E65/H65,0)*40+IF(ABS(J65)<0.5,15,0)+IF(E65>0.08,10,0),0)))),0) -> 0 | AC65: =IFERROR(ROUND(Z65*$B$45+AA65*$B$46+AB65*$B$47+IF(Q65<>"",Q65,MIN(100,MAX(0,ROUND(50+(M65*0.4+N65*0.3+O65*0.2+P65*0.1)*200,0))))*$B$48,0),0) -> 0 | AD65: 0.08 | AE65: 0.09 | AF65: =AE65-AD65 -> 0.01 | AG65: =IF(ABS(AF65)>$B$9,"REBALANCE",IF(AND(AC65>=60,AF65<0),"ADD",IF(AND(AC65<40,AF65>0),"TRIM","HOLD"))) -> TRIM
A66: XLV | B66: US Eq | C66: ETF | D66: =IFERROR(ycps("XLV","price"),"") | E66: =IFERROR(ycps("XLV","one_year_return"),"") | F66: =IFERROR(ycps("XLV","three_year_annualized_return"),"") | G66: =IFERROR(ycps("XLV","five_year_annualized_return"),"") | H66: =IFERROR(ycps("XLV","one_year_volatility"),"") | I66: =IFERROR(ycps("XLV","max_drawdown_3_year"),"") | J66: =IFERROR(ycps("XLV","beta_5_year"),"") | K66: =IFERROR(ycps("XLV","dividend_yield"),"") | L66: =IFERROR(ycps("XLV","forward_pe_ratio"),"") | M66: =IFERROR(ycps("XLV","one_month_return"),"") | N66: =IFERROR(ycps("XLV","three_month_return"),"") | O66: =IFERROR(ycps("XLV","six_month_return"),"") | P66: =IFERROR(ycps("XLV","one_year_return"),"") | V66: =IFERROR(IF(H66="","",IF(H66=0,0,(E66-$B$5)/H66)),"") | W66: =IFERROR(IF(V66="","",V66*1.3),"") | X66: =IFERROR(IF(H66="","",IF(H66=0,0,(E66-$B$6)/H66)),"") | Y66: =IFERROR(IF(OR(J66="",J66=0),"",((E66-$B$5)/J66)),"") | Z66: =IFERROR(IF(P66="",0,MIN(100,MAX(0,ROUND(50+P66*150+IF(E66>0,15,0)+IF(J66>0,5,-5),0)))),0) -> 0 | AA66: =IFERROR(IF(M66="",0,MIN(100,MAX(0,ROUND(50+M66*200+IF(AND(M66>0,N66>0),10,-5)+IF(H66<0.2,10,-5),0)))),0) -> 0 | AB66: =IFERROR(IF(OR(E66="",H66=""),0,MIN(100,MAX(0,ROUND(30+IF(H66>0,E66/H66,0)*40+IF(ABS(J66)<0.5,15,0)+IF(E66>0.08,10,0),0)))),0) -> 0 | AC66: =IFERROR(ROUND(Z66*$B$45+AA66*$B$46+AB66*$B$47+IF(Q66<>"",Q66,MIN(100,MAX(0,ROUND(50+(M66*0.4+N66*0.3+O66*0.2+P66*0.1)*200,0))))*$B$48,0),0) -> 0 | AD66: 0.04 | AE66: 0.035 | AF66: =AE66-AD66 -> -0.005 | AG66: =IF(ABS(AF66)>$B$9,"REBALANCE",IF(AND(AC66>=60,AF66<0),"ADD",IF(AND(AC66<40,AF66>0),"TRIM","HOLD"))) -> HOLD
A67: XLE | B67: US Eq | C67: ETF | D67: =IFERROR(ycps("XLE","price"),"") | E67: =IFERROR(ycps("XLE","one_year_return"),"") | F67: =IFERROR(ycps("XLE","three_year_annualized_return"),"") | G67: =IFERROR(ycps("XLE","five_year_annualized_return"),"") | H67: =IFERROR(ycps("XLE","one_year_volatility"),"") | I67: =IFERROR(ycps("XLE","max_drawdown_3_year"),"") | J67: =IFERROR(ycps("XLE","beta_5_year"),"") | K67: =IFERROR(ycps("XLE","dividend_yield"),"") | L67: =IFERROR(ycps("XLE","forward_pe_ratio"),"") | M67: =IFERROR(ycps("XLE","one_month_return"),"") | N67: =IFERROR(ycps("XLE","three_month_return"),"") | O67: =IFERROR(ycps("XLE","six_month_return"),"") | P67: =IFERROR(ycps("XLE","one_year_return"),"") | V67: =IFERROR(IF(H67="","",IF(H67=0,0,(E67-$B$5)/H67)),"") | W67: =IFERROR(IF(V67="","",V67*1.3),"") | X67: =IFERROR(IF(H67="","",IF(H67=0,0,(E67-$B$6)/H67)),"") | Y67: =IFERROR(IF(OR(J67="",J67=0),"",((E67-$B$5)/J67)),"") | Z67: =IFERROR(IF(P67="",0,MIN(100,MAX(0,ROUND(50+P67*150+IF(E67>0,15,0)+IF(J67>0,5,-5),0)))),0) -> 0 | AA67: =IFERROR(IF(M67="",0,MIN(100,MAX(0,ROUND(50+M67*200+IF(AND(M67>0,N67>0),10,-5)+IF(H67<0.2,10,-5),0)))),0) -> 0 | AB67: =IFERROR(IF(OR(E67="",H67=""),0,MIN(100,MAX(0,ROUND(30+IF(H67>0,E67/H67,0)*40+IF(ABS(J67)<0.5,15,0)+IF(E67>0.08,10,0),0)))),0) -> 0 | AC67: =IFERROR(ROUND(Z67*$B$45+AA67*$B$46+AB67*$B$47+IF(Q67<>"",Q67,MIN(100,MAX(0,ROUND(50+(M67*0.4+N67*0.3+O67*0.2+P67*0.1)*200,0))))*$B$48,0),0) -> 0 | AD67: 0.03 | AE67: 0.03 | AF67: =AE67-AD67 -> 0 | AG67: =IF(ABS(AF67)>$B$9,"REBALANCE",IF(AND(AC67>=60,AF67<0),"ADD",IF(AND(AC67<40,AF67>0),"TRIM","HOLD"))) -> HOLD
A68: XLF | B68: US Eq | C68: ETF | D68: =IFERROR(ycps("XLF","price"),"") | E68: =IFERROR(ycps("XLF","one_year_return"),"") | F68: =IFERROR(ycps("XLF","three_year_annualized_return"),"") | G68: =IFERROR(ycps("XLF","five_year_annualized_return"),"") | H68: =IFERROR(ycps("XLF","one_year_volatility"),"") | I68: =IFERROR(ycps("XLF","max_drawdown_3_year"),"") | J68: =IFERROR(ycps("XLF","beta_5_year"),"") | K68: =IFERROR(ycps("XLF","dividend_yield"),"") | L68: =IFERROR(ycps("XLF","forward_pe_ratio"),"") | M68: =IFERROR(ycps("XLF","one_month_return"),"") | N68: =IFERROR(ycps("XLF","three_month_return"),"") | O68: =IFERROR(ycps("XLF","six_month_return"),"") | P68: =IFERROR(ycps("XLF","one_year_return"),"") | V68: =IFERROR(IF(H68="","",IF(H68=0,0,(E68-$B$5)/H68)),"") | W68: =IFERROR(IF(V68="","",V68*1.3),"") | X68: =IFERROR(IF(H68="","",IF(H68=0,0,(E68-$B$6)/H68)),"") | Y68: =IFERROR(IF(OR(J68="",J68=0),"",((E68-$B$5)/J68)),"") | Z68: =IFERROR(IF(P68="",0,MIN(100,MAX(0,ROUND(50+P68*150+IF(E68>0,15,0)+IF(J68>0,5,-5),0)))),0) -> 0 | AA68: =IFERROR(IF(M68="",0,MIN(100,MAX(0,ROUND(50+M68*200+IF(AND(M68>0,N68>0),10,-5)+IF(H68<0.2,10,-5),0)))),0) -> 0 | AB68: =IFERROR(IF(OR(E68="",H68=""),0,MIN(100,MAX(0,ROUND(30+IF(H68>0,E68/H68,0)*40+IF(ABS(J68)<0.5,15,0)+IF(E68>0.08,10,0),0)))),0) -> 0 | AC68: =IFERROR(ROUND(Z68*$B$45+AA68*$B$46+AB68*$B$47+IF(Q68<>"",Q68,MIN(100,MAX(0,ROUND(50+(M68*0.4+N68*0.3+O68*0.2+P68*0.1)*200,0))))*$B$48,0),0) -> 0 | AD68: 0.04 | AE68: 0.05 | AF68: =AE68-AD68 -> 0.01 | AG68: =IF(ABS(AF68)>$B$9,"REBALANCE",IF(AND(AC68>=60,AF68<0),"ADD",IF(AND(AC68<40,AF68>0),"TRIM","HOLD"))) -> TRIM
A69: DBMF | B69: MF | C69: ETF | D69: =IFERROR(ycps("DBMF","price"),"") | E69: =IFERROR(ycps("DBMF","one_year_return"),"") | F69: =IFERROR(ycps("DBMF","three_year_annualized_return"),"") | G69: =IFERROR(ycps("DBMF","five_year_annualized_return"),"") | H69: =IFERROR(ycps("DBMF","one_year_volatility"),"") | I69: =IFERROR(ycps("DBMF","max_drawdown_3_year"),"") | J69: =IFERROR(ycps("DBMF","beta_5_year"),"") | K69: =IFERROR(ycps("DBMF","dividend_yield"),"") | L69: N/A | M69: =IFERROR(ycps("DBMF","one_month_return"),"") | N69: =IFERROR(ycps("DBMF","three_month_return"),"") | O69: =IFERROR(ycps("DBMF","six_month_return"),"") | P69: =IFERROR(ycps("DBMF","one_year_return"),"") | V69: =IFERROR(IF(H69="","",IF(H69=0,0,(E69-$B$5)/H69)),"") | W69: =IFERROR(IF(V69="","",V69*1.3),"") | X69: =IFERROR(IF(H69="","",IF(H69=0,0,(E69-$B$6)/H69)),"") | Y69: =IFERROR(IF(OR(J69="",J69=0),"",((E69-$B$5)/J69)),"") | Z69: =IFERROR(IF(P69="",0,MIN(100,MAX(0,ROUND(50+P69*150+IF(E69>0,15,0)+IF(J69>0,5,-5),0)))),0) -> 0 | AA69: =IFERROR(IF(M69="",0,MIN(100,MAX(0,ROUND(50+M69*200+IF(AND(M69>0,N69>0),10,-5)+IF(H69<0.2,10,-5),0)))),0) -> 0 | AB69: =IFERROR(IF(OR(E69="",H69=""),0,MIN(100,MAX(0,ROUND(30+IF(H69>0,E69/H69,0)*40+IF(ABS(J69)<0.5,15,0)+IF(E69>0.08,10,0),0)))),0) -> 0 | AC69: =IFERROR(ROUND(Z69*$B$45+AA69*$B$46+AB69*$B$47+IF(Q69<>"",Q69,MIN(100,MAX(0,ROUND(50+(M69*0.4+N69*0.3+O69*0.2+P69*0.1)*200,0))))*$B$48,0),0) -> 0 | AD69: 0.06 | AE69: 0.055 | AF69: =AE69-AD69 -> -0.005 | AG69: =IF(ABS(AF69)>$B$9,"REBALANCE",IF(AND(AC69>=60,AF69<0),"ADD",IF(AND(AC69<40,AF69>0),"TRIM","HOLD"))) -> HOLD
A70: CTA | B70: MF | C70: ETF | D70: =IFERROR(ycps("CTA","price"),"") | E70: =IFERROR(ycps("CTA","one_year_return"),"") | F70: =IFERROR(ycps("CTA","three_year_annualized_return"),"") | G70: =IFERROR(ycps("CTA","five_year_annualized_return"),"") | H70: =IFERROR(ycps("CTA","one_year_volatility"),"") | I70: =IFERROR(ycps("CTA","max_drawdown_3_year"),"") | J70: =IFERROR(ycps("CTA","beta_5_year"),"") | K70: =IFERROR(ycps("CTA","dividend_yield"),"") | L70: N/A | M70: =IFERROR(ycps("CTA","one_month_return"),"") | N70: =IFERROR(ycps("CTA","three_month_return"),"") | O70: =IFERROR(ycps("CTA","six_month_return"),"") | P70: =IFERROR(ycps("CTA","one_year_return"),"") | V70: =IFERROR(IF(H70="","",IF(H70=0,0,(E70-$B$5)/H70)),"") | W70: =IFERROR(IF(V70="","",V70*1.3),"") | X70: =IFERROR(IF(H70="","",IF(H70=0,0,(E70-$B$6)/H70)),"") | Y70: =IFERROR(IF(OR(J70="",J70=0),"",((E70-$B$5)/J70)),"") | Z70: =IFERROR(IF(P70="",0,MIN(100,MAX(0,ROUND(50+P70*150+IF(E70>0,15,0)+IF(J70>0,5,-5),0)))),0) -> 0 | AA70: =IFERROR(IF(M70="",0,MIN(100,MAX(0,ROUND(50+M70*200+IF(AND(M70>0,N70>0),10,-5)+IF(H70<0.2,10,-5),0)))),0) -> 0 | AB70: =IFERROR(IF(OR(E70="",H70=""),0,MIN(100,MAX(0,ROUND(30+IF(H70>0,E70/H70,0)*40+IF(ABS(J70)<0.5,15,0)+IF(E70>0.08,10,0),0)))),0) -> 0 | AC70: =IFERROR(ROUND(Z70*$B$45+AA70*$B$46+AB70*$B$47+IF(Q70<>"",Q70,MIN(100,MAX(0,ROUND(50+(M70*0.4+N70*0.3+O70*0.2+P70*0.1)*200,0))))*$B$48,0),0) -> 0 | AD70: 0.04 | AE70: 0.04 | AF70: =AE70-AD70 -> 0 | AG70: =IF(ABS(AF70)>$B$9,"REBALANCE",IF(AND(AC70>=60,AF70<0),"ADD",IF(AND(AC70<40,AF70>0),"TRIM","HOLD"))) -> HOLD
A71: KMLM | B71: MF | C71: ETF | D71: =IFERROR(ycps("KMLM","price"),"") | E71: =IFERROR(ycps("KMLM","one_year_return"),"") | F71: =IFERROR(ycps("KMLM","three_year_annualized_return"),"") | G71: =IFERROR(ycps("KMLM","five_year_annualized_return"),"") | H71: =IFERROR(ycps("KMLM","one_year_volatility"),"") | I71: =IFERROR(ycps("KMLM","max_drawdown_3_year"),"") | J71: =IFERROR(ycps("KMLM","beta_5_year"),"") | K71: =IFERROR(ycps("KMLM","dividend_yield"),"") | L71: N/A | M71: =IFERROR(ycps("KMLM","one_month_return"),"") | N71: =IFERROR(ycps("KMLM","three_month_return"),"") | O71: =IFERROR(ycps("KMLM","six_month_return"),"") | P71: =IFERROR(ycps("KMLM","one_year_return"),"") | V71: =IFERROR(IF(H71="","",IF(H71=0,0,(E71-$B$5)/H71)),"") | W71: =IFERROR(IF(V71="","",V71*1.3),"") | X71: =IFERROR(IF(H71="","",IF(H71=0,0,(E71-$B$6)/H71)),"") | Y71: =IFERROR(IF(OR(J71="",J71=0),"",((E71-$B$5)/J71)),"") | Z71: =IFERROR(IF(P71="",0,MIN(100,MAX(0,ROUND(50+P71*150+IF(E71>0,15,0)+IF(J71>0,5,-5),0)))),0) -> 0 | AA71: =IFERROR(IF(M71="",0,MIN(100,MAX(0,ROUND(50+M71*200+IF(AND(M71>0,N71>0),10,-5)+IF(H71<0.2,10,-5),0)))),0) -> 0 | AB71: =IFERROR(IF(OR(E71="",H71=""),0,MIN(100,MAX(0,ROUND(30+IF(H71>0,E71/H71,0)*40+IF(ABS(J71)<0.5,15,0)+IF(E71>0.08,10,0),0)))),0) -> 0 | AC71: =IFERROR(ROUND(Z71*$B$45+AA71*$B$46+AB71*$B$47+IF(Q71<>"",Q71,MIN(100,MAX(0,ROUND(50+(M71*0.4+N71*0.3+O71*0.2+P71*0.1)*200,0))))*$B$48,0),0) -> 0 | AD71: 0.04 | AE71: 0.05 | AF71: =AE71-AD71 -> 0.01 | AG71: =IF(ABS(AF71)>$B$9,"REBALANCE",IF(AND(AC71>=60,AF71<0),"ADD",IF(AND(AC71<40,AF71>0),"TRIM","HOLD"))) -> TRIM
A72: BTAL | B72: Hedge | C72: ETF | D72: =IFERROR(ycps("BTAL","price"),"") | E72: =IFERROR(ycps("BTAL","one_year_return"),"") | F72: =IFERROR(ycps("BTAL","three_year_annualized_return"),"") | G72: =IFERROR(ycps("BTAL","five_year_annualized_return"),"") | H72: =IFERROR(ycps("BTAL","one_year_volatility"),"") | I72: =IFERROR(ycps("BTAL","max_drawdown_3_year"),"") | J72: =IFERROR(ycps("BTAL","beta_5_year"),"") | K72: =IFERROR(ycps("BTAL","dividend_yield"),"") | L72: N/A | M72: =IFERROR(ycps("BTAL","one_month_return"),"") | N72: =IFERROR(ycps("BTAL","three_month_return"),"") | O72: =IFERROR(ycps("BTAL","six_month_return"),"") | P72: =IFERROR(ycps("BTAL","one_year_return"),"") | V72: =IFERROR(IF(H72="","",IF(H72=0,0,(E72-$B$5)/H72)),"") | W72: =IFERROR(IF(V72="","",V72*1.3),"") | X72: =IFERROR(IF(H72="","",IF(H72=0,0,(E72-$B$6)/H72)),"") | Y72: =IFERROR(IF(OR(J72="",J72=0),"",((E72-$B$5)/J72)),"") | Z72: =IFERROR(IF(P72="",0,MIN(100,MAX(0,ROUND(50+P72*150+IF(E72>0,15,0)+IF(J72>0,5,-5),0)))),0) -> 0 | AA72: =IFERROR(IF(M72="",0,MIN(100,MAX(0,ROUND(50+M72*200+IF(AND(M72>0,N72>0),10,-5)+IF(H72<0.2,10,-5),0)))),0) -> 0 | AB72: =IFERROR(IF(OR(E72="",H72=""),0,MIN(100,MAX(0,ROUND(30+IF(H72>0,E72/H72,0)*40+IF(ABS(J72)<0.5,15,0)+IF(E72>0.08,10,0),0)))),0) -> 0 | AC72: =IFERROR(ROUND(Z72*$B$45+AA72*$B$46+AB72*$B$47+IF(Q72<>"",Q72,MIN(100,MAX(0,ROUND(50+(M72*0.4+N72*0.3+O72*0.2+P72*0.1)*200,0))))*$B$48,0),0) -> 0 | AD72: 0.03 | AE72: 0.025 | AF72: =AE72-AD72 -> -0.005 | AG72: =IF(ABS(AF72)>$B$9,"REBALANCE",IF(AND(AC72>=60,AF72<0),"ADD",IF(AND(AC72<40,AF72>0),"TRIM","HOLD"))) -> HOLD
A73: TAIL | B73: Hedge | C73: ETF | D73: =IFERROR(ycps("TAIL","price"),"") | E73: =IFERROR(ycps("TAIL","one_year_return"),"") | F73: =IFERROR(ycps("TAIL","three_year_annualized_return"),"") | G73: =IFERROR(ycps("TAIL","five_year_annualized_return"),"") | H73: =IFERROR(ycps("TAIL","one_year_volatility"),"") | I73: =IFERROR(ycps("TAIL","max_drawdown_3_year"),"") | J73: =IFERROR(ycps("TAIL","beta_5_year"),"") | K73: =IFERROR(ycps("TAIL","dividend_yield"),"") | L73: N/A | M73: =IFERROR(ycps("TAIL","one_month_return"),"") | N73: =IFERROR(ycps("TAIL","three_month_return"),"") | O73: =IFERROR(ycps("TAIL","six_month_return"),"") | P73: =IFERROR(ycps("TAIL","one_year_return"),"") | V73: =IFERROR(IF(H73="","",IF(H73=0,0,(E73-$B$5)/H73)),"") | W73: =IFERROR(IF(V73="","",V73*1.3),"") | X73: =IFERROR(IF(H73="","",IF(H73=0,0,(E73-$B$6)/H73)),"") | Y73: =IFERROR(IF(OR(J73="",J73=0),"",((E73-$B$5)/J73)),"") | Z73: =IFERROR(IF(P73="",0,MIN(100,MAX(0,ROUND(50+P73*150+IF(E73>0,15,0)+IF(J73>0,5,-5),0)))),0) -> 0 | AA73: =IFERROR(IF(M73="",0,MIN(100,MAX(0,ROUND(50+M73*200+IF(AND(M73>0,N73>0),10,-5)+IF(H73<0.2,10,-5),0)))),0) -> 0 | AB73: =IFERROR(IF(OR(E73="",H73=""),0,MIN(100,MAX(0,ROUND(30+IF(H73>0,E73/H73,0)*40+IF(ABS(J73)<0.5,15,0)+IF(E73>0.08,10,0),0)))),0) -> 0 | AC73: =IFERROR(ROUND(Z73*$B$45+AA73*$B$46+AB73*$B$47+IF(Q73<>"",Q73,MIN(100,MAX(0,ROUND(50+(M73*0.4+N73*0.3+O73*0.2+P73*0.1)*200,0))))*$B$48,0),0) -> 0 | AD73: 0.02 | AE73: 0.02 | AF73: =AE73-AD73 -> 0 | AG73: =IF(ABS(AF73)>$B$9,"REBALANCE",IF(AND(AC73>=60,AF73<0),"ADD",IF(AND(AC73<40,AF73>0),"TRIM","HOLD"))) -> HOLD
A74: AAPL | B74: US Eq | C74: Stock | D74: =IFERROR(ycps("AAPL","price"),"") | E74: =IFERROR(ycps("AAPL","one_year_return"),"") | F74: =IFERROR(ycps("AAPL","three_year_annualized_return"),"") | G74: =IFERROR(ycps("AAPL","five_year_annualized_return"),"") | H74: =IFERROR(ycps("AAPL","one_year_volatility"),"") | I74: =IFERROR(ycps("AAPL","max_drawdown_3_year"),"") | J74: =IFERROR(ycps("AAPL","beta_5_year"),"") | K74: =IFERROR(ycps("AAPL","dividend_yield"),"") | L74: =IFERROR(ycps("AAPL","forward_pe_ratio"),"") | M74: =IFERROR(ycps("AAPL","one_month_return"),"") | N74: =IFERROR(ycps("AAPL","three_month_return"),"") | O74: =IFERROR(ycps("AAPL","six_month_return"),"") | P74: =IFERROR(ycps("AAPL","one_year_return"),"") | V74: =IFERROR(IF(H74="","",IF(H74=0,0,(E74-$B$5)/H74)),"") | W74: =IFERROR(IF(V74="","",V74*1.3),"") | X74: =IFERROR(IF(H74="","",IF(H74=0,0,(E74-$B$6)/H74)),"") | Y74: =IFERROR(IF(OR(J74="",J74=0),"",((E74-$B$5)/J74)),"") | Z74: =IFERROR(IF(P74="",0,MIN(100,MAX(0,ROUND(50+P74*150+IF(E74>0,15,0)+IF(J74>0,5,-5),0)))),0) -> 0 | AA74: =IFERROR(IF(M74="",0,MIN(100,MAX(0,ROUND(50+M74*200+IF(AND(M74>0,N74>0),10,-5)+IF(H74<0.2,10,-5),0)))),0) -> 0 | AB74: =IFERROR(IF(OR(E74="",H74=""),0,MIN(100,MAX(0,ROUND(30+IF(H74>0,E74/H74,0)*40+IF(ABS(J74)<0.5,15,0)+IF(E74>0.08,10,0),0)))),0) -> 0 | AC74: =IFERROR(ROUND(Z74*$B$45+AA74*$B$46+AB74*$B$47+IF(Q74<>"",Q74,MIN(100,MAX(0,ROUND(50+(M74*0.4+N74*0.3+O74*0.2+P74*0.1)*200,0))))*$B$48,0),0) -> 0 | AD74: 0.02 | AE74: 0.03 | AF74: =AE74-AD74 -> 0.01 | AG74: =IF(ABS(AF74)>$B$9,"REBALANCE",IF(AND(AC74>=60,AF74<0),"ADD",IF(AND(AC74<40,AF74>0),"TRIM","HOLD"))) -> TRIM
A75: MSFT | B75: US Eq | C75: Stock | D75: =IFERROR(ycps("MSFT","price"),"") | E75: =IFERROR(ycps("MSFT","one_year_return"),"") | F75: =IFERROR(ycps("MSFT","three_year_annualized_return"),"") | G75: =IFERROR(ycps("MSFT","five_year_annualized_return"),"") | H75: =IFERROR(ycps("MSFT","one_year_volatility"),"") | I75: =IFERROR(ycps("MSFT","max_drawdown_3_year"),"") | J75: =IFERROR(ycps("MSFT","beta_5_year"),"") | K75: =IFERROR(ycps("MSFT","dividend_yield"),"") | L75: =IFERROR(ycps("MSFT","forward_pe_ratio"),"") | M75: =IFERROR(ycps("MSFT","one_month_return"),"") | N75: =IFERROR(ycps("MSFT","three_month_return"),"") | O75: =IFERROR(ycps("MSFT","six_month_return"),"") | P75: =IFERROR(ycps("MSFT","one_year_return"),"") | V75: =IFERROR(IF(H75="","",IF(H75=0,0,(E75-$B$5)/H75)),"") | W75: =IFERROR(IF(V75="","",V75*1.3),"") | X75: =IFERROR(IF(H75="","",IF(H75=0,0,(E75-$B$6)/H75)),"") | Y75: =IFERROR(IF(OR(J75="",J75=0),"",((E75-$B$5)/J75)),"") | Z75: =IFERROR(IF(P75="",0,MIN(100,MAX(0,ROUND(50+P75*150+IF(E75>0,15,0)+IF(J75>0,5,-5),0)))),0) -> 0 | AA75: =IFERROR(IF(M75="",0,MIN(100,MAX(0,ROUND(50+M75*200+IF(AND(M75>0,N75>0),10,-5)+IF(H75<0.2,10,-5),0)))),0) -> 0 | AB75: =IFERROR(IF(OR(E75="",H75=""),0,MIN(100,MAX(0,ROUND(30+IF(H75>0,E75/H75,0)*40+IF(ABS(J75)<0.5,15,0)+IF(E75>0.08,10,0),0)))),0) -> 0 | AC75: =IFERROR(ROUND(Z75*$B$45+AA75*$B$46+AB75*$B$47+IF(Q75<>"",Q75,MIN(100,MAX(0,ROUND(50+(M75*0.4+N75*0.3+O75*0.2+P75*0.1)*200,0))))*$B$48,0),0) -> 0 | AD75: 0.02 | AE75: 0.015 | AF75: =AE75-AD75 -> -0.005 | AG75: =IF(ABS(AF75)>$B$9,"REBALANCE",IF(AND(AC75>=60,AF75<0),"ADD",IF(AND(AC75<40,AF75>0),"TRIM","HOLD"))) -> HOLD
A76: NVDA | B76: US Eq | C76: Stock | D76: =IFERROR(ycps("NVDA","price"),"") | E76: =IFERROR(ycps("NVDA","one_year_return"),"") | F76: =IFERROR(ycps("NVDA","three_year_annualized_return"),"") | G76: =IFERROR(ycps("NVDA","five_year_annualized_return"),"") | H76: =IFERROR(ycps("NVDA","one_year_volatility"),"") | I76: =IFERROR(ycps("NVDA","max_drawdown_3_year"),"") | J76: =IFERROR(ycps("NVDA","beta_5_year"),"") | K76: =IFERROR(ycps("NVDA","dividend_yield"),"") | L76: =IFERROR(ycps("NVDA","forward_pe_ratio"),"") | M76: =IFERROR(ycps("NVDA","one_month_return"),"") | N76: =IFERROR(ycps("NVDA","three_month_return"),"") | O76: =IFERROR(ycps("NVDA","six_month_return"),"") | P76: =IFERROR(ycps("NVDA","one_year_return"),"") | V76: =IFERROR(IF(H76="","",IF(H76=0,0,(E76-$B$5)/H76)),"") | W76: =IFERROR(IF(V76="","",V76*1.3),"") | X76: =IFERROR(IF(H76="","",IF(H76=0,0,(E76-$B$6)/H76)),"") | Y76: =IFERROR(IF(OR(J76="",J76=0),"",((E76-$B$5)/J76)),"") | Z76: =IFERROR(IF(P76="",0,MIN(100,MAX(0,ROUND(50+P76*150+IF(E76>0,15,0)+IF(J76>0,5,-5),0)))),0) -> 0 | AA76: =IFERROR(IF(M76="",0,MIN(100,MAX(0,ROUND(50+M76*200+IF(AND(M76>0,N76>0),10,-5)+IF(H76<0.2,10,-5),0)))),0) -> 0 | AB76: =IFERROR(IF(OR(E76="",H76=""),0,MIN(100,MAX(0,ROUND(30+IF(H76>0,E76/H76,0)*40+IF(ABS(J76)<0.5,15,0)+IF(E76>0.08,10,0),0)))),0) -> 0 | AC76: =IFERROR(ROUND(Z76*$B$45+AA76*$B$46+AB76*$B$47+IF(Q76<>"",Q76,MIN(100,MAX(0,ROUND(50+(M76*0.4+N76*0.3+O76*0.2+P76*0.1)*200,0))))*$B$48,0),0) -> 0 | AD76: 0.01 | AE76: 0.01 | AF76: =AE76-AD76 -> 0 | AG76: =IF(ABS(AF76)>$B$9,"REBALANCE",IF(AND(AC76>=60,AF76<0),"ADD",IF(AND(AC76<40,AF76>0),"TRIM","HOLD"))) -> HOLD
A77: JPM | B77: US Eq | C77: Stock | D77: =IFERROR(ycps("JPM","price"),"") | E77: =IFERROR(ycps("JPM","one_year_return"),"") | F77: =IFERROR(ycps("JPM","three_year_annualized_return"),"") | G77: =IFERROR(ycps("JPM","five_year_annualized_return"),"") | H77: =IFERROR(ycps("JPM","one_year_volatility"),"") | I77: =IFERROR(ycps("JPM","max_drawdown_3_year"),"") | J77: =IFERROR(ycps("JPM","beta_5_year"),"") | K77: =IFERROR(ycps("JPM","dividend_yield"),"") | L77: =IFERROR(ycps("JPM","forward_pe_ratio"),"") | M77: =IFERROR(ycps("JPM","one_month_return"),"") | N77: =IFERROR(ycps("JPM","three_month_return"),"") | O77: =IFERROR(ycps("JPM","six_month_return"),"") | P77: =IFERROR(ycps("JPM","one_year_return"),"") | V77: =IFERROR(IF(H77="","",IF(H77=0,0,(E77-$B$5)/H77)),"") | W77: =IFERROR(IF(V77="","",V77*1.3),"") | X77: =IFERROR(IF(H77="","",IF(H77=0,0,(E77-$B$6)/H77)),"") | Y77: =IFERROR(IF(OR(J77="",J77=0),"",((E77-$B$5)/J77)),"") | Z77: =IFERROR(IF(P77="",0,MIN(100,MAX(0,ROUND(50+P77*150+IF(E77>0,15,0)+IF(J77>0,5,-5),0)))),0) -> 0 | AA77: =IFERROR(IF(M77="",0,MIN(100,MAX(0,ROUND(50+M77*200+IF(AND(M77>0,N77>0),10,-5)+IF(H77<0.2,10,-5),0)))),0) -> 0 | AB77: =IFERROR(IF(OR(E77="",H77=""),0,MIN(100,MAX(0,ROUND(30+IF(H77>0,E77/H77,0)*40+IF(ABS(J77)<0.5,15,0)+IF(E77>0.08,10,0),0)))),0) -> 0 | AC77: =IFERROR(ROUND(Z77*$B$45+AA77*$B$46+AB77*$B$47+IF(Q77<>"",Q77,MIN(100,MAX(0,ROUND(50+(M77*0.4+N77*0.3+O77*0.2+P77*0.1)*200,0))))*$B$48,0),0) -> 0 | AD77: 0.02 | AE77: 0.03 | AF77: =AE77-AD77 -> 0.01 | AG77: =IF(ABS(AF77)>$B$9,"REBALANCE",IF(AND(AC77>=60,AF77<0),"ADD",IF(AND(AC77<40,AF77>0),"TRIM","HOLD"))) -> TRIM
A78: VFIAX | B78: US Eq | C78: MF | D78: =IFERROR(ycps("VFIAX","price"),"") | E78: =IFERROR(ycps("VFIAX","one_year_return"),"") | F78: =IFERROR(ycps("VFIAX","three_year_annualized_return"),"") | G78: =IFERROR(ycps("VFIAX","five_year_annualized_return"),"") | H78: =IFERROR(ycps("VFIAX","one_year_volatility"),"") | I78: =IFERROR(ycps("VFIAX","max_drawdown_3_year"),"") | J78: =IFERROR(ycps("VFIAX","beta_5_year"),"") | K78: =IFERROR(ycps("VFIAX","dividend_yield"),"") | L78: =IFERROR(ycps("VFIAX","forward_pe_ratio"),"") | M78: =IFERROR(ycps("VFIAX","one_month_return"),"") | N78: =IFERROR(ycps("VFIAX","three_month_return"),"") | O78: =IFERROR(ycps("VFIAX","six_month_return"),"") | P78: =IFERROR(ycps("VFIAX","one_year_return"),"") | V78: =IFERROR(IF(H78="","",IF(H78=0,0,(E78-$B$5)/H78)),"") | W78: =IFERROR(IF(V78="","",V78*1.3),"") | X78: =IFERROR(IF(H78="","",IF(H78=0,0,(E78-$B$6)/H78)),"") | Y78: =IFERROR(IF(OR(J78="",J78=0),"",((E78-$B$5)/J78)),"") | Z78: =IFERROR(IF(P78="",0,MIN(100,MAX(0,ROUND(50+P78*150+IF(E78>0,15,0)+IF(J78>0,5,-5),0)))),0) -> 0 | AA78: =IFERROR(IF(M78="",0,MIN(100,MAX(0,ROUND(50+M78*200+IF(AND(M78>0,N78>0),10,-5)+IF(H78<0.2,10,-5),0)))),0) -> 0 | AB78: =IFERROR(IF(OR(E78="",H78=""),0,MIN(100,MAX(0,ROUND(30+IF(H78>0,E78/H78,0)*40+IF(ABS(J78)<0.5,15,0)+IF(E78>0.08,10,0),0)))),0) -> 0 | AC78: =IFERROR(ROUND(Z78*$B$45+AA78*$B$46+AB78*$B$47+IF(Q78<>"",Q78,MIN(100,MAX(0,ROUND(50+(M78*0.4+N78*0.3+O78*0.2+P78*0.1)*200,0))))*$B$48,0),0) -> 0 | AD78: 0 | AE78: -0.005 | AF78: =AE78-AD78 -> -0.005 | AG78: =IF(ABS(AF78)>$B$9,"REBALANCE",IF(AND(AC78>=60,AF78<0),"ADD",IF(AND(AC78<40,AF78>0),"TRIM","HOLD"))) -> HOLD
A79: PIMIX | B79: Bond | C79: MF | D79: =IFERROR(ycps("PIMIX","price"),"") | E79: =IFERROR(ycps("PIMIX","one_year_return"),"") | F79: =IFERROR(ycps("PIMIX","three_year_annualized_return"),"") | G79: =IFERROR(ycps("PIMIX","five_year_annualized_return"),"") | H79: =IFERROR(ycps("PIMIX","one_year_volatility"),"") | I79: =IFERROR(ycps("PIMIX","max_drawdown_3_year"),"") | J79: =IFERROR(ycps("PIMIX","beta_5_year"),"") | K79: =IFERROR(ycps("PIMIX","dividend_yield"),"") | L79: N/A | M79: =IFERROR(ycps("PIMIX","one_month_return"),"") | N79: =IFERROR(ycps("PIMIX","three_month_return"),"") | O79: =IFERROR(ycps("PIMIX","six_month_return"),"") | P79: =IFERROR(ycps("PIMIX","one_year_return"),"") | V79: =IFERROR(IF(H79="","",IF(H79=0,0,(E79-$B$5)/H79)),"") | W79: =IFERROR(IF(V79="","",V79*1.3),"") | X79: =IFERROR(IF(H79="","",IF(H79=0,0,(E79-$B$6)/H79)),"") | Y79: =IFERROR(IF(OR(J79="",J79=0),"",((E79-$B$5)/J79)),"") | Z79: =IFERROR(IF(P79="",0,MIN(100,MAX(0,ROUND(50+P79*150+IF(E79>0,15,0)+IF(J79>0,5,-5),0)))),0) -> 0 | AA79: =IFERROR(IF(M79="",0,MIN(100,MAX(0,ROUND(50+M79*200+IF(AND(M79>0,N79>0),10,-5)+IF(H79<0.2,10,-5),0)))),0) -> 0 | AB79: =IFERROR(IF(OR(E79="",H79=""),0,MIN(100,MAX(0,ROUND(30+IF(H79>0,E79/H79,0)*40+IF(ABS(J79)<0.5,15,0)+IF(E79>0.08,10,0),0)))),0) -> 0 | AC79: =IFERROR(ROUND(Z79*$B$45+AA79*$B$46+AB79*$B$47+IF(Q79<>"",Q79,MIN(100,MAX(0,ROUND(50+(M79*0.4+N79*0.3+O79*0.2+P79*0.1)*200,0))))*$B$48,0),0) -> 0 | AD79: 0 | AE79: 0 | AF79: =AE79-AD79 -> 0 | AG79: =IF(ABS(AF79)>$B$9,"REBALANCE",IF(AND(AC79>=60,AF79<0),"ADD",IF(AND(AC79<40,AF79>0),"TRIM","HOLD"))) -> HOLD
A80: TOTALS | AD80: =SUM(AD56:AD79) -> 1 | AE80: =SUM(AE56:AE79) -> 1.04
A81: AVERAGES | E81: =IFERROR(AVERAGEIF(E56:E79,"<>"&""),0) -> 0 | H81: =IFERROR(AVERAGEIF(H56:H79,"<>"&""),0) -> 0 | J81: =IFERROR(AVERAGEIF(J56:J79,"<>"&""),0) -> 0 | V81: =IFERROR(AVERAGEIF(V56:V79,"<>"&""),0) -> 0 | AC81: =IFERROR(AVERAGEIF(AC56:AC79,"<>"&""),0) -> 0
A82: BUY Signals | B82: =COUNTIF(S56:S79,"BUY") -> 0 | C82: HOLD Signals | D82: =COUNTIF(S56:S79,"HOLD") -> 0 | E82: SELL Signals | F82: =COUNTIF(S56:S79,"SELL") -> 0
A84: FSM MODEL (computed from DWA scores) | B84: =COUNTIF(AC56:AC79,">="&60)/COUNTA(A56:A79) -> 0 | C84: Bullish %
B85: =IF(B84>=$B$33,"FULLY INVESTED",IF(B84>=$B$34,"CAUTION",IF(B84>=$B$35,"DEFENSIVE","RISK OFF"))) -> RISK OFF | C85: FSM Signal
A87: CASH TRIGGERS (computed from composite scores)
A88: MMPR50 | B88: =COUNTIF(AC56:AC79,">="&50)/COUNTA(A56:A79) -> 0 | C88: =IF(B88<$B$39,"⚠ TRIGGERED","OK") -> ⚠ TRIGGERED
A89: MMPR70 | B89: =COUNTIF(AC56:AC79,">="&70)/COUNTA(A56:A79) -> 0 | C89: =IF(B89<$B$40,"⚠ TRIGGERED","OK") -> ⚠ TRIGGERED
A90: PR4050 | B90: =AVERAGE(AC56:AC79) -> 0 | C90: =IF(B90<$B$41,"⚠ TRIGGERED","OK") -> ⚠ TRIGGERED
A91: PR4080 | B91: =AVERAGE(AC56:AC79) -> 0 | C91: =IF(B91<$B$42,"⚠ TRIGGERED","OK") -> ⚠ TRIGGERED
A92: OVERALL | B92: =IF(OR(C88="⚠ TRIGGERED",C89="⚠ TRIGGERED",C90="⚠ TRIGGERED",C91="⚠ TRIGGERED"),"⚠ CASH TRIGGER ACTIVE","ALL CLEAR") -> ⚠ CASH TRIGGER ACTIVE
A95: DWA DATA IMPORT GUIDE
A96: HOW TO POPULATE DWA DATA (Orange columns Q-U):
A98: OPTION A: Nasdaq Dorsey Wright Platform (Recommended)
A99: 1. Log into research.dorseywright.com → Research → Relative Strength
A100: 2. Enter your 24 tickers → Generate report
A101: 3. Export to Excel → Copy columns: RS Score, RS Rating (1-5), Signal, Matrix Position, Sector RS
A102: 4. Paste into this sheet columns Q-U, rows 56-79
A104: OPTION B: DWA Point & Figure Chart Manual Entry
A105: 1. Open each ticker's P&F chart on dorseywright.com
A106: 2. Record: RS Score (0-100), Rating (1=worst, 5=best)
A107: 3. Signal: BUY if last P&F signal was buy, SELL if sell, HOLD if neutral
A108: 4. Matrix: OFFENSE if RS improving, DEFENSE if declining, NEUTRAL if flat
... A143: one_month_return, three_month_return, six_month_return

Sheet Asset Analysis
A1: SECURITY ANALYSIS — Blue cells are inputs. All other cells are formulas.
A3: Ticker | B3: Class | C3: Type | D3: Ann Return | E3: Volatility | F3: Sharpe | G3: Sortino | H3: Beta | I3: Max DD | J3: 1M Mom | K3: 3M Mom | L3: 6M Mom | M3: 12M Mom | N3: DWA Score | O3: DWA Signal | P3: RS Rank | Q3: Target Wt | R3: Current Wt | S3: Drift | T3: Action
A4: ='Data Input'!A56 -> SPY | B4: ='Data Input'!B56 -> US Eq | C4: ='Data Input'!C56 -> ETF | D4: =IFERROR('Data Input'!E56,0) | E4: =IFERROR('Data Input'!H56,0) | F4: =IFERROR('Data Input'!V56,0) | G4: =IFERROR('Data Input'!W56,0) | H4: =IFERROR('Data Input'!J56,0) | I4: =IFERROR('Data Input'!I56,0) | J4: =IFERROR('Data Input'!M56,0) | K4: =IFERROR('Data Input'!N56,0) | L4: =IFERROR('Data Input'!O56,0) | M4: =IFERROR('Data Input'!P56,0) | N4: =IFERROR(IF('Data Input'!Q56<>"",'Data Input'!Q56,MIN(100,MAX(0,ROUND(50+(J4*0.4+K4*0.3+L4*0.2+M4*0.1)*200,0)))),0) -> 0 | O4: =IF('Data Input'!S56<>"",'Data Input'!S56,IF(N4>=70,"BUY",IF(N4>=50,"HOLD","SELL"))) -> SELL | P4: =RANK(N4,N$4:N$27,0) -> 1 | Q4: ='Data Input'!AD56 -> 0.08 | R4: ='Data Input'!AE56 -> 0.09 | S4: =R4-Q4 -> 0.01 | T4: =IF(ABS(S4)>'Data Input'!$B$9,"REBALANCE",IF(AND(O4="BUY",S4<0),"ADD",IF(AND(O4="SELL",S4>0),"TRIM","HOLD"))) -> TRIM
A5: ='Data Input'!A57 -> QQQ | B5: ='Data Input'!B57 -> US Eq | C5: ='Data Input'!C57 -> ETF | D5: =IFERROR('Data Input'!E57,0) | E5: =IFERROR('Data Input'!H57,0) | F5: =IFERROR('Data Input'!V57,0) | G5: =IFERROR('Data Input'!W57,0) | H5: =IFERROR('Data Input'!J57,0) | I5: =IFERROR('Data Input'!I57,0) | J5: =IFERROR('Data Input'!M57,0) | K5: =IFERROR('Data Input'!N57,0) | L5: =IFERROR('Data Input'!O57,0) | M5: =IFERROR('Data Input'!P57,0) | N5: =IFERROR(IF('Data Input'!Q57<>"",'Data Input'!Q57,MIN(100,MAX(0,ROUND(50+(J5*0.4+K5*0.3+L5*0.2+M5*0.1)*200,0)))),0) -> 0 | O5: =IF('Data Input'!S57<>"",'Data Input'!S57,IF(N5>=70,"BUY",IF(N5>=50,"HOLD","SELL"))) -> SELL | P5: =RANK(N5,N$4:N$27,0) -> 1 | Q5: ='Data Input'!AD57 -> 0.07 | R5: ='Data Input'!AE57 -> 0.065 | S5: =R5-Q5 -> -0.005 | T5: =IF(ABS(S5)>'Data Input'!$B$9,"REBALANCE",IF(AND(O5="BUY",S5<0),"ADD",IF(AND(O5="SELL",S5>0),"TRIM","HOLD"))) -> HOLD
A6: ='Data Input'!A58 -> IWM | B6: ='Data Input'!B58 -> US Eq | C6: ='Data Input'!C58 -> ETF | D6: =IFERROR('Data Input'!E58,0) | E6: =IFERROR('Data Input'!H58,0) | F6: =IFERROR('Data Input'!V58,0) | G6: =IFERROR('Data Input'!W58,0) | H6: =IFERROR('Data Input'!J58,0) | I6: =IFERROR('Data Input'!I58,0) | J6: =IFERROR('Data Input'!M58,0) | K6: =IFERROR('Data Input'!N58,0) | L6: =IFERROR('Data Input'!O58,0) | M6: =IFERROR('Data Input'!P58,0) | N6: =IFERROR(IF('Data Input'!Q58<>"",'Data Input'!Q58,MIN(100,MAX(0,ROUND(50+(J6*0.4+K6*0.3+L6*0.2+M6*0.1)*200,0)))),0) -> 0 | O6: =IF('Data Input'!S58<>"",'Data Input'!S58,IF(N6>=70,"BUY",IF(N6>=50,"HOLD","SELL"))) -> SELL | P6: =RANK(N6,N$4:N$27,0) -> 1 | Q6: ='Data Input'!AD58 -> 0.04 | R6: ='Data Input'!AE58 -> 0.04 | S6: =R6-Q6 -> 0 | T6: =IF(ABS(S6)>'Data Input'!$B$9,"REBALANCE",IF(AND(O6="BUY",S6<0),"ADD",IF(AND(O6="SELL",S6>0),"TRIM","HOLD"))) -> HOLD
A7: ='Data Input'!A59 -> EFA | B7: ='Data Input'!B59 -> Intl | C7: ='Data Input'!C59 -> ETF | D7: =IFERROR('Data Input'!E59,0) | E7: =IFERROR('Data Input'!H59,0) | F7: =IFERROR('Data Input'!V59,0) | G7: =IFERROR('Data Input'!W59,0) | H7: =IFERROR('Data Input'!J59,0) | I7: =IFERROR('Data Input'!I59,0) | J7: =IFERROR('Data Input'!M59,0) | K7: =IFERROR('Data Input'!N59,0) | L7: =IFERROR('Data Input'!O59,0) | M7: =IFERROR('Data Input'!P59,0) | N7: =IFERROR(IF('Data Input'!Q59<>"",'Data Input'!Q59,MIN(100,MAX(0,ROUND(50+(J7*0.4+K7*0.3+L7*0.2+M7*0.1)*200,0)))),0) -> 0 | O7: =IF('Data Input'!S59<>"",'Data Input'!S59,IF(N7>=70,"BUY",IF(N7>=50,"HOLD","SELL"))) -> SELL | P7: =RANK(N7,N$4:N$27,0) -> 1 | Q7: ='Data Input'!AD59 -> 0.05 | R7: ='Data Input'!AE59 -> 0.06 | S7: =R7-Q7 -> 0.01 | T7: =IF(ABS(S7)>'Data Input'!$B$9,"REBALANCE",IF(AND(O7="BUY",S7<0),"ADD",IF(AND(O7="SELL",S7>0),"TRIM","HOLD"))) -> TRIM
A8: ='Data Input'!A60 -> EEM | B8: ='Data Input'!B60 -> Intl | C8: ='Data Input'!C60 -> ETF | D8: =IFERROR('Data Input'!E60,0) | E8: =IFERROR('Data Input'!H60,0) | F8: =IFERROR('Data Input'!V60,0) | G8: =IFERROR('Data Input'!W60,0) | H8: =IFERROR('Data Input'!J60,0) | I8: =IFERROR('Data Input'!I60,0) | J8: =IFERROR('Data Input'!M60,0) | K8: =IFERROR('Data Input'!N60,0) | L8: =IFERROR('Data Input'!O60,0) | M8: =IFERROR('Data Input'!P60,0) | N8: =IFERROR(IF('Data Input'!Q60<>"",'Data Input'!Q60,MIN(100,MAX(0,ROUND(50+(J8*0.4+K8*0.3+L8*0.2+M8*0.1)*200,0)))),0) -> 0 | O8: =IF('Data Input'!S60<>"",'Data Input'!S60,IF(N8>=70,"BUY",IF(N8>=50,"HOLD","SELL"))) -> SELL | P8: =RANK(N8,N$4:N$27,0) -> 1 | Q8: ='Data Input'!AD60 -> 0.03 | R8: ='Data Input'!AE60 -> 0.025 | S8: =R8-Q8 -> -0.005 | T8: =IF(ABS(S8)>'Data Input'!$B$9,"REBALANCE",IF(AND(O8="BUY",S8<0),"ADD",IF(AND(O8="SELL",S8>0),"TRIM","HOLD"))) -> HOLD
A9: ='Data Input'!A61 -> AGG | B9: ='Data Input'!B61 -> Bond | C9: ='Data Input'!C61 -> ETF | D9: =IFERROR('Data Input'!E61,0) | E9: =IFERROR('Data Input'!H61,0) | F9: =IFERROR('Data Input'!V61,0) | G9: =IFERROR('Data Input'!W61,0) | H9: =IFERROR('Data Input'!J61,0) | I9: =IFERROR('Data Input'!I61,0) | J9: =IFERROR('Data Input'!M61,0) | K9: =IFERROR('Data Input'!N61,0) | L9: =IFERROR('Data Input'!O61,0) | M9: =IFERROR('Data Input'!P61,0) | N9: =IFERROR(IF('Data Input'!Q61<>"",'Data Input'!Q61,MIN(100,MAX(0,ROUND(50+(J9*0.4+K9*0.3+L9*0.2+M9*0.1)*200,0)))),0) -> 0 | O9: =IF('Data Input'!S61<>"",'Data Input'!S61,IF(N9>=70,"BUY",IF(N9>=50,"HOLD","SELL"))) -> SELL | P9: =RANK(N9,N$4:N$27,0) -> 1 | Q9: ='Data Input'!AD61 -> 0.1 | R9: ='Data Input'!AE61 -> 0.1 | S9: =R9-Q9 -> 0 | T9: =IF(ABS(S9)>'Data Input'!$B$9,"REBALANCE",IF(AND(O9="BUY",S9<0),"ADD",IF(AND(O9="SELL",S9>0),"TRIM","HOLD"))) -> HOLD
A10: ='Data Input'!A62 -> TLT | B10: ='Data Input'!B62 -> Bond | C10: ='Data Input'!C62 -> ETF | D10: =IFERROR('Data Input'!E62,0) | E10: =IFERROR('Data Input'!H62,0) | F10: =IFERROR('Data Input'!V62,0) | G10: =IFERROR('Data Input'!W62,0) | H10: =IFERROR('Data Input'!J62,0) | I10: =IFERROR('Data Input'!I62,0) | J10: =IFERROR('Data Input'!M62,0) | K10: =IFERROR('Data Input'!N62,0) | L10: =IFERROR('Data Input'!O62,0) | M10: =IFERROR('Data Input'!P62,0) | N10: =IFERROR(IF('Data Input'!Q62<>"",'Data Input'!Q62,MIN(100,MAX(0,ROUND(50+(J10*0.4+K10*0.3+L10*0.2+M10*0.1)*200,0)))),0) -> 0 | O10: =IF('Data Input'!S62<>"",'Data Input'!S62,IF(N10>=70,"BUY",IF(N10>=50,"HOLD","SELL"))) -> SELL | P10: =RANK(N10,N$4:N$27,0) -> 1 | Q10: ='Data Input'!AD62 -> 0.05 | R10: ='Data Input'!AE62 -> 0.06 | S10: =R10-Q10 -> 0.01 | T10: =IF(ABS(S10)>'Data Input'!$B$9,"REBALANCE",IF(AND(O10="BUY",S10<0),"ADD",IF(AND(O10="SELL",S10>0),"TRIM","HOLD"))) -> TRIM
A11: ='Data Input'!A63 -> GLD | B11: ='Data Input'!B63 -> Alt | C11: ='Data Input'!C63 -> ETF | D11: =IFERROR('Data Input'!E63,0) | E11: =IFERROR('Data Input'!H63,0) | F11: =IFERROR('Data Input'!V63,0) | G11: =IFERROR('Data Input'!W63,0) | H11: =IFERROR('Data Input'!J63,0) | I11: =IFERROR('Data Input'!I63,0) | J11: =IFERROR('Data Input'!M63,0) | K11: =IFERROR('Data Input'!N63,0) | L11: =IFERROR('Data Input'!O63,0) | M11: =IFERROR('Data Input'!P63,0) | N11: =IFERROR(IF('Data Input'!Q63<>"",'Data Input'!Q63,MIN(100,MAX(0,ROUND(50+(J11*0.4+K11*0.3+L11*0.2+M11*0.1)*200,0)))),0) -> 0 | O11: =IF('Data Input'!S63<>"",'Data Input'!S63,IF(N11>=70,"BUY",IF(N11>=50,"HOLD","SELL"))) -> SELL | P11: =RANK(N11,N$4:N$27,0) -> 1 | Q11: ='Data Input'!AD63 -> 0.08 | R11: ='Data Input'!AE63 -> 0.075 | S11: =R11-Q11 -> -0.005 | T11: =IF(ABS(S11)>'Data Input'!$B$9,"REBALANCE",IF(AND(O11="BUY",S11<0),"ADD",IF(AND(O11="SELL",S11>0),"TRIM","HOLD"))) -> HOLD
A12: ='Data Input'!A64 -> VNQ | B12: ='Data Input'!B64 -> REIT | C12: ='Data Input'!C64 -> ETF | D12: =IFERROR('Data Input'!E64,0) | E12: =IFERROR('Data Input'!H64,0) | F12: =IFERROR('Data Input'!V64,0) | G12: =IFERROR('Data Input'!W64,0) | H12: =IFERROR('Data Input'!J64,0) | I12: =IFERROR('Data Input'!I64,0) | J12: =IFERROR('Data Input'!M64,0) | K12: =IFERROR('Data Input'!N64,0) | L12: =IFERROR('Data Input'!O64,0) | M12: =IFERROR('Data Input'!P64,0) | N12: =IFERROR(IF('Data Input'!Q64<>"",'Data Input'!Q64,MIN(100,MAX(0,ROUND(50+(J12*0.4+K12*0.3+L12*0.2+M12*0.1)*200,0)))),0) -> 0 | O12: =IF('Data Input'!S64<>"",'Data Input'!S64,IF(N12>=70,"BUY",IF(N12>=50,"HOLD","SELL"))) -> SELL | P12: =RANK(N12,N$4:N$27,0) -> 1 | Q12: ='Data Input'!AD64 -> 0.05 | R12: ='Data Input'!AE64 -> 0.05 | S12: =R12-Q12 -> 0 | T12: =IF(ABS(S12)>'Data Input'!$B$9,"REBALANCE",IF(AND(O12="BUY",S12<0),"ADD",IF(AND(O12="SELL",S12>0),"TRIM","HOLD"))) -> HOLD
A13: ='Data Input'!A65 -> XLK | B13: ='Data Input'!B65 -> US Eq | C13: ='Data Input'!C65 -> ETF | D13: =IFERROR('Data Input'!E65,0) | E13: =IFERROR('Data Input'!H65,0) | F13: =IFERROR('Data Input'!V65,0) | G13: =IFERROR('Data Input'!W65,0) | H13: =IFERROR('Data Input'!J65,0) | I13: =IFERROR('Data Input'!I65,0) | J13: =IFERROR('Data Input'!M65,0) | K13: =IFERROR('Data Input'!N65,0) | L13: =IFERROR('Data Input'!O65,0) | M13: =IFERROR('Data Input'!P65,0) | N13: =IFERROR(IF('Data Input'!Q65<>"",'Data Input'!Q65,MIN(100,MAX(0,ROUND(50+(J13*0.4+K13*0.3+L13*0.2+M13*0.1)*200,0)))),0) -> 0 | O13: =IF('Data Input'!S65<>"",'Data Input'!S65,IF(N13>=70,"BUY",IF(N13>=50,"HOLD","SELL"))) -> SELL | P13: =RANK(N13,N$4:N$27,0) -> 1 | Q13: ='Data Input'!AD65 -> 0.08 | R13: ='Data Input'!AE65 -> 0.09 | S13: =R13-Q13 -> 0.01 | T13: =IF(ABS(S13)>'Data Input'!$B$9,"REBALANCE",IF(AND(O13="BUY",S13<0),"ADD",IF(AND(O13="SELL",S13>0),"TRIM","HOLD"))) -> TRIM
A14: ='Data Input'!A66 -> XLV | B14: ='Data Input'!B66 -> US Eq | C14: ='Data Input'!C66 -> ETF | D14: =IFERROR('Data Input'!E66,0) | E14: =IFERROR('Data Input'!H66,0) | F14: =IFERROR('Data Input'!V66,0) | G14: =IFERROR('Data Input'!W66,0) | H14: =IFERROR('Data Input'!J66,0) | I14: =IFERROR('Data Input'!I66,0) | J14: =IFERROR('Data Input'!M66,0) | K14: =IFERROR('Data Input'!N66,0) | L14: =IFERROR('Data Input'!O66,0) | M14: =IFERROR('Data Input'!P66,0) | N14: =IFERROR(IF('Data Input'!Q66<>"",'Data Input'!Q66,MIN(100,MAX(0,ROUND(50+(J14*0.4+K14*0.3+L14*0.2+M14*0.1)*200,0)))),0) -> 0 | O14: =IF('Data Input'!S66<>"",'Data Input'!S66,IF(N14>=70,"BUY",IF(N14>=50,"HOLD","SELL"))) -> SELL | P14: =RANK(N14,N$4:N$27,0) -> 1 | Q14: ='Data Input'!AD66 -> 0.04 | R14: ='Data Input'!AE66 -> 0.035 | S14: =R14-Q14 -> -0.005 | T14: =IF(ABS(S14)>'Data Input'!$B$9,"REBALANCE",IF(AND(O14="BUY",S14<0),"ADD",IF(AND(O14="SELL",S14>0),"TRIM","HOLD"))) -> HOLD
A15: ='Data Input'!A67 -> XLE | B15: ='Data Input'!B67 -> US Eq | C15: ='Data Input'!C67 -> ETF | D15: =IFERROR('Data Input'!E67,0) | E15: =IFERROR('Data Input'!H67,0) | F15: =IFERROR('Data Input'!V67,0) | G15: =IFERROR('Data Input'!W67,0) | H15: =IFERROR('Data Input'!J67,0) | I15: =IFERROR('Data Input'!I67,0) | J15: =IFERROR('Data Input'!M67,0) | K15: =IFERROR('Data Input'!N67,0) | L15: =IFERROR('Data Input'!O67,0) | M15: =IFERROR('Data Input'!P67,0) | N15: =IFERROR(IF('Data Input'!Q67<>"",'Data Input'!Q67,MIN(100,MAX(0,ROUND(50+(J15*0.4+K15*0.3+L15*0.2+M15*0.1)*200,0)))),0) -> 0 | O15: =IF('Data Input'!S67<>"",'Data Input'!S67,IF(N15>=70,"BUY",IF(N15>=50,"HOLD","SELL"))) -> SELL | P15: =RANK(N15,N$4:N$27,0) -> 1 | Q15: ='Data Input'!AD67 -> 0.03 | R15: ='Data Input'!AE67 -> 0.03 | S15: =R15-Q15 -> 0 | T15: =IF(ABS(S15)>'Data Input'!$B$9,"REBALANCE",IF(AND(O15="BUY",S15<0),"ADD",IF(AND(O15="SELL",S15>0),"TRIM","HOLD"))) -> HOLD
... A27: ='Data Input'!A79 -> PIMIX | B27: ='Data Input'!B79 -> Bond | C27: ='Data Input'!C79 -> MF | D27: =IFERROR('Data Input'!E79,0) | E27: =IFERROR('Data Input'!H79,0) | F27: =IFERROR('Data Input'!V79,0) | G27: =IFERROR('Data Input'!W79,0) | H27: =IFERROR('Data Input'!J79,0) | I27: =IFERROR('Data Input'!I79,0) | J27: =IFERROR('Data Input'!M79,0) | K27: =IFERROR('Data Input'!N79,0) | L27: =IFERROR('Data Input'!O79,0) | M27: =IFERROR('Data Input'!P79,0) | N27: =IFERROR(IF('Data Input'!Q79<>"",'Data Input'!Q79,MIN(100,MAX(0,ROUND(50+(J27*0.4+K27*0.3+L27*0.2+M27*0.1)*200,0)))),0) -> 0 | O27: =IF('Data Input'!S79<>"",'Data Input'!S79,IF(N27>=70,"BUY",IF(N27>=50,"HOLD","SELL"))) -> SELL | P27: =RANK(N27,N$4:N$27,0) -> 1 | Q27: ='Data Input'!AD79 -> 0 | R27: ='Data Input'!AE79 -> 0 | S27: =R27-Q27 -> 0 | T27: =IF(ABS(S27)>'Data Input'!$B$9,"REBALANCE",IF(AND(O27="BUY",S27<0),"ADD",IF(AND(O27="SELL",S27>0),"TRIM","HOLD"))) -> HOLD
A28: TOTALS | Q28: =SUM(Q4:Q27) -> 1 | R28: =SUM(R4:R27) -> 1.04
A29: AVERAGES | D29: =IFERROR(AVERAGE(D4:D27),0) -> 0 | E29: =IFERROR(AVERAGE(E4:E27),0) -> 0 | F29: =IFERROR(AVERAGE(F4:F27),0) -> 0 | H29: =IFERROR(AVERAGE(H4:H27),0) -> 0 | N29: =IFERROR(AVERAGE(N4:N27),0) -> 0
A30: SIGNAL COUNTS | O30: =COUNTIF(O4:O27,"BUY")&" BUY / "&COUNTIF(O4:O27,"HOLD")&" HOLD / "&COUNTIF(O4:O27,"SELL")&" SELL" -> 0 BUY / 0 HOLD / 24 SELL

Sheet Dashboard
A1: PORTFOLIO DASHBOARD — All values computed from Asset Analysis & Data Input
A3: PORTFOLIO METRICS
A4: Portfolio Value | C4: Weighted Return | E4: Weighted Vol | G4: Sharpe | I4: Avg Max DD | K4: Avg Beta | M4: # Assets | O4: # BUY Signals
A5: ='Data Input'!B7 -> 0.16 | C5: =SUMPRODUCT('Asset Analysis'!R4:R27,'Asset Analysis'!D4:D27) -> 0 | E5: =SUMPRODUCT('Asset Analysis'!R4:R27,'Asset Analysis'!E4:E27) -> 0 | G5: =IF(E5=0,0,(C5-'Data Input'!B4)/E5) -> 0 | I5: =IFERROR(AVERAGE('Asset Analysis'!I4:I27),0) -> 0 | K5: =SUMPRODUCT('Asset Analysis'!R4:R27,'Asset Analysis'!H4:H27) -> 0 | M5: =COUNTA('Asset Analysis'!A4:A27) -> 24 | O5: =COUNTIF('Asset Analysis'!O4:O27,"BUY") -> 0
A8: FSM MODEL STATUS
A9: Bullish % | B9: ='Data Input'!B84 -> 0
A10: FSM Signal | B10: ='Data Input'!B85 -> RISK OFF
A12: CASH TRIGGERS
A13: Trigger | B13: Current | C13: Threshold | D13: Status
A14: MMPR50 | B14: ='Data Input'!B88 -> 0 | C14: ='Data Input'!B23 -> 0.04 | D14: ='Data Input'!C88 -> ⚠ TRIGGERED
A15: MMPR70 | B15: ='Data Input'!B89 -> 0 | C15: ='Data Input'!B24 -> 0.005 | D15: ='Data Input'!C89 -> ⚠ TRIGGERED
A16: PR4050 | B16: ='Data Input'!B90 -> 0 | C16: ='Data Input'!B25 | D16: ='Data Input'!C90 -> ⚠ TRIGGERED
A17: PR4080 | B17: ='Data Input'!B91 -> 0 | C17: ='Data Input'!B26 | D17: ='Data Input'!C91 -> ⚠ TRIGGERED
A18: ='Data Input'!B92 -> ⚠ CASH TRIGGER ACTIVE

Sheet Signal Engine
A1: MULTI-FACTOR SIGNAL ENGINE — All scores are formulas
A3: WEIGHTS (from Data Input)
A4: Trend | B4: ='Data Input'!B29 -> 50 | C4: Technical | D4: ='Data Input'!B30 -> 0 | E4: Fundamental | F4: ='Data Input'!B31 -> 0 | G4: DWA | H4: ='Data Input'!B32 -> 0
A6: SIGNAL THRESHOLDS
A7: STRONG BUY | B7: ≥70 | C7: 3+ factors ≥60 | D7: Overweight aggressively
A8: BUY | B8: ≥60 | C8: 2+ factors ≥60 | D8: Add / Initiate
A9: HOLD | B9: 45-59 | C9: Mixed | D9: Maintain weight
A10: SELL | B10: <45 | C10: ≤1 factor ≥60 | D10: Trim / Reduce
A11: STRONG SELL | B11: <35 | C11: 0-1 factors | D11: Exit / Replace w/ buffered
A14: COMPOSITE SIGNALS
A15: Ticker | B15: Trend | C15: Technical | D15: Fundamental | E15: DWA | F15: Composite | G15: Signal | H15: Conviction | I15: Factors ≥60 | J15: Divergence
A16: ='Data Input'!A56 -> SPY | B16: ='Data Input'!Z56 -> 0 | C16: ='Data Input'!AA56 -> 0 | D16: ='Data Input'!AB56 -> 0 | E16: ='Asset Analysis'!N4 -> 0 | F16: ='Data Input'!AC56 -> 0 | G16: =IF(AND(F16>=70,I16>=3),"STRONG BUY",IF(AND(F16>=60,I16>=2),"BUY",IF(AND(F16<35),"STRONG SELL",IF(AND(F16<45,I16<=1),"SELL","HOLD")))) -> STRONG SELL | H16: =IF(OR(G16="STRONG BUY",G16="STRONG SELL"),"HIGH",IF(OR(G16="BUY",G16="SELL"),"MEDIUM",IF(G16="HOLD","NEUTRAL","LOW"))) -> HIGH | I16: =IF(B16>=60,1,0)+IF(C16>=60,1,0)+IF(D16>=60,1,0)+IF(E16>=60,1,0) -> 0 | J16: =IF((MAX(B16:E16)-MIN(B16:E16))>35,"⚠ DIVERGENCE","")
A17: ='Data Input'!A57 -> QQQ | B17: ='Data Input'!Z57 -> 0 | C17: ='Data Input'!AA57 -> 0 | D17: ='Data Input'!AB57 -> 0 | E17: ='Asset Analysis'!N5 -> 0 | F17: ='Data Input'!AC57 -> 0 | G17: =IF(AND(F17>=70,I17>=3),"STRONG BUY",IF(AND(F17>=60,I17>=2),"BUY",IF(AND(F17<35),"STRONG SELL",IF(AND(F17<45,I17<=1),"SELL","HOLD")))) -> STRONG SELL | H17: =IF(OR(G17="STRONG BUY",G17="STRONG SELL"),"HIGH",IF(OR(G17="BUY",G17="SELL"),"MEDIUM",IF(G17="HOLD","NEUTRAL","LOW"))) -> HIGH | I17: =IF(B17>=60,1,0)+IF(C17>=60,1,0)+IF(D17>=60,1,0)+IF(E17>=60,1,0) -> 0 | J17: =IF((MAX(B17:E17)-MIN(B17:E17))>35,"⚠ DIVERGENCE","")
A18: ='Data Input'!A58 -> IWM | B18: ='Data Input'!Z58 -> 0 | C18: ='Data Input'!AA58 -> 0 | D18: ='Data Input'!AB58 -> 0 | E18: ='Asset Analysis'!N6 -> 0 | F18: ='Data Input'!AC58 -> 0 | G18: =IF(AND(F18>=70,I18>=3),"STRONG BUY",IF(AND(F18>=60,I18>=2),"BUY",IF(AND(F18<35),"STRONG SELL",IF(AND(F18<45,I18<=1),"SELL","HOLD")))) -> STRONG SELL | H18: =IF(OR(G18="STRONG BUY",G18="STRONG SELL"),"HIGH",IF(OR(G18="BUY",G18="SELL"),"MEDIUM",IF(G18="HOLD","NEUTRAL","LOW"))) -> HIGH | I18: =IF(B18>=60,1,0)+IF(C18>=60,1,0)+IF(D18>=60,1,0)+IF(E18>=60,1,0) -> 0 | J18: =IF((MAX(B18:E18)-MIN(B18:E18))>35,"⚠ DIVERGENCE","")
A19: ='Data Input'!A59 -> EFA | B19: ='Data Input'!Z59 -> 0 | C19: ='Data Input'!AA59 -> 0 | D19: ='Data Input'!AB59 -> 0 | E19: ='Asset Analysis'!N7 -> 0 | F19: ='Data Input'!AC59 -> 0 | G19: =IF(AND(F19>=70,I19>=3),"STRONG BUY",IF(AND(F19>=60,I19>=2),"BUY",IF(AND(F19<35),"STRONG SELL",IF(AND(F19<45,I19<=1),"SELL","HOLD")))) -> STRONG SELL | H19: =IF(OR(G19="STRONG BUY",G19="STRONG SELL"),"HIGH",IF(OR(G19="BUY",G19="SELL"),"MEDIUM",IF(G19="HOLD","NEUTRAL","LOW"))) -> HIGH | I19: =IF(B19>=60,1,0)+IF(C19>=60,1,0)+IF(D19>=60,1,0)+IF(E19>=60,1,0) -> 0 | J19: =IF((MAX(B19:E19)-MIN(B19:E19))>35,"⚠ DIVERGENCE","")
A20: ='Data Input'!A60 -> EEM | B20: ='Data Input'!Z60 -> 0 | C20: ='Data Input'!AA60 -> 0 | D20: ='Data Input'!AB60 -> 0 | E20: ='Asset Analysis'!N8 -> 0 | F20: ='Data Input'!AC60 -> 0 | G20: =IF(AND(F20>=70,I20>=3),"STRONG BUY",IF(AND(F20>=60,I20>=2),"BUY",IF(AND(F20<35),"STRONG SELL",IF(AND(F20<45,I20<=1),"SELL","HOLD")))) -> STRONG SELL | H20: =IF(OR(G20="STRONG BUY",G20="STRONG SELL"),"HIGH",IF(OR(G20="BUY",G20="SELL"),"MEDIUM",IF(G20="HOLD","NEUTRAL","LOW"))) -> HIGH | I20: =IF(B20>=60,1,0)+IF(C20>=60,1,0)+IF(D20>=60,1,0)+IF(E20>=60,1,0) -> 0 | J20: =IF((MAX(B20:E20)-MIN(B20:E20))>35,"⚠ DIVERGENCE","")
A21: ='Data Input'!A61 -> AGG | B21: ='Data Input'!Z61 -> 0 | C21: ='Data Input'!AA61 -> 0 | D21: ='Data Input'!AB61 -> 0 | E21: ='Asset Analysis'!N9 -> 0 | F21: ='Data Input'!AC61 -> 0 | G21: =IF(AND(F21>=70,I21>=3),"STRONG BUY",IF(AND(F21>=60,I21>=2),"BUY",IF(AND(F21<35),"STRONG SELL",IF(AND(F21<45,I21<=1),"SELL","HOLD")))) -> STRONG SELL | H21: =IF(OR(G21="STRONG BUY",G21="STRONG SELL"),"HIGH",IF(OR(G21="BUY",G21="SELL"),"MEDIUM",IF(G21="HOLD","NEUTRAL","LOW"))) -> HIGH | I21: =IF(B21>=60,1,0)+IF(C21>=60,1,0)+IF(D21>=60,1,0)+IF(E21>=60,1,0) -> 0 | J21: =IF((MAX(B21:E21)-MIN(B21:E21))>35,"⚠ DIVERGENCE","")
A22: ='Data Input'!A62 -> TLT | B22: ='Data Input'!Z62 -> 0 | C22: ='Data Input'!AA62 -> 0 | D22: ='Data Input'!AB62 -> 0 | E22: ='Asset Analysis'!N10 -> 0 | F22: ='Data Input'!AC62 -> 0 | G22: =IF(AND(F22>=70,I22>=3),"STRONG BUY",IF(AND(F22>=60,I22>=2),"BUY",IF(AND(F22<35),"STRONG SELL",IF(AND(F22<45,I22<=1),"SELL","HOLD")))) -> STRONG SELL | H22: =IF(OR(G22="STRONG BUY",G22="STRONG SELL"),"HIGH",IF(OR(G22="BUY",G22="SELL"),"MEDIUM",IF(G22="HOLD","NEUTRAL","LOW"))) -> HIGH | I22: =IF(B22>=60,1,0)+IF(C22>=60,1,0)+IF(D22>=60,1,0)+IF(E22>=60,1,0) -> 0 | J22: =IF((MAX(B22:E22)-MIN(B22:E22))>35,"⚠ DIVERGENCE","")
A23: ='Data Input'!A63 -> GLD | B23: ='Data Input'!Z63 -> 0 | C23: ='Data Input'!AA63 -> 0 | D23: ='Data Input'!AB63 -> 0 | E23: ='Asset Analysis'!N11 -> 0 | F23: ='Data Input'!AC63 -> 0 | G23: =IF(AND(F23>=70,I23>=3),"STRONG BUY",IF(AND(F23>=60,I23>=2),"BUY",IF(AND(F23<35),"STRONG SELL",IF(AND(F23<45,I23<=1),"SELL","HOLD")))) -> STRONG SELL | H23: =IF(OR(G23="STRONG BUY",G23="STRONG SELL"),"HIGH",IF(OR(G23="BUY",G23="SELL"),"MEDIUM",IF(G23="HOLD","NEUTRAL","LOW"))) -> HIGH | I23: =IF(B23>=60,1,0)+IF(C23>=60,1,0)+IF(D23>=60,1,0)+IF(E23>=60,1,0) -> 0 | J23: =IF((MAX(B23:E23)-MIN(B23:E23))>35,"⚠ DIVERGENCE","")
A24: ='Data Input'!A64 -> VNQ | B24: ='Data Input'!Z64 -> 0 | C24: ='Data Input'!AA64 -> 0 | D24: ='Data Input'!AB64 -> 0 | E24: ='Asset Analysis'!N12 -> 0 | F24: ='Data Input'!AC64 -> 0 | G24: =IF(AND(F24>=70,I24>=3),"STRONG BUY",IF(AND(F24>=60,I24>=2),"BUY",IF(AND(F24<35),"STRONG SELL",IF(AND(F24<45,I24<=1),"SELL","HOLD")))) -> STRONG SELL | H24: =IF(OR(G24="STRONG BUY",G24="STRONG SELL"),"HIGH",IF(OR(G24="BUY",G24="SELL"),"MEDIUM",IF(G24="HOLD","NEUTRAL","LOW"))) -> HIGH | I24: =IF(B24>=60,1,0)+IF(C24>=60,1,0)+IF(D24>=60,1,0)+IF(E24>=60,1,0) -> 0 | J24: =IF((MAX(B24:E24)-MIN(B24:E24))>35,"⚠ DIVERGENCE","")
A25: ='Data Input'!A65 -> XLK | B25: ='Data Input'!Z65 -> 0 | C25: ='Data Input'!AA65 -> 0 | D25: ='Data Input'!AB65 -> 0 | E25: ='Asset Analysis'!N13 -> 0 | F25: ='Data Input'!AC65 -> 0 | G25: =IF(AND(F25>=70,I25>=3),"STRONG BUY",IF(AND(F25>=60,I25>=2),"BUY",IF(AND(F25<35),"STRONG SELL",IF(AND(F25<45,I25<=1),"SELL","HOLD")))) -> STRONG SELL | H25: =IF(OR(G25="STRONG BUY",G25="STRONG SELL"),"HIGH",IF(OR(G25="BUY",G25="SELL"),"MEDIUM",IF(G25="HOLD","NEUTRAL","LOW"))) -> HIGH | I25: =IF(B25>=60,1,0)+IF(C25>=60,1,0)+IF(D25>=60,1,0)+IF(E25>=60,1,0) -> 0 | J25: =IF((MAX(B25:E25)-MIN(B25:E25))>35,"⚠ DIVERGENCE","")
A26: ='Data Input'!A66 -> XLV | B26: ='Data Input'!Z66 -> 0 | C26: ='Data Input'!AA66 -> 0 | D26: ='Data Input'!AB66 -> 0 | E26: ='Asset Analysis'!N14 -> 0 | F26: ='Data Input'!AC66 -> 0 | G26: =IF(AND(F26>=70,I26>=3),"STRONG BUY",IF(AND(F26>=60,I26>=2),"BUY",IF(AND(F26<35),"STRONG SELL",IF(AND(F26<45,I26<=1),"SELL","HOLD")))) -> STRONG SELL | H26: =IF(OR(G26="STRONG BUY",G26="STRONG SELL"),"HIGH",IF(OR(G26="BUY",G26="SELL"),"MEDIUM",IF(G26="HOLD","NEUTRAL","LOW"))) -> HIGH | I26: =IF(B26>=60,1,0)+IF(C26>=60,1,0)+IF(D26>=60,1,0)+IF(E26>=60,1,0) -> 0 | J26: =IF((MAX(B26:E26)-MIN(B26:E26))>35,"⚠ DIVERGENCE","")
A27: ='Data Input'!A67 -> XLE | B27: ='Data Input'!Z67 -> 0 | C27: ='Data Input'!AA67 -> 0 | D27: ='Data Input'!AB67 -> 0 | E27: ='Asset Analysis'!N15 -> 0 | F27: ='Data Input'!AC67 -> 0 | G27: =IF(AND(F27>=70,I27>=3),"STRONG BUY",IF(AND(F27>=60,I27>=2),"BUY",IF(AND(F27<35),"STRONG SELL",IF(AND(F27<45,I27<=1),"SELL","HOLD")))) -> STRONG SELL | H27: =IF(OR(G27="STRONG BUY",G27="STRONG SELL"),"HIGH",IF(OR(G27="BUY",G27="SELL"),"MEDIUM",IF(G27="HOLD","NEUTRAL","LOW"))) -> HIGH | I27: =IF(B27>=60,1,0)+IF(C27>=60,1,0)+IF(D27>=60,1,0)+IF(E27>=60,1,0) -> 0 | J27: =IF((MAX(B27:E27)-MIN(B27:E27))>35,"⚠ DIVERGENCE","")
... A39: ='Data Input'!A79 -> PIMIX | B39: ='Data Input'!Z79 -> 0 | C39: ='Data Input'!AA79 -> 0 | D39: ='Data Input'!AB79 -> 0 | E39: ='Asset Analysis'!N27 -> 0 | F39: ='Data Input'!AC79 -> 0 | G39: =IF(AND(F39>=70,I39>=3),"STRONG BUY",IF(AND(F39>=60,I39>=2),"BUY",IF(AND(F39<35),"STRONG SELL",IF(AND(F39<45,I39<=1),"SELL","HOLD")))) -> STRONG SELL | H39: =IF(OR(G39="STRONG BUY",G39="STRONG SELL"),"HIGH",IF(OR(G39="BUY",G39="SELL"),"MEDIUM",IF(G39="HOLD","NEUTRAL","LOW"))) -> HIGH | I39: =IF(B39>=60,1,0)+IF(C39>=60,1,0)+IF(D39>=60,1,0)+IF(E39>=60,1,0) -> 0 | J39: =IF((MAX(B39:E39)-MIN(B39:E39))>35,"⚠ DIVERGENCE","")
A41: SUMMARY | F41: =AVERAGE(F16:F39) -> 0
A42: Buy Signals | F42: =COUNTIF(G16:G39,"*BUY*") -> 0
A43: Sell Signals | F43: =COUNTIF(G16:G39,"*SELL*") -> 24
A44: Divergences | F44: =COUNTIF(J16:J39,"*DIV*") -> 0

Sheet Buffered ETF Strategy
A1: BUFFERED ETF ALLOCATION — Regime score drives allocation (all formulas)
A3: REGIME SCORING ENGINE
A4: Component | B4: Input | C4: Score | D4: Max | E4: Logic
A5: Volatility (VIX Input) | B5: ='Data Input'!B21 -> 18 | C5: =IF(B5>30,25,IF(B5>25,22,IF(B5>20,18,IF(B5>15,12,6)))) -> 12 | D5: 25 | E5: VIX>30=25, >25=22, >20=18, >15=12, else 6
A6: FSM Regime | B6: =Dashboard!B10 -> RISK OFF | C6: =IF(B6="RISK OFF",25,IF(B6="DEFENSIVE",20,IF(B6="CAUTION",12,5))) -> 25 | D6: 25 | E6: RISK OFF=25, DEFENSIVE=20, CAUTION=12, else 5
A7: Cash Triggers Active | B7: =COUNTIF(Dashboard!D14:D17,"⚠ TRIGGERED") -> 4 | C7: =MIN(25,B7*7) -> 25 | D7: 25 | E7: 7 pts per trigger, max 25
A8: Trend (% in uptrend) | B8: =Dashboard!B9 -> 0 | C8: =IF(B8<0.3,25,IF(B8<0.4,20,IF(B8<0.5,15,IF(B8<0.6,8,3)))) -> 25 | D8: 25 | E8: <30%=25, <40%=20, <50%=15, <60%=8, else 3
A10: TOTAL REGIME SCORE | C10: =SUM(C5:C8) -> 87 | D10: 100
A11: URGENCY | C11: =IF(C10>=75,"MAXIMUM BUFFER",IF(C10>=55,"ELEVATED BUFFER",IF(C10>=35,"STANDARD BUFFER","MINIMAL / OPPORTUNISTIC"))) -> MAXIMUM BUFFER
C12: =IF(C10>=75,"IMMEDIATE",IF(C10>=55,"THIS WEEK",IF(C10>=35,"NEXT REBALANCE","MONITOR"))) -> IMMEDIATE
A13: TARGET ALLOCATION | B13: =IF(C10>=75,"25-35%",IF(C10>=55,"15-28%",IF(C10>=35,"8-20%","0-12%"))) -> 25-35%
A14: Min % | B14: =IF(C10>=75,0.25,IF(C10>=55,0.15,IF(C10>=35,0.08,0))) -> 0.25
A15: Target % | B15: =IF(C10>=75,0.3,IF(C10>=55,0.22,IF(C10>=35,0.15,0.08))) -> 0.3
A16: Max % | B16: =IF(C10>=75,0.35,IF(C10>=55,0.28,IF(C10>=35,0.2,0.12))) -> 0.35
A17: $ Target | B17: =B15*'Data Input'!B7 -> 0.048
A20: ALLOCATION SCALE
A21: Regime | B21: Score | C21: Allocation | D21: Products | E21: Urgency
A22: MINIMAL | B22: 0-34 | C22: 0-12% | D22: DDT/DDF (high caps), small BUFR | E22: MONITOR
A23: STANDARD | B23: 35-54 | C23: 8-20% | D23: BUFR core, DDSQ/DDNQ tactical | E23: NEXT REBALANCE
A24: ELEVATED | B24: 55-74 | C24: 15-28% | D24: BUFR+DDT, BUFS small cap | E24: THIS WEEK
A25: MAXIMUM | B25: 75-100 | C25: 25-35% | D25: BUFZ deep, DDF 15%, shift eq→buf | E25: IMMEDIATE
A28: PRODUCT UNIVERSE
A29: Ticker | B29: Name | C29: Provider | D29: Reference | E29: Buffer | F29: Period | G29: Type
A30: BUFR | B30: Laddered Moderate Buffer | C30: First Trust | D30: S&P 500 | E30: 15% | F30: 12-mo Ladder | G30: Buffer
A31: BUFZ | B31: Laddered Deep Buffer | C31: First Trust | D31: S&P 500 | E31: 5-30% | F31: 12-mo Ladder | G31: Deep Buffer
A32: BUFS | B32: Small Cap Moderate | C32: First Trust | D32: Russell 2000 | E32: 15% | F32: Quarterly | G32: Buffer
A33: BUFY | B33: Int'l Moderate | C33: First Trust | D33: MSCI EAFE | E33: 15% | F33: Quarterly | G33: Buffer
A34: DDT | B34: Dual Directional 10 | C34: Innovator | D34: S&P 500 | E34: 10% | F34: 1Y Monthly | G34: Dual Dir
A35: DDF | B35: Dual Directional 15 | C35: Innovator | D35: S&P 500 | E35: 15% | F35: 1Y Monthly | G35: Dual Dir
A36: DDSQ | B36: Quarterly DD (SPY) | C36: Innovator | D36: S&P 500 | E36: 5% | F36: 3M Quarterly | G36: Dual Dir
A37: DDNQ | B37: Quarterly DD (QQQ) | C37: Innovator | D37: Nasdaq-100 | E37: 5% | F37: 3M Quarterly | G37: Dual Dir
A40: INTEGRATION TRIGGERS
A41: Trigger | B41: Condition Met? | C41: Action | D41: Products
A42: FSM RISK OFF | B42: =IF(Dashboard!B10="RISK OFF","YES","NO") -> YES | C42: Max buffer 25-35% | D42: BUFZ+DDF
A43: FSM DEFENSIVE | B43: =IF(Dashboard!B10="DEFENSIVE","YES","NO") -> NO | C43: Elevated 15-28% | D43: BUFR+DDT
A44: MMPR50 Triggered | B44: =IF(Dashboard!D14="⚠ TRIGGERED","YES","NO") -> YES | C44: Buffer +5% | D44: BUFR priority
A45: PR4080 Triggered | B45: =IF(Dashboard!D17="⚠ TRIGGERED","YES","NO") -> YES | C45: Emergency: 15% eq→buffer | D45: BUFZ/BUFD deep
A46: Avg Composite ≤ 35 | B46: =IF(AVERAGE('Signal Engine'!F16:F39)<=35,"YES","NO") -> YES | C46: Replace sells w/ buffered | D46: BUFR/DDT
A47: VIX<15 + FULLY INVESTED | B47: =IF(AND(B5<15,Dashboard!B10="FULLY INVESTED"),"YES","NO") -> NO | C47: Optimal entry — lock high caps | D47: DDT/DDF ladder

Sheet Risk Management
A1: RISK MANAGEMENT — Metrics computed from portfolio data
A3: PORTFOLIO RISK METRICS
A4: Metric | B4: Value | C4: Threshold | D4: Status
A5: Wtd Portfolio Vol | B5: =Dashboard!E5 -> 0 | C5: 0.25 | D5: =IF(B5>C5,"⚠ HIGH","OK") -> OK
A6: VaR 95% Daily | B6: =B5*1.645/SQRT(252) -> 0 | C6: 0.025 | D6: =IF(B6>C6,"⚠ BREACH","OK") -> OK
A7: VaR 99% Daily | B7: =B5*2.326/SQRT(252) -> 0 | C7: 0.04 | D7: =IF(B7>C7,"⚠ BREACH","OK") -> OK
A8: CVaR 95% (est) | B8: =B6*1.4 -> 0 | C8: 0.035 | D8: =IF(B8>C8,"⚠ BREACH","OK") -> OK
A9: Portfolio Beta | B9: =Dashboard!K5 -> 0 | C9: 1 | D9: =IF(B9>C9,"⚠ HIGH","OK") -> OK
A10: Avg Max Drawdown | B10: =IFERROR(Dashboard!I5,0) -> 0 | C10: 0.2 | D10: =IF(B10>C10,"⚠ HIGH","OK") -> OK
A11: $ at Risk (95% daily) | B11: =B6*'Data Input'!B7 -> 0 | C11: =C6*'Data Input'!B7 -> 0.004 | D11: =IF(B11>C11,"⚠ BREACH","OK") -> OK
A14: STRESS TESTS
A15: Scenario | B15: Market Shock | C15: Est. Portfolio Impact | D15: $ Loss | E15: Recovery Est.
A16: Market Crash -20% | B16: -0.2 | C16: =B16*Dashboard!$K$5 -> 0 | D16: =C16*'Data Input'!$B$7 -> 0 | E16: =ROUND(ABS(C16)*1000,0)&" days" -> 0 days
A17: Rate Shock +200bp | B17: -0.08 | C17: =B17*Dashboard!$K$5 -> 0 | D17: =C17*'Data Input'!$B$7 -> 0 | E17: =ROUND(ABS(C17)*1000,0)&" days" -> 0 days
A18: Tech Correction -15% | B18: -0.15 | C18: =B18*Dashboard!$K$5 -> 0 | D18: =C18*'Data Input'!$B$7 -> 0 | E18: =ROUND(ABS(C18)*1000,0)&" days" -> 0 days
A19: Recession -12% | B19: -0.12 | C19: =B19*Dashboard!$K$5 -> 0 | D19: =C19*'Data Input'!$B$7 -> 0 | E19: =ROUND(ABS(C19)*1000,0)&" days" -> 0 days
A20: Flash Crash -10% | B20: -0.1 | C20: =B20*Dashboard!$K$5 -> 0 | D20: =C20*'Data Input'!$B$7 -> 0 | E20: =ROUND(ABS(C20)*1000,0)&" days" -> 0 days
A21: Pandemic -30% | B21: -0.3 | C21: =B21*Dashboard!$K$5 -> 0 | D21: =C21*'Data Input'!$B$7 -> 0 | E21: =ROUND(ABS(C21)*1000,0)&" days" -> 0 days
A24: HEDGING RECOMMENDATIONS
A25: Hedge | B25: Allocation | C25: Corr to SPY | D25: Crisis Alpha | E25: Need Level
A26: TAIL | B26: 3-5% | C26: -0.7 | D26: HIGH | E26: MEDIUM
A27: BTAL | B27: 3-7% | C27: -0.5 | D27: MEDIUM | E27: MEDIUM
A28: DBMF | B28: 5-10% | C28: -0.1 | D28: HIGH | E28: HIGH
A29: TLT | B29: 5-15% | C29: -0.3 | D29: MEDIUM | E29: LOW
A30: GLD | B30: 5-10% | C30: 0.05 | D30: MEDIUM | E30: MEDIUM
A31: BUFR/BUFZ | B31: 10-30% | C31: N/A | D31: HIGH | E31: See Buffered ETF tab

Sheet Rebalancing
A1: REBALANCING WORKFLOW — All drift/action computed from Asset Analysis
A3: Ticker | B3: Target% | C3: Current% | D3: Drift | E3: Band | F3: Breach? | G3: Signal | H3: Action | I3: Shares | J3: $ Amount | K3: Tax | L3: Priority
A4: ='Asset Analysis'!A4 -> SPY | B4: ='Asset Analysis'!Q4 -> 0.08 | C4: ='Asset Analysis'!R4 -> 0.09 | D4: =C4-B4 -> 0.01 | E4: ='Data Input'!$B$8 -> 100000 | F4: =IF(ABS(D4)>E4,"YES","NO") -> NO | G4: ='Asset Analysis'!O4 -> SELL | H4: =IF(F4="YES",IF(D4<0,"BUY","SELL"),IF(AND(G4="BUY",D4<0),"ADD",IF(AND(G4="SELL",D4>0),"TRIM","HOLD"))) -> TRIM | I4: =ROUND(J4/100,0) -> 0 | J4: =ABS(D4)*'Data Input'!$B$7 -> 0.0016 | K4: =IF(H4="SELL","Check TLH","N/A") -> N/A | L4: =IF(ABS(D4)>0.03,"HIGH",IF(ABS(D4)>0.015,"MEDIUM","LOW")) -> LOW
A5: ='Asset Analysis'!A5 -> QQQ | B5: ='Asset Analysis'!Q5 -> 0.07 | C5: ='Asset Analysis'!R5 -> 0.065 | D5: =C5-B5 -> -0.005 | E5: ='Data Input'!$B$8 -> 100000 | F5: =IF(ABS(D5)>E5,"YES","NO") -> NO | G5: ='Asset Analysis'!O5 -> SELL | H5: =IF(F5="YES",IF(D5<0,"BUY","SELL"),IF(AND(G5="BUY",D5<0),"ADD",IF(AND(G5="SELL",D5>0),"TRIM","HOLD"))) -> HOLD | I5: =ROUND(J5/100,0) -> 0 | J5: =ABS(D5)*'Data Input'!$B$7 -> 0.0008 | K5: =IF(H5="SELL","Check TLH","N/A") -> N/A | L5: =IF(ABS(D5)>0.03,"HIGH",IF(ABS(D5)>0.015,"MEDIUM","LOW")) -> LOW
A6: ='Asset Analysis'!A6 -> IWM | B6: ='Asset Analysis'!Q6 -> 0.04 | C6: ='Asset Analysis'!R6 -> 0.04 | D6: =C6-B6 -> 0 | E6: ='Data Input'!$B$8 -> 100000 | F6: =IF(ABS(D6)>E6,"YES","NO") -> NO | G6: ='Asset Analysis'!O6 -> SELL | H6: =IF(F6="YES",IF(D6<0,"BUY","SELL"),IF(AND(G6="BUY",D6<0),"ADD",IF(AND(G6="SELL",D6>0),"TRIM","HOLD"))) -> HOLD | I6: =ROUND(J6/100,0) -> 0 | J6: =ABS(D6)*'Data Input'!$B$7 -> 0 | K6: =IF(H6="SELL","Check TLH","N/A") -> N/A | L6: =IF(ABS(D6)>0.03,"HIGH",IF(ABS(D6)>0.015,"MEDIUM","LOW")) -> LOW
A7: ='Asset Analysis'!A7 -> EFA | B7: ='Asset Analysis'!Q7 -> 0.05 | C7: ='Asset Analysis'!R7 -> 0.06 | D7: =C7-B7 -> 0.01 | E7: ='Data Input'!$B$8 -> 100000 | F7: =IF(ABS(D7)>E7,"YES","NO") -> NO | G7: ='Asset Analysis'!O7 -> SELL | H7: =IF(F7="YES",IF(D7<0,"BUY","SELL"),IF(AND(G7="BUY",D7<0),"ADD",IF(AND(G7="SELL",D7>0),"TRIM","HOLD"))) -> TRIM | I7: =ROUND(J7/100,0) -> 0 | J7: =ABS(D7)*'Data Input'!$B$7 -> 0.0016 | K7: =IF(H7="SELL","Check TLH","N/A") -> N/A | L7: =IF(ABS(D7)>0.03,"HIGH",IF(ABS(D7)>0.015,"MEDIUM","LOW")) -> LOW
A8: ='Asset Analysis'!A8 -> EEM | B8: ='Asset Analysis'!Q8 -> 0.03 | C8: ='Asset Analysis'!R8 -> 0.025 | D8: =C8-B8 -> -0.005 | E8: ='Data Input'!$B$8 -> 100000 | F8: =IF(ABS(D8)>E8,"YES","NO") -> NO | G8: ='Asset Analysis'!O8 -> SELL | H8: =IF(F8="YES",IF(D8<0,"BUY","SELL"),IF(AND(G8="BUY",D8<0),"ADD",IF(AND(G8="SELL",D8>0),"TRIM","HOLD"))) -> HOLD | I8: =ROUND(J8/100,0) -> 0 | J8: =ABS(D8)*'Data Input'!$B$7 -> 0.0008 | K8: =IF(H8="SELL","Check TLH","N/A") -> N/A | L8: =IF(ABS(D8)>0.03,"HIGH",IF(ABS(D8)>0.015,"MEDIUM","LOW")) -> LOW
A9: ='Asset Analysis'!A9 -> AGG | B9: ='Asset Analysis'!Q9 -> 0.1 | C9: ='Asset Analysis'!R9 -> 0.1 | D9: =C9-B9 -> 0 | E9: ='Data Input'!$B$8 -> 100000 | F9: =IF(ABS(D9)>E9,"YES","NO") -> NO | G9: ='Asset Analysis'!O9 -> SELL | H9: =IF(F9="YES",IF(D9<0,"BUY","SELL"),IF(AND(G9="BUY",D9<0),"ADD",IF(AND(G9="SELL",D9>0),"TRIM","HOLD"))) -> HOLD | I9: =ROUND(J9/100,0) -> 0 | J9: =ABS(D9)*'Data Input'!$B$7 -> 0 | K9: =IF(H9="SELL","Check TLH","N/A") -> N/A | L9: =IF(ABS(D9)>0.03,"HIGH",IF(ABS(D9)>0.015,"MEDIUM","LOW")) -> LOW
A10: ='Asset Analysis'!A10 -> TLT | B10: ='Asset Analysis'!Q10 -> 0.05 | C10: ='Asset Analysis'!R10 -> 0.06 | D10: =C10-B10 -> 0.01 | E10: ='Data Input'!$B$8 -> 100000 | F10: =IF(ABS(D10)>E10,"YES","NO") -> NO | G10: ='Asset Analysis'!O10 -> SELL | H10: =IF(F10="YES",IF(D10<0,"BUY","SELL"),IF(AND(G10="BUY",D10<0),"ADD",IF(AND(G10="SELL",D10>0),"TRIM","HOLD"))) -> TRIM | I10: =ROUND(J10/100,0) -> 0 | J10: =ABS(D10)*'Data Input'!$B$7 -> 0.0016 | K10: =IF(H10="SELL","Check TLH","N/A") -> N/A | L10: =IF(ABS(D10)>0.03,"HIGH",IF(ABS(D10)>0.015,"MEDIUM","LOW")) -> LOW
A11: ='Asset Analysis'!A11 -> GLD | B11: ='Asset Analysis'!Q11 -> 0.08 | C11: ='Asset Analysis'!R11 -> 0.075 | D11: =C11-B11 -> -0.005 | E11: ='Data Input'!$B$8 -> 100000 | F11: =IF(ABS(D11)>E11,"YES","NO") -> NO | G11: ='Asset Analysis'!O11 -> SELL | H11: =IF(F11="YES",IF(D11<0,"BUY","SELL"),IF(AND(G11="BUY",D11<0),"ADD",IF(AND(G11="SELL",D11>0),"TRIM","HOLD"))) -> HOLD | I11: =ROUND(J11/100,0) -> 0 | J11: =ABS(D11)*'Data Input'!$B$7 -> 0.0008 | K11: =IF(H11="SELL","Check TLH","N/A") -> N/A | L11: =IF(ABS(D11)>0.03,"HIGH",IF(ABS(D11)>0.015,"MEDIUM","LOW")) -> LOW
A12: ='Asset Analysis'!A12 -> VNQ | B12: ='Asset Analysis'!Q12 -> 0.05 | C12: ='Asset Analysis'!R12 -> 0.05 | D12: =C12-B12 -> 0 | E12: ='Data Input'!$B$8 -> 100000 | F12: =IF(ABS(D12)>E12,"YES","NO") -> NO | G12: ='Asset Analysis'!O12 -> SELL | H12: =IF(F12="YES",IF(D12<0,"BUY","SELL"),IF(AND(G12="BUY",D12<0),"ADD",IF(AND(G12="SELL",D12>0),"TRIM","HOLD"))) -> HOLD | I12: =ROUND(J12/100,0) -> 0 | J12: =ABS(D12)*'Data Input'!$B$7 -> 0 | K12: =IF(H12="SELL","Check TLH","N/A") -> N/A | L12: =IF(ABS(D12)>0.03,"HIGH",IF(ABS(D12)>0.015,"MEDIUM","LOW")) -> LOW
A13: ='Asset Analysis'!A13 -> XLK | B13: ='Asset Analysis'!Q13 -> 0.08 | C13: ='Asset Analysis'!R13 -> 0.09 | D13: =C13-B13 -> 0.01 | E13: ='Data Input'!$B$8 -> 100000 | F13: =IF(ABS(D13)>E13,"YES","NO") -> NO | G13: ='Asset Analysis'!O13 -> SELL | H13: =IF(F13="YES",IF(D13<0,"BUY","SELL"),IF(AND(G13="BUY",D13<0),"ADD",IF(AND(G13="SELL",D13>0),"TRIM","HOLD"))) -> TRIM | I13: =ROUND(J13/100,0) -> 0 | J13: =ABS(D13)*'Data Input'!$B$7 -> 0.0016 | K13: =IF(H13="SELL","Check TLH","N/A") -> N/A | L13: =IF(ABS(D13)>0.03,"HIGH",IF(ABS(D13)>0.015,"MEDIUM","LOW")) -> LOW
A14: ='Asset Analysis'!A14 -> XLV | B14: ='Asset Analysis'!Q14 -> 0.04 | C14: ='Asset Analysis'!R14 -> 0.035 | D14: =C14-B14 -> -0.005 | E14: ='Data Input'!$B$8 -> 100000 | F14: =IF(ABS(D14)>E14,"YES","NO") -> NO | G14: ='Asset Analysis'!O14 -> SELL | H14: =IF(F14="YES",IF(D14<0,"BUY","SELL"),IF(AND(G14="BUY",D14<0),"ADD",IF(AND(G14="SELL",D14>0),"TRIM","HOLD"))) -> HOLD | I14: =ROUND(J14/100,0) -> 0 | J14: =ABS(D14)*'Data Input'!$B$7 -> 0.0008 | K14: =IF(H14="SELL","Check TLH","N/A") -> N/A | L14: =IF(ABS(D14)>0.03,"HIGH",IF(ABS(D14)>0.015,"MEDIUM","LOW")) -> LOW
A15: ='Asset Analysis'!A15 -> XLE | B15: ='Asset Analysis'!Q15 -> 0.03 | C15: ='Asset Analysis'!R15 -> 0.03 | D15: =C15-B15 -> 0 | E15: ='Data Input'!$B$8 -> 100000 | F15: =IF(ABS(D15)>E15,"YES","NO") -> NO | G15: ='Asset Analysis'!O15 -> SELL | H15: =IF(F15="YES",IF(D15<0,"BUY","SELL"),IF(AND(G15="BUY",D15<0),"ADD",IF(AND(G15="SELL",D15>0),"TRIM","HOLD"))) -> HOLD | I15: =ROUND(J15/100,0) -> 0 | J15: =ABS(D15)*'Data Input'!$B$7 -> 0 | K15: =IF(H15="SELL","Check TLH","N/A") -> N/A | L15: =IF(ABS(D15)>0.03,"HIGH",IF(ABS(D15)>0.015,"MEDIUM","LOW")) -> LOW
... A27: ='Asset Analysis'!A27 -> PIMIX | B27: ='Asset Analysis'!Q27 -> 0 | C27: ='Asset Analysis'!R27 -> 0 | D27: =C27-B27 -> 0 | E27: ='Data Input'!$B$8 -> 100000 | F27: =IF(ABS(D27)>E27,"YES","NO") -> NO | G27: ='Asset Analysis'!O27 -> SELL | H27: =IF(F27="YES",IF(D27<0,"BUY","SELL"),IF(AND(G27="BUY",D27<0),"ADD",IF(AND(G27="SELL",D27>0),"TRIM","HOLD"))) -> HOLD | I27: =ROUND(J27/100,0) -> 0 | J27: =ABS(D27)*'Data Input'!$B$7 -> 0 | K27: =IF(H27="SELL","Check TLH","N/A") -> N/A | L27: =IF(ABS(D27)>0.03,"HIGH",IF(ABS(D27)>0.015,"MEDIUM","LOW")) -> LOW
A29: Total Trades | J29: =SUM(J4:J27) -> 0.0192
A30: # Rebalance Actions | J30: =COUNTIF(H4:H27,"<>"&"HOLD") -> 8

Sheet Portfolio Construction
A1: STRATEGIC ALLOCATION — Bands & status computed
A3: Asset Class | B3: Min% | C3: Target% | D3: Max% | E3: Current% | F3: Deviation | G3: Status
A4: US Large Cap | B4: 0.15 | C4: 0.3 | D4: 0.45 | E4: 0.3 | F4: =E4-C4 -> 0 | G4: =IF(AND(E4>=B4,E4<=D4),"OK","⚠ OUT OF BAND") -> OK
A5: US Small/Mid | B5: 0 | C5: 0.05 | D5: 0.15 | E5: 0.06 | F5: =E5-C5 -> 0.01 | G5: =IF(AND(E5>=B5,E5<=D5),"OK","⚠ OUT OF BAND") -> OK
A6: Intl Developed | B6: 0.05 | C6: 0.1 | D6: 0.2 | E6: 0.09 | F6: =E6-C6 -> -0.01 | G6: =IF(AND(E6>=B6,E6<=D6),"OK","⚠ OUT OF BAND") -> OK
A7: Emerging Markets | B7: 0 | C7: 0.05 | D7: 0.1 | E7: 0.05 | F7: =E7-C7 -> 0 | G7: =IF(AND(E7>=B7,E7<=D7),"OK","⚠ OUT OF BAND") -> OK
A8: IG Bonds | B8: 0.1 | C8: 0.15 | D8: 0.3 | E8: 0.16 | F8: =E8-C8 -> 0.01 | G8: =IF(AND(E8>=B8,E8<=D8),"OK","⚠ OUT OF BAND") -> OK
A9: Long Treasury | B9: 0 | C9: 0.05 | D9: 0.15 | E9: 0.04 | F9: =E9-C9 -> -0.01 | G9: =IF(AND(E9>=B9,E9<=D9),"OK","⚠ OUT OF BAND") -> OK
A10: REITs | B10: 0 | C10: 0.05 | D10: 0.1 | E10: 0.05 | F10: =E10-C10 -> 0 | G10: =IF(AND(E10>=B10,E10<=D10),"OK","⚠ OUT OF BAND") -> OK
A11: Gold/Commodities | B11: 0 | C11: 0.1 | D11: 0.15 | E11: 0.11 | F11: =E11-C11 -> 0.01 | G11: =IF(AND(E11>=B11,E11<=D11),"OK","⚠ OUT OF BAND") -> OK
A12: Managed Futures | B12: 0 | C12: 0.08 | D12: 0.15 | E12: 0.07 | F12: =E12-C12 -> -0.01 | G12: =IF(AND(E12>=B12,E12<=D12),"OK","⚠ OUT OF BAND") -> OK
A13: Tail Hedges | B13: 0 | C13: 0.03 | D13: 0.07 | E13: 0.03 | F13: =E13-C13 -> 0 | G13: =IF(AND(E13>=B13,E13<=D13),"OK","⚠ OUT OF BAND") -> OK
A14: Cash | B14: 0 | C14: 0.04 | D14: 0.2 | E14: 0.05 | F14: =E14-C14 -> 0.01 | G14: =IF(AND(E14>=B14,E14<=D14),"OK","⚠ OUT OF BAND") -> OK
A15: TOTAL | C15: =SUM(C4:C14) -> 1 | E15: =SUM(E4:E14) -> 1.01

Sheet Trading Desk
A1: TRADING DESK & EXECUTION
A3: INVIOLABLE TRADING PROTOCOLS
A4: 1. Limit Orders Only — No market orders except emergency risk reduction
A5: 2. 5% Daily Limit — No single trade > 5% of portfolio value
A6: 3. DWA Confirmation — No BUY on assets with DWA < 50
A7: 4. Tax-Loss Harvest — Check TLH before any SELL
A8: 5. Cash Trigger Override — If triggered, prioritize risk reduction
A9: 6. OPEX Awareness — No large trades within 2 days of OPEX
A10: 7. Sells Before Buys — All sells executed before buy orders
A11: 8. Post-Trade Verify — Confirm allocations match targets
A12: 9. Buffered ETF Check — Review regime score before equity adds
A15: EXECUTION CHECKLIST
... A27: ☐ Schedule next rebalance

Sheet Screening Universe
A1: SCREENING UNIVERSE — Ticker inventory with auto-scoring & add/delete recommendations
A2: Blue = manual input or YCharts paste | Black = formula | Red = YCharts Add-In formula (auto-populates) | Green = cross-sheet reference
A4: SCREENING THRESHOLDS (adjust these to change recommendations)
A5: Min Sharpe to ADD | B5: 0.5 | C5: B5
A6: Min DWA Score to ADD | B6: 55 | C6: B6
A7: Min Composite to ADD | B7: 55 | C7: B7
A8: Max Vol to ADD | B8: 0.3 | C8: B8
A9: Min Return to ADD | B9: 0.05 | C9: B9
A10: Max Sharpe to DELETE | B10: 0.2 | C10: B10
A11: Max DWA Score to DELETE | B11: 35 | C11: B11
A12: Max Composite to DELETE | B12: 35 | C12: B12
A13: Max Drawdown to DELETE | B13: 0.35 | C13: B13
A16: Ticker | B16: Name | C16: Class | D16: Sub-Class | E16: Price | F16: 1Y Return | G16: 3Y Return | H16: 5Y Return | I16: Volatility | J16: Sharpe | K16: Max DD | L16: Beta | M16: Div Yield | N16: Fwd P/E | O16: 1M Mom | P16: 3M Mom | Q16: 6M Mom | R16: 12M Mom | S16: DWA Score | T16: Trend | U16: Technical | V16: Fundamental | W16: Composite | X16: Signal | Y16: Conviction | Z16: In Portfolio? | AA16: Recommendation | AB16: Priority
A17: SPY | B17: SPDR S&P 500 | C17: US Equity | D17: Large Cap | E17: =IFERROR(ycps("SPY","price"),"") | F17: =IFERROR(ycps("SPY","one_year_return"),"") | G17: =IFERROR(ycps("SPY","three_year_annualized_return"),"") | H17: =IFERROR(ycps("SPY","five_year_annualized_return"),"") | I17: =IFERROR(ycps("SPY","one_year_volatility"),"") | J17: =IFERROR(IF(I17=0,0,(F17-'Data Input'!$B$4)/I17),0) -> 0 | K17: =IFERROR(ycps("SPY","max_drawdown_3_year"),"") | L17: =IFERROR(ycps("SPY","beta_5_year"),"") | M17: =IFERROR(ycps("SPY","dividend_yield"),"") | N17: =IFERROR(ycps("SPY","forward_pe_ratio"),"") | O17: =IFERROR(ycps("SPY","one_month_return"),"") | P17: =IFERROR(ycps("SPY","three_month_return"),"") | Q17: =IFERROR(ycps("SPY","six_month_return"),"") | R17: =IFERROR(ycps("SPY","one_year_return"),"") | S17: =IFERROR(MIN(100,MAX(0,ROUND(50+(O17*0.4+P17*0.3+Q17*0.2+R17*0.1)*200,0))),0) -> 0 | T17: =IFERROR(MIN(100,MAX(0,ROUND(50+R17*150+IF(F17>0,15,0)+IF(L17>0,5,-5),0))),0) -> 0 | U17: =IFERROR(MIN(100,MAX(0,ROUND(50+O17*200+IF(AND(O17>0,P17>0),10,-5)+IF(I17<0.2,10,-5),0))),0) -> 0 | V17: =IFERROR(MIN(100,MAX(0,ROUND(30+IF(I17>0,F17/I17,0)*40+IF(ABS(L17)<0.5,15,0)+IF(F17>0.08,10,0),0))),0) -> 0 | W17: =IFERROR(ROUND(T17*'Data Input'!$B$29+U17*'Data Input'!$B$30+V17*'Data Input'!$B$31+S17*'Data Input'!$B$32,0),0) -> 0 | X17: =IFERROR(IF(AND(W17>=70,IF(T17>=60,1,0)+IF(U17>=60,1,0)+IF(V17>=60,1,0)+IF(S17>=60,1,0)>=3),"STRONG BUY",IF(AND(W17>=60,IF(T17>=60,1,0)+IF(U17>=60,1,0)+IF(V17>=60,1,0)+IF(S17>=60,1,0)>=2),"BUY",IF(W17<35,"STRONG SELL",IF(AND(W17<45,IF(T17>=60,1,0)+IF(U17>=60,1,0)+IF(V17>=60,1,0)+IF(S17>=60,1,0)<=1),"SELL","HOLD")))),"") -> STRONG SELL | Y17: =IFERROR(IF(OR(X17="STRONG BUY",X17="STRONG SELL"),"HIGH",IF(OR(X17="BUY",X17="SELL"),"MEDIUM","NEUTRAL")),"") -> HIGH | Z17: =IFERROR(IF(COUNTIF('Asset Analysis'!$A$4:$A$27,A17)>0,"YES","NO"),"") -> YES | AA17: =IFERROR(IF(AND(Z17="NO",W17>=$B$7,J17>=$B$5,S17>=$B$6,I17<=$B$8,F17>=$B$9),"→ ADD TO PORTFOLIO",IF(AND(Z17="YES",OR(J17<=$B$10,S17<=$B$11,W17<=$B$12,K17<=-$B$13)),"→ DELETE FROM PORTFOLIO",IF(AND(Z17="YES",X17="HOLD"),"HOLD — MONITOR",IF(AND(Z17="YES",OR(X17="BUY",X17="STRONG BUY")),"HOLD — STRONG",IF(Z17="NO","NOT QUALIFIED","REVIEW"))))),"") -> → DELETE FROM PORTFOLIO | AB17: =IFERROR(IF(AA17="→ ADD TO PORTFOLIO",IF(W17>=70,"P1 — IMMEDIATE",IF(W17>=60,"P2 — THIS WEEK","P3 — NEXT REBALANCE")),IF(AA17="→ DELETE FROM PORTFOLIO","P1 — IMMEDIATE","—")),"") -> P1 — IMMEDIATE
A18: VOO | B18: Vanguard S&P 500 | C18: US Equity | D18: Large Cap | E18: =IFERROR(ycps("VOO","price"),"") | F18: =IFERROR(ycps("VOO","one_year_return"),"") | G18: =IFERROR(ycps("VOO","three_year_annualized_return"),"") | H18: =IFERROR(ycps("VOO","five_year_annualized_return"),"") | I18: =IFERROR(ycps("VOO","one_year_volatility"),"") | J18: =IFERROR(IF(I18=0,0,(F18-'Data Input'!$B$4)/I18),0) -> 0 | K18: =IFERROR(ycps("VOO","max_drawdown_3_year"),"") | L18: =IFERROR(ycps("VOO","beta_5_year"),"") | M18: =IFERROR(ycps("VOO","dividend_yield"),"") | N18: =IFERROR(ycps("VOO","forward_pe_ratio"),"") | O18: =IFERROR(ycps("VOO","one_month_return"),"") | P18: =IFERROR(ycps("VOO","three_month_return"),"") | Q18: =IFERROR(ycps("VOO","six_month_return"),"") | R18: =IFERROR(ycps("VOO","one_year_return"),"") | S18: =IFERROR(MIN(100,MAX(0,ROUND(50+(O18*0.4+P18*0.3+Q18*0.2+R18*0.1)*200,0))),0) -> 0 | T18: =IFERROR(MIN(100,MAX(0,ROUND(50+R18*150+IF(F18>0,15,0)+IF(L18>0,5,-5),0))),0) -> 0 | U18: =IFERROR(MIN(100,MAX(0,ROUND(50+O18*200+IF(AND(O18>0,P18>0),10,-5)+IF(I18<0.2,10,-5),0))),0) -> 0 | V18: =IFERROR(MIN(100,MAX(0,ROUND(30+IF(I18>0,F18/I18,0)*40+IF(ABS(L18)<0.5,15,0)+IF(F18>0.08,10,0),0))),0) -> 0 | W18: =IFERROR(ROUND(T18*'Data Input'!$B$29+U18*'Data Input'!$B$30+V18*'Data Input'!$B$31+S18*'Data Input'!$B$32,0),0) -> 0 | X18: =IFERROR(IF(AND(W18>=70,IF(T18>=60,1,0)+IF(U18>=60,1,0)+IF(V18>=60,1,0)+IF(S18>=60,1,0)>=3),"STRONG BUY",IF(AND(W18>=60,IF(T18>=60,1,0)+IF(U18>=60,1,0)+IF(V18>=60,1,0)+IF(S18>=60,1,0)>=2),"BUY",IF(W18<35,"STRONG SELL",IF(AND(W18<45,IF(T18>=60,1,0)+IF(U18>=60,1,0)+IF(V18>=60,1,0)+IF(S18>=60,1,0)<=1),"SELL","HOLD")))),"") -> STRONG SELL | Y18: =IFERROR(IF(OR(X18="STRONG BUY",X18="STRONG SELL"),"HIGH",IF(OR(X18="BUY",X18="SELL"),"MEDIUM","NEUTRAL")),"") -> HIGH | Z18: =IFERROR(IF(COUNTIF('Asset Analysis'!$A$4:$A$27,A18)>0,"YES","NO"),"") -> NO | AA18: =IFERROR(IF(AND(Z18="NO",W18>=$B$7,J18>=$B$5,S18>=$B$6,I18<=$B$8,F18>=$B$9),"→ ADD TO PORTFOLIO",IF(AND(Z18="YES",OR(J18<=$B$10,S18<=$B$11,W18<=$B$12,K18<=-$B$13)),"→ DELETE FROM PORTFOLIO",IF(AND(Z18="YES",X18="HOLD"),"HOLD — MONITOR",IF(AND(Z18="YES",OR(X18="BUY",X18="STRONG BUY")),"HOLD — STRONG",IF(Z18="NO","NOT QUALIFIED","REVIEW"))))),"") -> NOT QUALIFIED | AB18: =IFERROR(IF(AA18="→ ADD TO PORTFOLIO",IF(W18>=70,"P1 — IMMEDIATE",IF(W18>=60,"P2 — THIS WEEK","P3 — NEXT REBALANCE")),IF(AA18="→ DELETE FROM PORTFOLIO","P1 — IMMEDIATE","—")),"") -> —
A19: QQQ | B19: Invesco Nasdaq 100 | C19: US Equity | D19: Large Growth | E19: =IFERROR(ycps("QQQ","price"),"") | F19: =IFERROR(ycps("QQQ","one_year_return"),"") | G19: =IFERROR(ycps("QQQ","three_year_annualized_return"),"") | H19: =IFERROR(ycps("QQQ","five_year_annualized_return"),"") | I19: =IFERROR(ycps("QQQ","one_year_volatility"),"") | J19: =IFERROR(IF(I19=0,0,(F19-'Data Input'!$B$4)/I19),0) -> 0 | K19: =IFERROR(ycps("QQQ","max_drawdown_3_year"),"") | L19: =IFERROR(ycps("QQQ","beta_5_year"),"") | M19: =IFERROR(ycps("QQQ","dividend_yield"),"") | N19: =IFERROR(ycps("QQQ","forward_pe_ratio"),"") | O19: =IFERROR(ycps("QQQ","one_month_return"),"") | P19: =IFERROR(ycps("QQQ","three_month_return"),"") | Q19: =IFERROR(ycps("QQQ","six_month_return"),"") | R19: =IFERROR(ycps("QQQ","one_year_return"),"") | S19: =IFERROR(MIN(100,MAX(0,ROUND(50+(O19*0.4+P19*0.3+Q19*0.2+R19*0.1)*200,0))),0) -> 0 | T19: =IFERROR(MIN(100,MAX(0,ROUND(50+R19*150+IF(F19>0,15,0)+IF(L19>0,5,-5),0))),0) -> 0 | U19: =IFERROR(MIN(100,MAX(0,ROUND(50+O19*200+IF(AND(O19>0,P19>0),10,-5)+IF(I19<0.2,10,-5),0))),0) -> 0 | V19: =IFERROR(MIN(100,MAX(0,ROUND(30+IF(I19>0,F19/I19,0)*40+IF(ABS(L19)<0.5,15,0)+IF(F19>0.08,10,0),0))),0) -> 0 | W19: =IFERROR(ROUND(T19*'Data Input'!$B$29+U19*'Data Input'!$B$30+V19*'Data Input'!$B$31+S19*'Data Input'!$B$32,0),0) -> 0 | X19: =IFERROR(IF(AND(W19>=70,IF(T19>=60,1,0)+IF(U19>=60,1,0)+IF(V19>=60,1,0)+IF(S19>=60,1,0)>=3),"STRONG BUY",IF(AND(W19>=60,IF(T19>=60,1,0)+IF(U19>=60,1,0)+IF(V19>=60,1,0)+IF(S19>=60,1,0)>=2),"BUY",IF(W19<35,"STRONG SELL",IF(AND(W19<45,IF(T19>=60,1,0)+IF(U19>=60,1,0)+IF(V19>=60,1,0)+IF(S19>=60,1,0)<=1),"SELL","HOLD")))),"") -> STRONG SELL | Y19: =IFERROR(IF(OR(X19="STRONG BUY",X19="STRONG SELL"),"HIGH",IF(OR(X19="BUY",X19="SELL"),"MEDIUM","NEUTRAL")),"") -> HIGH | Z19: =IFERROR(IF(COUNTIF('Asset Analysis'!$A$4:$A$27,A19)>0,"YES","NO"),"") -> YES | AA19: =IFERROR(IF(AND(Z19="NO",W19>=$B$7,J19>=$B$5,S19>=$B$6,I19<=$B$8,F19>=$B$9),"→ ADD TO PORTFOLIO",IF(AND(Z19="YES",OR(J19<=$B$10,S19<=$B$11,W19<=$B$12,K19<=-$B$13)),"→ DELETE FROM PORTFOLIO",IF(AND(Z19="YES",X19="HOLD"),"HOLD — MONITOR",IF(AND(Z19="YES",OR(X19="BUY",X19="STRONG BUY")),"HOLD — STRONG",IF(Z19="NO","NOT QUALIFIED","REVIEW"))))),"") -> → DELETE FROM PORTFOLIO | AB19: =IFERROR(IF(AA19="→ ADD TO PORTFOLIO",IF(W19>=70,"P1 — IMMEDIATE",IF(W19>=60,"P2 — THIS WEEK","P3 — NEXT REBALANCE")),IF(AA19="→ DELETE FROM PORTFOLIO","P1 — IMMEDIATE","—")),"") -> P1 — IMMEDIATE
A20: VTI | B20: Vanguard Total Stock | C20: US Equity | D20: Broad | E20: =IFERROR(ycps("VTI","price"),"") | F20: =IFERROR(ycps("VTI","one_year_return"),"") | G20: =IFERROR(ycps("VTI","three_year_annualized_return"),"") | H20: =IFERROR(ycps("VTI","five_year_annualized_return"),"") | I20: =IFERROR(ycps("VTI","one_year_volatility"),"") | J20: =IFERROR(IF(I20=0,0,(F20-'Data Input'!$B$4)/I20),0) -> 0 | K20: =IFERROR(ycps("VTI","max_drawdown_3_year"),"") | L20: =IFERROR(ycps("VTI","beta_5_year"),"") | M20: =IFERROR(ycps("VTI","dividend_yield"),"") | N20: =IFERROR(ycps("VTI","forward_pe_ratio"),"") | O20: =IFERROR(ycps("VTI","one_month_return"),"") | P20: =IFERROR(ycps("VTI","three_month_return"),"") | Q20: =IFERROR(ycps("VTI","six_month_return"),"") | R20: =IFERROR(ycps("VTI","one_year_return"),"") | S20: =IFERROR(MIN(100,MAX(0,ROUND(50+(O20*0.4+P20*0.3+Q20*0.2+R20*0.1)*200,0))),0) -> 0 | T20: =IFERROR(MIN(100,MAX(0,ROUND(50+R20*150+IF(F20>0,15,0)+IF(L20>0,5,-5),0))),0) -> 0 | U20: =IFERROR(MIN(100,MAX(0,ROUND(50+O20*200+IF(AND(O20>0,P20>0),10,-5)+IF(I20<0.2,10,-5),0))),0) -> 0 | V20: =IFERROR(MIN(100,MAX(0,ROUND(30+IF(I20>0,F20/I20,0)*40+IF(ABS(L20)<0.5,15,0)+IF(F20>0.08,10,0),0))),0) -> 0 | W20: =IFERROR(ROUND(T20*'Data Input'!$B$29+U20*'Data Input'!$B$30+V20*'Data Input'!$B$31+S20*'Data Input'!$B$32,0),0) -> 0 | X20: =IFERROR(IF(AND(W20>=70,IF(T20>=60,1,0)+IF(U20>=60,1,0)+IF(V20>=60,1,0)+IF(S20>=60,1,0)>=3),"STRONG BUY",IF(AND(W20>=60,IF(T20>=60,1,0)+IF(U20>=60,1,0)+IF(V20>=60,1,0)+IF(S20>=60,1,0)>=2),"BUY",IF(W20<35,"STRONG SELL",IF(AND(W20<45,IF(T20>=60,1,0)+IF(U20>=60,1,0)+IF(V20>=60,1,0)+IF(S20>=60,1,0)<=1),"SELL","HOLD")))),"") -> STRONG SELL | Y20: =IFERROR(IF(OR(X20="STRONG BUY",X20="STRONG SELL"),"HIGH",IF(OR(X20="BUY",X20="SELL"),"MEDIUM","NEUTRAL")),"") -> HIGH | Z20: =IFERROR(IF(COUNTIF('Asset Analysis'!$A$4:$A$27,A20)>0,"YES","NO"),"") -> NO | AA20: =IFERROR(IF(AND(Z20="NO",W20>=$B$7,J20>=$B$5,S20>=$B$6,I20<=$B$8,F20>=$B$9),"→ ADD TO PORTFOLIO",IF(AND(Z20="YES",OR(J20<=$B$10,S20<=$B$11,W20<=$B$12,K20<=-$B$13)),"→ DELETE FROM PORTFOLIO",IF(AND(Z20="YES",X20="HOLD"),"HOLD — MONITOR",IF(AND(Z20="YES",OR(X20="BUY",X20="STRONG BUY")),"HOLD — STRONG",IF(Z20="NO","NOT QUALIFIED","REVIEW"))))),"") -> NOT QUALIFIED | AB20: =IFERROR(IF(AA20="→ ADD TO PORTFOLIO",IF(W20>=70,"P1 — IMMEDIATE",IF(W20>=60,"P2 — THIS WEEK","P3 — NEXT REBALANCE")),IF(AA20="→ DELETE FROM PORTFOLIO","P1 — IMMEDIATE","—")),"") -> —
A21: IVV | B21: iShares Core S&P 500 | C21: US Equity | D21: Large Cap | E21: =IFERROR(ycps("IVV","price"),"") | F21: =IFERROR(ycps("IVV","one_year_return"),"") | G21: =IFERROR(ycps("IVV","three_year_annualized_return"),"") | H21: =IFERROR(ycps("IVV","five_year_annualized_return"),"") | I21: =IFERROR(ycps("IVV","one_year_volatility"),"") | J21: =IFERROR(IF(I21=0,0,(F21-'Data Input'!$B$4)/I21),0) -> 0 | K21: =IFERROR(ycps("IVV","max_drawdown_3_year"),"") | L21: =IFERROR(ycps("IVV","beta_5_year"),"") | M21: =IFERROR(ycps("IVV","dividend_yield"),"") | N21: =IFERROR(ycps("IVV","forward_pe_ratio"),"") | O21: =IFERROR(ycps("IVV","one_month_return"),"") | P21: =IFERROR(ycps("IVV","three_month_return"),"") | Q21: =IFERROR(ycps("IVV","six_month_return"),"") | R21: =IFERROR(ycps("IVV","one_year_return"),"") | S21: =IFERROR(MIN(100,MAX(0,ROUND(50+(O21*0.4+P21*0.3+Q21*0.2+R21*0.1)*200,0))),0) -> 0 | T21: =IFERROR(MIN(100,MAX(0,ROUND(50+R21*150+IF(F21>0,15,0)+IF(L21>0,5,-5),0))),0) -> 0 | U21: =IFERROR(MIN(100,MAX(0,ROUND(50+O21*200+IF(AND(O21>0,P21>0),10,-5)+IF(I21<0.2,10,-5),0))),0) -> 0 | V21: =IFERROR(MIN(100,MAX(0,ROUND(30+IF(I21>0,F21/I21,0)*40+IF(ABS(L21)<0.5,15,0)+IF(F21>0.08,10,0),0))),0) -> 0 | W21: =IFERROR(ROUND(T21*'Data Input'!$B$29+U21*'Data Input'!$B$30+V21*'Data Input'!$B$31+S21*'Data Input'!$B$32,0),0) -> 0 | X21: =IFERROR(IF(AND(W21>=70,IF(T21>=60,1,0)+IF(U21>=60,1,0)+IF(V21>=60,1,0)+IF(S21>=60,1,0)>=3),"STRONG BUY",IF(AND(W21>=60,IF(T21>=60,1,0)+IF(U21>=60,1,0)+IF(V21>=60,1,0)+IF(S21>=60,1,0)>=2),"BUY",IF(W21<35,"STRONG SELL",IF(AND(W21<45,IF(T21>=60,1,0)+IF(U21>=60,1,0)+IF(V21>=60,1,0)+IF(S21>=60,1,0)<=1),"SELL","HOLD")))),"") -> STRONG SELL | Y21: =IFERROR(IF(OR(X21="STRONG BUY",X21="STRONG SELL"),"HIGH",IF(OR(X21="BUY",X21="SELL"),"MEDIUM","NEUTRAL")),"") -> HIGH | Z21: =IFERROR(IF(COUNTIF('Asset Analysis'!$A$4:$A$27,A21)>0,"YES","NO"),"") -> NO | AA21: =IFERROR(IF(AND(Z21="NO",W21>=$B$7,J21>=$B$5,S21>=$B$6,I21<=$B$8,F21>=$B$9),"→ ADD TO PORTFOLIO",IF(AND(Z21="YES",OR(J21<=$B$10,S21<=$B$11,W21<=$B$12,K21<=-$B$13)),"→ DELETE FROM PORTFOLIO",IF(AND(Z21="YES",X21="HOLD"),"HOLD — MONITOR",IF(AND(Z21="YES",OR(X21="BUY",X21="STRONG BUY")),"HOLD — STRONG",IF(Z21="NO","NOT QUALIFIED","REVIEW"))))),"") -> NOT QUALIFIED | AB21: =IFERROR(IF(AA21="→ ADD TO PORTFOLIO",IF(W21>=70,"P1 — IMMEDIATE",IF(W21>=60,"P2 — THIS WEEK","P3 — NEXT REBALANCE")),IF(AA21="→ DELETE FROM PORTFOLIO","P1 — IMMEDIATE","—")),"") -> —
A22: RSP | B22: Invesco Equal Weight S&P | C22: US Equity | D22: Equal Wt | E22: =IFERROR(ycps("RSP","price"),"") | F22: =IFERROR(ycps("RSP","one_year_return"),"") | G22: =IFERROR(ycps("RSP","three_year_annualized_return"),"") | H22: =IFERROR(ycps("RSP","five_year_annualized_return"),"") | I22: =IFERROR(ycps("RSP","one_year_volatility"),"") | J22: =IFERROR(IF(I22=0,0,(F22-'Data Input'!$B$4)/I22),0) -> 0 | K22: =IFERROR(ycps("RSP","max_drawdown_3_year"),"") | L22: =IFERROR(ycps("RSP","beta_5_year"),"") | M22: =IFERROR(ycps("RSP","dividend_yield"),"") | N22: =IFERROR(ycps("RSP","forward_pe_ratio"),"") | O22: =IFERROR(ycps("RSP","one_month_return"),"") | P22: =IFERROR(ycps("RSP","three_month_return"),"") | Q22: =IFERROR(ycps("RSP","six_month_return"),"") | R22: =IFERROR(ycps("RSP","one_year_return"),"") | S22: =IFERROR(MIN(100,MAX(0,ROUND(50+(O22*0.4+P22*0.3+Q22*0.2+R22*0.1)*200,0))),0) -> 0 | T22: =IFERROR(MIN(100,MAX(0,ROUND(50+R22*150+IF(F22>0,15,0)+IF(L22>0,5,-5),0))),0) -> 0 | U22: =IFERROR(MIN(100,MAX(0,ROUND(50+O22*200+IF(AND(O22>0,P22>0),10,-5)+IF(I22<0.2,10,-5),0))),0) -> 0 | V22: =IFERROR(MIN(100,MAX(0,ROUND(30+IF(I22>0,F22/I22,0)*40+IF(ABS(L22)<0.5,15,0)+IF(F22>0.08,10,0),0))),0) -> 0 | W22: =IFERROR(ROUND(T22*'Data Input'!$B$29+U22*'Data Input'!$B$30+V22*'Data Input'!$B$31+S22*'Data Input'!$B$32,0),0) -> 0 | X22: =IFERROR(IF(AND(W22>=70,IF(T22>=60,1,0)+IF(U22>=60,1,0)+IF(V22>=60,1,0)+IF(S22>=60,1,0)>=3),"STRONG BUY",IF(AND(W22>=60,IF(T22>=60,1,0)+IF(U22>=60,1,0)+IF(V22>=60,1,0)+IF(S22>=60,1,0)>=2),"BUY",IF(W22<35,"STRONG SELL",IF(AND(W22<45,IF(T22>=60,1,0)+IF(U22>=60,1,0)+IF(V22>=60,1,0)+IF(S22>=60,1,0)<=1),"SELL","HOLD")))),"") -> STRONG SELL | Y22: =IFERROR(IF(OR(X22="STRONG BUY",X22="STRONG SELL"),"HIGH",IF(OR(X22="BUY",X22="SELL"),"MEDIUM","NEUTRAL")),"") -> HIGH | Z22: =IFERROR(IF(COUNTIF('Asset Analysis'!$A$4:$A$27,A22)>0,"YES","NO"),"") -> NO | AA22: =IFERROR(IF(AND(Z22="NO",W22>=$B$7,J22>=$B$5,S22>=$B$6,I22<=$B$8,F22>=$B$9),"→ ADD TO PORTFOLIO",IF(AND(Z22="YES",OR(J22<=$B$10,S22<=$B$11,W22<=$B$12,K22<=-$B$13)),"→ DELETE FROM PORTFOLIO",IF(AND(Z22="YES",X22="HOLD"),"HOLD — MONITOR",IF(AND(Z22="YES",OR(X22="BUY",X22="STRONG BUY")),"HOLD — STRONG",IF(Z22="NO","NOT QUALIFIED","REVIEW"))))),"") -> NOT QUALIFIED | AB22: =IFERROR(IF(AA22="→ ADD TO PORTFOLIO",IF(W22>=70,"P1 — IMMEDIATE",IF(W22>=60,"P2 — THIS WEEK","P3 — NEXT REBALANCE")),IF(AA22="→ DELETE FROM PORTFOLIO","P1 — IMMEDIATE","—")),"") -> —
A23: SCHD | B23: Schwab US Dividend | C23: US Equity | D23: Dividend | E23: =IFERROR(ycps("SCHD","price"),"") | F23: =IFERROR(ycps("SCHD","one_year_return"),"") | G23: =IFERROR(ycps("SCHD","three_year_annualized_return"),"") | H23: =IFERROR(ycps("SCHD","five_year_annualized_return"),"") | I23: =IFERROR(ycps("SCHD","one_year_volatility"),"") | J23: =IFERROR(IF(I23=0,0,(F23-'Data Input'!$B$4)/I23),0) -> 0 | K23: =IFERROR(ycps("SCHD","max_drawdown_3_year"),"") | L23: =IFERROR(ycps("SCHD","beta_5_year"),"") | M23: =IFERROR(ycps("SCHD","dividend_yield"),"") | N23: =IFERROR(ycps("SCHD","forward_pe_ratio"),"") | O23: =IFERROR(ycps("SCHD","one_month_return"),"") | P23: =IFERROR(ycps("SCHD","three_month_return"),"") | Q23: =IFERROR(ycps("SCHD","six_month_return"),"") | R23: =IFERROR(ycps("SCHD","one_year_return"),"") | S23: =IFERROR(MIN(100,MAX(0,ROUND(50+(O23*0.4+P23*0.3+Q23*0.2+R23*0.1)*200,0))),0) -> 0 | T23: =IFERROR(MIN(100,MAX(0,ROUND(50+R23*150+IF(F23>0,15,0)+IF(L23>0,5,-5),0))),0) -> 0 | U23: =IFERROR(MIN(100,MAX(0,ROUND(50+O23*200+IF(AND(O23>0,P23>0),10,-5)+IF(I23<0.2,10,-5),0))),0) -> 0 | V23: =IFERROR(MIN(100,MAX(0,ROUND(30+IF(I23>0,F23/I23,0)*40+IF(ABS(L23)<0.5,15,0)+IF(F23>0.08,10,0),0))),0) -> 0 | W23: =IFERROR(ROUND(T23*'Data Input'!$B$29+U23*'Data Input'!$B$30+V23*'Data Input'!$B$31+S23*'Data Input'!$B$32,0),0) -> 0 | X23: =IFERROR(IF(AND(W23>=70,IF(T23>=60,1,0)+IF(U23>=60,1,0)+IF(V23>=60,1,0)+IF(S23>=60,1,0)>=3),"STRONG BUY",IF(AND(W23>=60,IF(T23>=60,1,0)+IF(U23>=60,1,0)+IF(V23>=60,1,0)+IF(S23>=60,1,0)>=2),"BUY",IF(W23<35,"STRONG SELL",IF(AND(W23<45,IF(T23>=60,1,0)+IF(U23>=60,1,0)+IF(V23>=60,1,0)+IF(S23>=60,1,0)<=1),"SELL","HOLD")))),"") -> STRONG SELL | Y23: =IFERROR(IF(OR(X23="STRONG BUY",X23="STRONG SELL"),"HIGH",IF(OR(X23="BUY",X23="SELL"),"MEDIUM","NEUTRAL")),"") -> HIGH | Z23: =IFERROR(IF(COUNTIF('Asset Analysis'!$A$4:$A$27,A23)>0,"YES","NO"),"") -> NO | AA23: =IFERROR(IF(AND(Z23="NO",W23>=$B$7,J23>=$B$5,S23>=$B$6,I23<=$B$8,F23>=$B$9),"→ ADD TO PORTFOLIO",IF(AND(Z23="YES",OR(J23<=$B$10,S23<=$B$11,W23<=$B$12,K23<=-$B$13)),"→ DELETE FROM PORTFOLIO",IF(AND(Z23="YES",X23="HOLD"),"HOLD — MONITOR",IF(AND(Z23="YES",OR(X23="BUY",X23="STRONG BUY")),"HOLD — STRONG",IF(Z23="NO","NOT QUALIFIED","REVIEW"))))),"") -> NOT QUALIFIED | AB23: =IFERROR(IF(AA23="→ ADD TO PORTFOLIO",IF(W23>=70,"P1 — IMMEDIATE",IF(W23>=60,"P2 — THIS WEEK","P3 — NEXT REBALANCE")),IF(AA23="→ DELETE FROM PORTFOLIO","P1 — IMMEDIATE","—")),"") -> —
A24: VIG | B24: Vanguard Div Appreciation | C24: US Equity | D24: Dividend | E24: =IFERROR(ycps("VIG","price"),"") | F24: =IFERROR(ycps("VIG","one_year_return"),"") | G24: =IFERROR(ycps("VIG","three_year_annualized_return"),"") | H24: =IFERROR(ycps("VIG","five_year_annualized_return"),"") | I24: =IFERROR(ycps("VIG","one_year_volatility"),"") | J24: =IFERROR(IF(I24=0,0,(F24-'Data Input'!$B$4)/I24),0) -> 0 | K24: =IFERROR(ycps("VIG","max_drawdown_3_year"),"") | L24: =IFERROR(ycps("VIG","beta_5_year"),"") | M24: =IFERROR(ycps("VIG","dividend_yield"),"") | N24: =IFERROR(ycps("VIG","forward_pe_ratio"),"") | O24: =IFERROR(ycps("VIG","one_month_return"),"") | P24: =IFERROR(ycps("VIG","three_month_return"),"") | Q24: =IFERROR(ycps("VIG","six_month_return"),"") | R24: =IFERROR(ycps("VIG","one_year_return"),"") | S24: =IFERROR(MIN(100,MAX(0,ROUND(50+(O24*0.4+P24*0.3+Q24*0.2+R24*0.1)*200,0))),0) -> 0 | T24: =IFERROR(MIN(100,MAX(0,ROUND(50+R24*150+IF(F24>0,15,0)+IF(L24>0,5,-5),0))),0) -> 0 | U24: =IFERROR(MIN(100,MAX(0,ROUND(50+O24*200+IF(AND(O24>0,P24>0),10,-5)+IF(I24<0.2,10,-5),0))),0) -> 0 | V24: =IFERROR(MIN(100,MAX(0,ROUND(30+IF(I24>0,F24/I24,0)*40+IF(ABS(L24)<0.5,15,0)+IF(F24>0.08,10,0),0))),0) -> 0 | W24: =IFERROR(ROUND(T24*'Data Input'!$B$29+U24*'Data Input'!$B$30+V24*'Data Input'!$B$31+S24*'Data Input'!$B$32,0),0) -> 0 | X24: =IFERROR(IF(AND(W24>=70,IF(T24>=60,1,0)+IF(U24>=60,1,0)+IF(V24>=60,1,0)+IF(S24>=60,1,0)>=3),"STRONG BUY",IF(AND(W24>=60,IF(T24>=60,1,0)+IF(U24>=60,1,0)+IF(V24>=60,1,0)+IF(S24>=60,1,0)>=2),"BUY",IF(W24<35,"STRONG SELL",IF(AND(W24<45,IF(T24>=60,1,0)+IF(U24>=60,1,0)+IF(V24>=60,1,0)+IF(S24>=60,1,0)<=1),"SELL","HOLD")))),"") -> STRONG SELL | Y24: =IFERROR(IF(OR(X24="STRONG BUY",X24="STRONG SELL"),"HIGH",IF(OR(X24="BUY",X24="SELL"),"MEDIUM","NEUTRAL")),"") -> HIGH | Z24: =IFERROR(IF(COUNTIF('Asset Analysis'!$A$4:$A$27,A24)>0,"YES","NO"),"") -> NO | AA24: =IFERROR(IF(AND(Z24="NO",W24>=$B$7,J24>=$B$5,S24>=$B$6,I24<=$B$8,F24>=$B$9),"→ ADD TO PORTFOLIO",IF(AND(Z24="YES",OR(J24<=$B$10,S24<=$B$11,W24<=$B$12,K24<=-$B$13)),"→ DELETE FROM PORTFOLIO",IF(AND(Z24="YES",X24="HOLD"),"HOLD — MONITOR",IF(AND(Z24="YES",OR(X24="BUY",X24="STRONG BUY")),"HOLD — STRONG",IF(Z24="NO","NOT QUALIFIED","REVIEW"))))),"") -> NOT QUALIFIED | AB24: =IFERROR(IF(AA24="→ ADD TO PORTFOLIO",IF(W24>=70,"P1 — IMMEDIATE",IF(W24>=60,"P2 — THIS WEEK","P3 — NEXT REBALANCE")),IF(AA24="→ DELETE FROM PORTFOLIO","P1 — IMMEDIATE","—")),"") -> —
A25: DGRO | B25: iShares Dividend Growth | C25: US Equity | D25: Dividend | E25: =IFERROR(ycps("DGRO","price"),"") | F25: =IFERROR(ycps("DGRO","one_year_return"),"") | G25: =IFERROR(ycps("DGRO","three_year_annualized_return"),"") | H25: =IFERROR(ycps("DGRO","five_year_annualized_return"),"") | I25: =IFERROR(ycps("DGRO","one_year_volatility"),"") | J25: =IFERROR(IF(I25=0,0,(F25-'Data Input'!$B$4)/I25),0) -> 0 | K25: =IFERROR(ycps("DGRO","max_drawdown_3_year"),"") | L25: =IFERROR(ycps("DGRO","beta_5_year"),"") | M25: =IFERROR(ycps("DGRO","dividend_yield"),"") | N25: =IFERROR(ycps("DGRO","forward_pe_ratio"),"") | O25: =IFERROR(ycps("DGRO","one_month_return"),"") | P25: =IFERROR(ycps("DGRO","three_month_return"),"") | Q25: =IFERROR(ycps("DGRO","six_month_return"),"") | R25: =IFERROR(ycps("DGRO","one_year_return"),"") | S25: =IFERROR(MIN(100,MAX(0,ROUND(50+(O25*0.4+P25*0.3+Q25*0.2+R25*0.1)*200,0))),0) -> 0 | T25: =IFERROR(MIN(100,MAX(0,ROUND(50+R25*150+IF(F25>0,15,0)+IF(L25>0,5,-5),0))),0) -> 0 | U25: =IFERROR(MIN(100,MAX(0,ROUND(50+O25*200+IF(AND(O25>0,P25>0),10,-5)+IF(I25<0.2,10,-5),0))),0) -> 0 | V25: =IFERROR(MIN(100,MAX(0,ROUND(30+IF(I25>0,F25/I25,0)*40+IF(ABS(L25)<0.5,15,0)+IF(F25>0.08,10,0),0))),0) -> 0 | W25: =IFERROR(ROUND(T25*'Data Input'!$B$29+U25*'Data Input'!$B$30+V25*'Data Input'!$B$31+S25*'Data Input'!$B$32,0),0) -> 0 | X25: =IFERROR(IF(AND(W25>=70,IF(T25>=60,1,0)+IF(U25>=60,1,0)+IF(V25>=60,1,0)+IF(S25>=60,1,0)>=3),"STRONG BUY",IF(AND(W25>=60,IF(T25>=60,1,0)+IF(U25>=60,1,0)+IF(V25>=60,1,0)+IF(S25>=60,1,0)>=2),"BUY",IF(W25<35,"STRONG SELL",IF(AND(W25<45,IF(T25>=60,1,0)+IF(U25>=60,1,0)+IF(V25>=60,1,0)+IF(S25>=60,1,0)<=1),"SELL","HOLD")))),"") -> STRONG SELL | Y25: =IFERROR(IF(OR(X25="STRONG BUY",X25="STRONG SELL"),"HIGH",IF(OR(X25="BUY",X25="SELL"),"MEDIUM","NEUTRAL")),"") -> HIGH | Z25: =IFERROR(IF(COUNTIF('Asset Analysis'!$A$4:$A$27,A25)>0,"YES","NO"),"") -> NO | AA25: =IFERROR(IF(AND(Z25="NO",W25>=$B$7,J25>=$B$5,S25>=$B$6,I25<=$B$8,F25>=$B$9),"→ ADD TO PORTFOLIO",IF(AND(Z25="YES",OR(J25<=$B$10,S25<=$B$11,W25<=$B$12,K25<=-$B$13)),"→ DELETE FROM PORTFOLIO",IF(AND(Z25="YES",X25="HOLD"),"HOLD — MONITOR",IF(AND(Z25="YES",OR(X25="BUY",X25="STRONG BUY")),"HOLD — STRONG",IF(Z25="NO","NOT QUALIFIED","REVIEW"))))),"") -> NOT QUALIFIED | AB25: =IFERROR(IF(AA25="→ ADD TO PORTFOLIO",IF(W25>=70,"P1 — IMMEDIATE",IF(W25>=60,"P2 — THIS WEEK","P3 — NEXT REBALANCE")),IF(AA25="→ DELETE FROM PORTFOLIO","P1 — IMMEDIATE","—")),"") -> —
A26: DGRW | B26: WisdomTree Growth | C26: US Equity | D26: Quality Growth | E26: =IFERROR(ycps("DGRW","price"),"") | F26: =IFERROR(ycps("DGRW","one_year_return"),"") | G26: =IFERROR(ycps("DGRW","three_year_annualized_return"),"") | H26: =IFERROR(ycps("DGRW","five_year_annualized_return"),"") | I26: =IFERROR(ycps("DGRW","one_year_volatility"),"") | J26: =IFERROR(IF(I26=0,0,(F26-'Data Input'!$B$4)/I26),0) -> 0 | K26: =IFERROR(ycps("DGRW","max_drawdown_3_year"),"") | L26: =IFERROR(ycps("DGRW","beta_5_year"),"") | M26: =IFERROR(ycps("DGRW","dividend_yield"),"") | N26: =IFERROR(ycps("DGRW","forward_pe_ratio"),"") | O26: =IFERROR(ycps("DGRW","one_month_return"),"") | P26: =IFERROR(ycps("DGRW","three_month_return"),"") | Q26: =IFERROR(ycps("DGRW","six_month_return"),"") | R26: =IFERROR(ycps("DGRW","one_year_return"),"") | S26: =IFERROR(MIN(100,MAX(0,ROUND(50+(O26*0.4+P26*0.3+Q26*0.2+R26*0.1)*200,0))),0) -> 0 | T26: =IFERROR(MIN(100,MAX(0,ROUND(50+R26*150+IF(F26>0,15,0)+IF(L26>0,5,-5),0))),0) -> 0 | U26: =IFERROR(MIN(100,MAX(0,ROUND(50+O26*200+IF(AND(O26>0,P26>0),10,-5)+IF(I26<0.2,10,-5),0))),0) -> 0 | V26: =IFERROR(MIN(100,MAX(0,ROUND(30+IF(I26>0,F26/I26,0)*40+IF(ABS(L26)<0.5,15,0)+IF(F26>0.08,10,0),0))),0) -> 0 | W26: =IFERROR(ROUND(T26*'Data Input'!$B$29+U26*'Data Input'!$B$30+V26*'Data Input'!$B$31+S26*'Data Input'!$B$32,0),0) -> 0 | X26: =IFERROR(IF(AND(W26>=70,IF(T26>=60,1,0)+IF(U26>=60,1,0)+IF(V26>=60,1,0)+IF(S26>=60,1,0)>=3),"STRONG BUY",IF(AND(W26>=60,IF(T26>=60,1,0)+IF(U26>=60,1,0)+IF(V26>=60,1,0)+IF(S26>=60,1,0)>=2),"BUY",IF(W26<35,"STRONG SELL",IF(AND(W26<45,IF(T26>=60,1,0)+IF(U26>=60,1,0)+IF(V26>=60,1,0)+IF(S26>=60,1,0)<=1),"SELL","HOLD")))),"") -> STRONG SELL | Y26: =IFERROR(IF(OR(X26="STRONG BUY",X26="STRONG SELL"),"HIGH",IF(OR(X26="BUY",X26="SELL"),"MEDIUM","NEUTRAL")),"") -> HIGH | Z26: =IFERROR(IF(COUNTIF('Asset Analysis'!$A$4:$A$27,A26)>0,"YES","NO"),"") -> NO | AA26: =IFERROR(IF(AND(Z26="NO",W26>=$B$7,J26>=$B$5,S26>=$B$6,I26<=$B$8,F26>=$B$9),"→ ADD TO PORTFOLIO",IF(AND(Z26="YES",OR(J26<=$B$10,S26<=$B$11,W26<=$B$12,K26<=-$B$13)),"→ DELETE FROM PORTFOLIO",IF(AND(Z26="YES",X26="HOLD"),"HOLD — MONITOR",IF(AND(Z26="YES",OR(X26="BUY",X26="STRONG BUY")),"HOLD — STRONG",IF(Z26="NO","NOT QUALIFIED","REVIEW"))))),"") -> NOT QUALIFIED | AB26: =IFERROR(IF(AA26="→ ADD TO PORTFOLIO",IF(W26>=70,"P1 — IMMEDIATE",IF(W26>=60,"P2 — THIS WEEK","P3 — NEXT REBALANCE")),IF(AA26="→ DELETE FROM PORTFOLIO","P1 — IMMEDIATE","—")),"") -> —
A27: XLK | B27: Technology Select | C27: Sector | D27: Technology | E27: =IFERROR(ycps("XLK","price"),"") | F27: =IFERROR(ycps("XLK","one_year_return"),"") | G27: =IFERROR(ycps("XLK","three_year_annualized_return"),"") | H27: =IFERROR(ycps("XLK","five_year_annualized_return"),"") | I27: =IFERROR(ycps("XLK","one_year_volatility"),"") | J27: =IFERROR(IF(I27=0,0,(F27-'Data Input'!$B$4)/I27),0) -> 0 | K27: =IFERROR(ycps("XLK","max_drawdown_3_year"),"") | L27: =IFERROR(ycps("XLK","beta_5_year"),"") | M27: =IFERROR(ycps("XLK","dividend_yield"),"") | N27: =IFERROR(ycps("XLK","forward_pe_ratio"),"") | O27: =IFERROR(ycps("XLK","one_month_return"),"") | P27: =IFERROR(ycps("XLK","three_month_return"),"") | Q27: =IFERROR(ycps("XLK","six_month_return"),"") | R27: =IFERROR(ycps("XLK","one_year_return"),"") | S27: =IFERROR(MIN(100,MAX(0,ROUND(50+(O27*0.4+P27*0.3+Q27*0.2+R27*0.1)*200,0))),0) -> 0 | T27: =IFERROR(MIN(100,MAX(0,ROUND(50+R27*150+IF(F27>0,15,0)+IF(L27>0,5,-5),0))),0) -> 0 | U27: =IFERROR(MIN(100,MAX(0,ROUND(50+O27*200+IF(AND(O27>0,P27>0),10,-5)+IF(I27<0.2,10,-5),0))),0) -> 0 | V27: =IFERROR(MIN(100,MAX(0,ROUND(30+IF(I27>0,F27/I27,0)*40+IF(ABS(L27)<0.5,15,0)+IF(F27>0.08,10,0),0))),0) -> 0 | W27: =IFERROR(ROUND(T27*'Data Input'!$B$29+U27*'Data Input'!$B$30+V27*'Data Input'!$B$31+S27*'Data Input'!$B$32,0),0) -> 0 | X27: =IFERROR(IF(AND(W27>=70,IF(T27>=60,1,0)+IF(U27>=60,1,0)+IF(V27>=60,1,0)+IF(S27>=60,1,0)>=3),"STRONG BUY",IF(AND(W27>=60,IF(T27>=60,1,0)+IF(U27>=60,1,0)+IF(V27>=60,1,0)+IF(S27>=60,1,0)>=2),"BUY",IF(W27<35,"STRONG SELL",IF(AND(W27<45,IF(T27>=60,1,0)+IF(U27>=60,1,0)+IF(V27>=60,1,0)+IF(S27>=60,1,0)<=1),"SELL","HOLD")))),"") -> STRONG SELL | Y27: =IFERROR(IF(OR(X27="STRONG BUY",X27="STRONG SELL"),"HIGH",IF(OR(X27="BUY",X27="SELL"),"MEDIUM","NEUTRAL")),"") -> HIGH | Z27: =IFERROR(IF(COUNTIF('Asset Analysis'!$A$4:$A$27,A27)>0,"YES","NO"),"") -> YES | AA27: =IFERROR(IF(AND(Z27="NO",W27>=$B$7,J27>=$B$5,S27>=$B$6,I27<=$B$8,F27>=$B$9),"→ ADD TO PORTFOLIO",IF(AND(Z27="YES",OR(J27<=$B$10,S27<=$B$11,W27<=$B$12,K27<=-$B$13)),"→ DELETE FROM PORTFOLIO",IF(AND(Z27="YES",X27="HOLD"),"HOLD — MONITOR",IF(AND(Z27="YES",OR(X27="BUY",X27="STRONG BUY")),"HOLD — STRONG",IF(Z27="NO","NOT QUALIFIED","REVIEW"))))),"") -> → DELETE FROM PORTFOLIO | AB27: =IFERROR(IF(AA27="→ ADD TO PORTFOLIO",IF(W27>=70,"P1 — IMMEDIATE",IF(W27>=60,"P2 — THIS WEEK","P3 — NEXT REBALANCE")),IF(AA27="→ DELETE FROM PORTFOLIO","P1 — IMMEDIATE","—")),"") -> P1 — IMMEDIATE
A28: XLV | B28: Health Care Select | C28: Sector | D28: Healthcare | E28: =IFERROR(ycps("XLV","price"),"") | F28: =IFERROR(ycps("XLV","one_year_return"),"") | G28: =IFERROR(ycps("XLV","three_year_annualized_return"),"") | H28: =IFERROR(ycps("XLV","five_year_annualized_return"),"") | I28: =IFERROR(ycps("XLV","one_year_volatility"),"") | J28: =IFERROR(IF(I28=0,0,(F28-'Data Input'!$B$4)/I28),0) -> 0 | K28: =IFERROR(ycps("XLV","max_drawdown_3_year"),"") | L28: =IFERROR(ycps("XLV","beta_5_year"),"") | M28: =IFERROR(ycps("XLV","dividend_yield"),"") | N28: =IFERROR(ycps("XLV","forward_pe_ratio"),"") | O28: =IFERROR(ycps("XLV","one_month_return"),"") | P28: =IFERROR(ycps("XLV","three_month_return"),"") | Q28: =IFERROR(ycps("XLV","six_month_return"),"") | R28: =IFERROR(ycps("XLV","one_year_return"),"") | S28: =IFERROR(MIN(100,MAX(0,ROUND(50+(O28*0.4+P28*0.3+Q28*0.2+R28*0.1)*200,0))),0) -> 0 | T28: =IFERROR(MIN(100,MAX(0,ROUND(50+R28*150+IF(F28>0,15,0)+IF(L28>0,5,-5),0))),0) -> 0 | U28: =IFERROR(MIN(100,MAX(0,ROUND(50+O28*200+IF(AND(O28>0,P28>0),10,-5)+IF(I28<0.2,10,-5),0))),0) -> 0 | V28: =IFERROR(MIN(100,MAX(0,ROUND(30+IF(I28>0,F28/I28,0)*40+IF(ABS(L28)<0.5,15,0)+IF(F28>0.08,10,0),0))),0) -> 0 | W28: =IFERROR(ROUND(T28*'Data Input'!$B$29+U28*'Data Input'!$B$30+V28*'Data Input'!$B$31+S28*'Data Input'!$B$32,0),0) -> 0 | X28: =IFERROR(IF(AND(W28>=70,IF(T28>=60,1,0)+IF(U28>=60,1,0)+IF(V28>=60,1,0)+IF(S28>=60,1,0)>=3),"STRONG BUY",IF(AND(W28>=60,IF(T28>=60,1,0)+IF(U28>=60,1,0)+IF(V28>=60,1,0)+IF(S28>=60,1,0)>=2),"BUY",IF(W28<35,"STRONG SELL",IF(AND(W28<45,IF(T28>=60,1,0)+IF(U28>=60,1,0)+IF(V28>=60,1,0)+IF(S28>=60,1,0)<=1),"SELL","HOLD")))),"") -> STRONG SELL | Y28: =IFERROR(IF(OR(X28="STRONG BUY",X28="STRONG SELL"),"HIGH",IF(OR(X28="BUY",X28="SELL"),"MEDIUM","NEUTRAL")),"") -> HIGH | Z28: =IFERROR(IF(COUNTIF('Asset Analysis'!$A$4:$A$27,A28)>0,"YES","NO"),"") -> YES | AA28: =IFERROR(IF(AND(Z28="NO",W28>=$B$7,J28>=$B$5,S28>=$B$6,I28<=$B$8,F28>=$B$9),"→ ADD TO PORTFOLIO",IF(AND(Z28="YES",OR(J28<=$B$10,S28<=$B$11,W28<=$B$12,K28<=-$B$13)),"→ DELETE FROM PORTFOLIO",IF(AND(Z28="YES",X28="HOLD"),"HOLD — MONITOR",IF(AND(Z28="YES",OR(X28="BUY",X28="STRONG BUY")),"HOLD — STRONG",IF(Z28="NO","NOT QUALIFIED","REVIEW"))))),"") -> → DELETE FROM PORTFOLIO | AB28: =IFERROR(IF(AA28="→ ADD TO PORTFOLIO",IF(W28>=70,"P1 — IMMEDIATE",IF(W28>=60,"P2 — THIS WEEK","P3 — NEXT REBALANCE")),IF(AA28="→ DELETE FROM PORTFOLIO","P1 — IMMEDIATE","—")),"") -> P1 — IMMEDIATE
A29: XLE | B29: Energy Select | C29: Sector | D29: Energy | E29: =IFERROR(ycps("XLE","price"),"") | F29: =IFERROR(ycps("XLE","one_year_return"),"") | G29: =IFERROR(ycps("XLE","three_year_annualized_return"),"") | H29: =IFERROR(ycps("XLE","five_year_annualized_return"),"") | I29: =IFERROR(ycps("XLE","one_year_volatility"),"") | J29: =IFERROR(IF(I29=0,0,(F29-'Data Input'!$B$4)/I29),0) -> 0 | K29: =IFERROR(ycps("XLE","max_drawdown_3_year"),"") | L29: =IFERROR(ycps("XLE","beta_5_year"),"") | M29: =IFERROR(ycps("XLE","dividend_yield"),"") | N29: =IFERROR(ycps("XLE","forward_pe_ratio"),"") | O29: =IFERROR(ycps("XLE","one_month_return"),"") | P29: =IFERROR(ycps("XLE","three_month_return"),"") | Q29: =IFERROR(ycps("XLE","six_month_return"),"") | R29: =IFERROR(ycps("XLE","one_year_return"),"") | S29: =IFERROR(MIN(100,MAX(0,ROUND(50+(O29*0.4+P29*0.3+Q29*0.2+R29*0.1)*200,0))),0) -> 0 | T29: =IFERROR(MIN(100,MAX(0,ROUND(50+R29*150+IF(F29>0,15,0)+IF(L29>0,5,-5),0))),0) -> 0 | U29: =IFERROR(MIN(100,MAX(0,ROUND(50+O29*200+IF(AND(O29>0,P29>0),10,-5)+IF(I29<0.2,10,-5),0))),0) -> 0 | V29: =IFERROR(MIN(100,MAX(0,ROUND(30+IF(I29>0,F29/I29,0)*40+IF(ABS(L29)<0.5,15,0)+IF(F29>0.08,10,0),0))),0) -> 0 | W29: =IFERROR(ROUND(T29*'Data Input'!$B$29+U29*'Data Input'!$B$30+V29*'Data Input'!$B$31+S29*'Data Input'!$B$32,0),0) -> 0 | X29: =IFERROR(IF(AND(W29>=70,IF(T29>=60,1,0)+IF(U29>=60,1,0)+IF(V29>=60,1,0)+IF(S29>=60,1,0)>=3),"STRONG BUY",IF(AND(W29>=60,IF(T29>=60,1,0)+IF(U29>=60,1,0)+IF(V29>=60,1,0)+IF(S29>=60,1,0)>=2),"BUY",IF(W29<35,"STRONG SELL",IF(AND(W29<45,IF(T29>=60,1,0)+IF(U29>=60,1,0)+IF(V29>=60,1,0)+IF(S29>=60,1,0)<=1),"SELL","HOLD")))),"") -> STRONG SELL | Y29: =IFERROR(IF(OR(X29="STRONG BUY",X29="STRONG SELL"),"HIGH",IF(OR(X29="BUY",X29="SELL"),"MEDIUM","NEUTRAL")),"") -> HIGH | Z29: =IFERROR(IF(COUNTIF('Asset Analysis'!$A$4:$A$27,A29)>0,"YES","NO"),"") -> YES | AA29: =IFERROR(IF(AND(Z29="NO",W29>=$B$7,J29>=$B$5,S29>=$B$6,I29<=$B$8,F29>=$B$9),"→ ADD TO PORTFOLIO",IF(AND(Z29="YES",OR(J29<=$B$10,S29<=$B$11,W29<=$B$12,K29<=-$B$13)),"→ DELETE FROM PORTFOLIO",IF(AND(Z29="YES",X29="HOLD"),"HOLD — MONITOR",IF(AND(Z29="YES",OR(X29="BUY",X29="STRONG BUY")),"HOLD — STRONG",IF(Z29="NO","NOT QUALIFIED","REVIEW"))))),"") -> → DELETE FROM PORTFOLIO | AB29: =IFERROR(IF(AA29="→ ADD TO PORTFOLIO",IF(W29>=70,"P1 — IMMEDIATE",IF(W29>=60,"P2 — THIS WEEK","P3 — NEXT REBALANCE")),IF(AA29="→ DELETE FROM PORTFOLIO","P1 — IMMEDIATE","—")),"") -> P1 — IMMEDIATE
A30: XLF | B30: Financial Select | C30: Sector | D30: Financials | E30: =IFERROR(ycps("XLF","price"),"") | F30: =IFERROR(ycps("XLF","one_year_return"),"") | G30: =IFERROR(ycps("XLF","three_year_annualized_return"),"") | H30: =IFERROR(ycps("XLF","five_year_annualized_return"),"") | I30: =IFERROR(ycps("XLF","one_year_volatility"),"") | J30: =IFERROR(IF(I30=0,0,(F30-'Data Input'!$B$4)/I30),0) -> 0 | K30: =IFERROR(ycps("XLF","max_drawdown_3_year"),"") | L30: =IFERROR(ycps("XLF","beta_5_year"),"") | M30: =IFERROR(ycps("XLF","dividend_yield"),"") | N30: =IFERROR(ycps("XLF","forward_pe_ratio"),"") | O30: =IFERROR(ycps("XLF","one_month_return"),"") | P30: =IFERROR(ycps("XLF","three_month_return"),"") | Q30: =IFERROR(ycps("XLF","six_month_return"),"") | R30: =IFERROR(ycps("XLF","one_year_return"),"") | S30: =IFERROR(MIN(100,MAX(0,ROUND(50+(O30*0.4+P30*0.3+Q30*0.2+R30*0.1)*200,0))),0) -> 0 | T30: =IFERROR(MIN(100,MAX(0,ROUND(50+R30*150+IF(F30>0,15,0)+IF(L30>0,5,-5),0))),0) -> 0 | U30: =IFERROR(MIN(100,MAX(0,ROUND(50+O30*200+IF(AND(O30>0,P30>0),10,-5)+IF(I30<0.2,10,-5),0))),0) -> 0 | V30: =IFERROR(MIN(100,MAX(0,ROUND(30+IF(I30>0,F30/I30,0)*40+IF(ABS(L30)<0.5,15,0)+IF(F30>0.08,10,0),0))),0) -> 0 | W30: =IFERROR(ROUND(T30*'Data Input'!$B$29+U30*'Data Input'!$B$30+V30*'Data Input'!$B$31+S30*'Data Input'!$B$32,0),0) -> 0 | X30: =IFERROR(IF(AND(W30>=70,IF(T30>=60,1,0)+IF(U30>=60,1,0)+IF(V30>=60,1,0)+IF(S30>=60,1,0)>=3),"STRONG BUY",IF(AND(W30>=60,IF(T30>=60,1,0)+IF(U30>=60,1,0)+IF(V30>=60,1,0)+IF(S30>=60,1,0)>=2),"BUY",IF(W30<35,"STRONG SELL",IF(AND(W30<45,IF(T30>=60,1,0)+IF(U30>=60,1,0)+IF(V30>=60,1,0)+IF(S30>=60,1,0)<=1),"SELL","HOLD")))),"") -> STRONG SELL | Y30: =IFERROR(IF(OR(X30="STRONG BUY",X30="STRONG SELL"),"HIGH",IF(OR(X30="BUY",X30="SELL"),"MEDIUM","NEUTRAL")),"") -> HIGH | Z30: =IFERROR(IF(COUNTIF('Asset Analysis'!$A$4:$A$27,A30)>0,"YES","NO"),"") -> YES | AA30: =IFERROR(IF(AND(Z30="NO",W30>=$B$7,J30>=$B$5,S30>=$B$6,I30<=$B$8,F30>=$B$9),"→ ADD TO PORTFOLIO",IF(AND(Z30="YES",OR(J30<=$B$10,S30<=$B$11,W30<=$B$12,K30<=-$B$13)),"→ DELETE FROM PORTFOLIO",IF(AND(Z30="YES",X30="HOLD"),"HOLD — MONITOR",IF(AND(Z30="YES",OR(X30="BUY",X30="STRONG BUY")),"HOLD — STRONG",IF(Z30="NO","NOT QUALIFIED","REVIEW"))))),"") -> → DELETE FROM PORTFOLIO | AB30: =IFERROR(IF(AA30="→ ADD TO PORTFOLIO",IF(W30>=70,"P1 — IMMEDIATE",IF(W30>=60,"P2 — THIS WEEK","P3 — NEXT REBALANCE")),IF(AA30="→ DELETE FROM PORTFOLIO","P1 — IMMEDIATE","—")),"") -> P1 — IMMEDIATE
A31: XLI | B31: Industrial Select | C31: Sector | D31: Industrials | E31: =IFERROR(ycps("XLI","price"),"") | F31: =IFERROR(ycps("XLI","one_year_return"),"") | G31: =IFERROR(ycps("XLI","three_year_annualized_return"),"") | H31: =IFERROR(ycps("XLI","five_year_annualized_return"),"") | I31: =IFERROR(ycps("XLI","one_year_volatility"),"") | J31: =IFERROR(IF(I31=0,0,(F31-'Data Input'!$B$4)/I31),0) -> 0 | K31: =IFERROR(ycps("XLI","max_drawdown_3_year"),"") | L31: =IFERROR(ycps("XLI","beta_5_year"),"") | M31: =IFERROR(ycps("XLI","dividend_yield"),"") | N31: =IFERROR(ycps("XLI","forward_pe_ratio"),"") | O31: =IFERROR(ycps("XLI","one_month_return"),"") | P31: =IFERROR(ycps("XLI","three_month_return"),"") | Q31: =IFERROR(ycps("XLI","six_month_return"),"") | R31: =IFERROR(ycps("XLI","one_year_return"),"") | S31: =IFERROR(MIN(100,MAX(0,ROUND(50+(O31*0.4+P31*0.3+Q31*0.2+R31*0.1)*200,0))),0) -> 0 | T31: =IFERROR(MIN(100,MAX(0,ROUND(50+R31*150+IF(F31>0,15,0)+IF(L31>0,5,-5),0))),0) -> 0 | U31: =IFERROR(MIN(100,MAX(0,ROUND(50+O31*200+IF(AND(O31>0,P31>0),10,-5)+IF(I31<0.2,10,-5),0))),0) -> 0 | V31: =IFERROR(MIN(100,MAX(0,ROUND(30+IF(I31>0,F31/I31,0)*40+IF(ABS(L31)<0.5,15,0)+IF(F31>0.08,10,0),0))),0) -> 0 | W31: =IFERROR(ROUND(T31*'Data Input'!$B$29+U31*'Data Input'!$B$30+V31*'Data Input'!$B$31+S31*'Data Input'!$B$32,0),0) -> 0 | X31: =IFERROR(IF(AND(W31>=70,IF(T31>=60,1,0)+IF(U31>=60,1,0)+IF(V31>=60,1,0)+IF(S31>=60,1,0)>=3),"STRONG BUY",IF(AND(W31>=60,IF(T31>=60,1,0)+IF(U31>=60,1,0)+IF(V31>=60,1,0)+IF(S31>=60,1,0)>=2),"BUY",IF(W31<35,"STRONG SELL",IF(AND(W31<45,IF(T31>=60,1,0)+IF(U31>=60,1,0)+IF(V31>=60,1,0)+IF(S31>=60,1,0)<=1),"SELL","HOLD")))),"") -> STRONG SELL | Y31: =IFERROR(IF(OR(X31="STRONG BUY",X31="STRONG SELL"),"HIGH",IF(OR(X31="BUY",X31="SELL"),"MEDIUM","NEUTRAL")),"") -> HIGH | Z31: =IFERROR(IF(COUNTIF('Asset Analysis'!$A$4:$A$27,A31)>0,"YES","NO"),"") -> NO | AA31: =IFERROR(IF(AND(Z31="NO",W31>=$B$7,J31>=$B$5,S31>=$B$6,I31<=$B$8,F31>=$B$9),"→ ADD TO PORTFOLIO",IF(AND(Z31="YES",OR(J31<=$B$10,S31<=$B$11,W31<=$B$12,K31<=-$B$13)),"→ DELETE FROM PORTFOLIO",IF(AND(Z31="YES",X31="HOLD"),"HOLD — MONITOR",IF(AND(Z31="YES",OR(X31="BUY",X31="STRONG BUY")),"HOLD — STRONG",IF(Z31="NO","NOT QUALIFIED","REVIEW"))))),"") -> NOT QUALIFIED | AB31: =IFERROR(IF(AA31="→ ADD TO PORTFOLIO",IF(W31>=70,"P1 — IMMEDIATE",IF(W31>=60,"P2 — THIS WEEK","P3 — NEXT REBALANCE")),IF(AA31="→ DELETE FROM PORTFOLIO","P1 — IMMEDIATE","—")),"") -> —
A32: XLP | B32: Consumer Staples | C32: Sector | D32: Staples | E32: =IFERROR(ycps("XLP","price"),"") | F32: =IFERROR(ycps("XLP","one_year_return"),"") | G32: =IFERROR(ycps("XLP","three_year_annualized_return"),"") | H32: =IFERROR(ycps("XLP","five_year_annualized_return"),"") | I32: =IFERROR(ycps("XLP","one_year_volatility"),"") | J32: =IFERROR(IF(I32=0,0,(F32-'Data Input'!$B$4)/I32),0) -> 0 | K32: =IFERROR(ycps("XLP","max_drawdown_3_year"),"") | L32: =IFERROR(ycps("XLP","beta_5_year"),"") | M32: =IFERROR(ycps("XLP","dividend_yield"),"") | N32: =IFERROR(ycps("XLP","forward_pe_ratio"),"") | O32: =IFERROR(ycps("XLP","one_month_return"),"") | P32: =IFERROR(ycps("XLP","three_month_return"),"") | Q32: =IFERROR(ycps("XLP","six_month_return"),"") | R32: =IFERROR(ycps("XLP","one_year_return"),"") | S32: =IFERROR(MIN(100,MAX(0,ROUND(50+(O32*0.4+P32*0.3+Q32*0.2+R32*0.1)*200,0))),0) -> 0 | T32: =IFERROR(MIN(100,MAX(0,ROUND(50+R32*150+IF(F32>0,15,0)+IF(L32>0,5,-5),0))),0) -> 0 | U32: =IFERROR(MIN(100,MAX(0,ROUND(50+O32*200+IF(AND(O32>0,P32>0),10,-5)+IF(I32<0.2,10,-5),0))),0) -> 0 | V32: =IFERROR(MIN(100,MAX(0,ROUND(30+IF(I32>0,F32/I32,0)*40+IF(ABS(L32)<0.5,15,0)+IF(F32>0.08,10,0),0))),0) -> 0 | W32: =IFERROR(ROUND(T32*'Data Input'!$B$29+U32*'Data Input'!$B$30+V32*'Data Input'!$B$31+S32*'Data Input'!$B$32,0),0) -> 0 | X32: =IFERROR(IF(AND(W32>=70,IF(T32>=60,1,0)+IF(U32>=60,1,0)+IF(V32>=60,1,0)+IF(S32>=60,1,0)>=3),"STRONG BUY",IF(AND(W32>=60,IF(T32>=60,1,0)+IF(U32>=60,1,0)+IF(V32>=60,1,0)+IF(S32>=60,1,0)>=2),"BUY",IF(W32<35,"STRONG SELL",IF(AND(W32<45,IF(T32>=60,1,0)+IF(U32>=60,1,0)+IF(V32>=60,1,0)+IF(S32>=60,1,0)<=1),"SELL","HOLD")))),"") -> STRONG SELL | Y32: =IFERROR(IF(OR(X32="STRONG BUY",X32="STRONG SELL"),"HIGH",IF(OR(X32="BUY",X32="SELL"),"MEDIUM","NEUTRAL")),"") -> HIGH | Z32: =IFERROR(IF(COUNTIF('Asset Analysis'!$A$4:$A$27,A32)>0,"YES","NO"),"") -> NO | AA32: =IFERROR(IF(AND(Z32="NO",W32>=$B$7,J32>=$B$5,S32>=$B$6,I32<=$B$8,F32>=$B$9),"→ ADD TO PORTFOLIO",IF(AND(Z32="YES",OR(J32<=$B$10,S32<=$B$11,W32<=$B$12,K32<=-$B$13)),"→ DELETE FROM PORTFOLIO",IF(AND(Z32="YES",X32="HOLD"),"HOLD — MONITOR",IF(AND(Z32="YES",OR(X32="BUY",X32="STRONG BUY")),"HOLD — STRONG",IF(Z32="NO","NOT QUALIFIED","REVIEW"))))),"") -> NOT QUALIFIED | AB32: =IFERROR(IF(AA32="→ ADD TO PORTFOLIO",IF(W32>=70,"P1 — IMMEDIATE",IF(W32>=60,"P2 — THIS WEEK","P3 — NEXT REBALANCE")),IF(AA32="→ DELETE FROM PORTFOLIO","P1 — IMMEDIATE","—")),"") -> —
A33: XLU | B33: Utilities Select | C33: Sector | D33: Utilities | E33: =IFERROR(ycps("XLU","price"),"") | F33: =IFERROR(ycps("XLU","one_year_return"),"") | G33: =IFERROR(ycps("XLU","three_year_annualized_return"),"") | H33: =IFERROR(ycps("XLU","five_year_annualized_return"),"") | I33: =IFERROR(ycps("XLU","one_year_volatility"),"") | J33: =IFERROR(IF(I33=0,0,(F33-'Data Input'!$B$4)/I33),0) -> 0 | K33: =IFERROR(ycps("XLU","max_drawdown_3_year"),"") | L33: =IFERROR(ycps("XLU","beta_5_year"),"") | M33: =IFERROR(ycps("XLU","dividend_yield"),"") | N33: =IFERROR(ycps("XLU","forward_pe_ratio"),"") | O33: =IFERROR(ycps("XLU","one_month_return"),"") | P33: =IFERROR(ycps("XLU","three_month_return"),"") | Q33: =IFERROR(ycps("XLU","six_month_return"),"") | R33: =IFERROR(ycps("XLU","one_year_return"),"") | S33: =IFERROR(MIN(100,MAX(0,ROUND(50+(O33*0.4+P33*0.3+Q33*0.2+R33*0.1)*200,0))),0) -> 0 | T33: =IFERROR(MIN(100,MAX(0,ROUND(50+R33*150+IF(F33>0,15,0)+IF(L33>0,5,-5),0))),0) -> 0 | U33: =IFERROR(MIN(100,MAX(0,ROUND(50+O33*200+IF(AND(O33>0,P33>0),10,-5)+IF(I33<0.2,10,-5),0))),0) -> 0 | V33: =IFERROR(MIN(100,MAX(0,ROUND(30+IF(I33>0,F33/I33,0)*40+IF(ABS(L33)<0.5,15,0)+IF(F33>0.08,10,0),0))),0) -> 0 | W33: =IFERROR(ROUND(T33*'Data Input'!$B$29+U33*'Data Input'!$B$30+V33*'Data Input'!$B$31+S33*'Data Input'!$B$32,0),0) -> 0 | X33: =IFERROR(IF(AND(W33>=70,IF(T33>=60,1,0)+IF(U33>=60,1,0)+IF(V33>=60,1,0)+IF(S33>=60,1,0)>=3),"STRONG BUY",IF(AND(W33>=60,IF(T33>=60,1,0)+IF(U33>=60,1,0)+IF(V33>=60,1,0)+IF(S33>=60,1,0)>=2),"BUY",IF(W33<35,"STRONG SELL",IF(AND(W33<45,IF(T33>=60,1,0)+IF(U33>=60,1,0)+IF(V33>=60,1,0)+IF(S33>=60,1,0)<=1),"SELL","HOLD")))),"") -> STRONG SELL | Y33: =IFERROR(IF(OR(X33="STRONG BUY",X33="STRONG SELL"),"HIGH",IF(OR(X33="BUY",X33="SELL"),"MEDIUM","NEUTRAL")),"") -> HIGH | Z33: =IFERROR(IF(COUNTIF('Asset Analysis'!$A$4:$A$27,A33)>0,"YES","NO"),"") -> NO | AA33: =IFERROR(IF(AND(Z33="NO",W33>=$B$7,J33>=$B$5,S33>=$B$6,I33<=$B$8,F33>=$B$9),"→ ADD TO PORTFOLIO",IF(AND(Z33="YES",OR(J33<=$B$10,S33<=$B$11,W33<=$B$12,K33<=-$B$13)),"→ DELETE FROM PORTFOLIO",IF(AND(Z33="YES",X33="HOLD"),"HOLD — MONITOR",IF(AND(Z33="YES",OR(X33="BUY",X33="STRONG BUY")),"HOLD — STRONG",IF(Z33="NO","NOT QUALIFIED","REVIEW"))))),"") -> NOT QUALIFIED | AB33: =IFERROR(IF(AA33="→ ADD TO PORTFOLIO",IF(W33>=70,"P1 — IMMEDIATE",IF(W33>=60,"P2 — THIS WEEK","P3 — NEXT REBALANCE")),IF(AA33="→ DELETE FROM PORTFOLIO","P1 — IMMEDIATE","—")),"") -> —
A34: XLY | B34: Consumer Disc Select | C34: Sector | D34: Discretionary | E34: =IFERROR(ycps("XLY","price"),"") | F34: =IFERROR(ycps("XLY","one_year_return"),"") | G34: =IFERROR(ycps("XLY","three_year_annualized_return"),"") | H34: =IFERROR(ycps("XLY","five_year_annualized_return"),"") | I34: =IFERROR(ycps("XLY","one_year_volatility"),"") | J34: =IFERROR(IF(I34=0,0,(F34-'Data Input'!$B$4)/I34),0) -> 0 | K34: =IFERROR(ycps("XLY","max_drawdown_3_year"),"") | L34: =IFERROR(ycps("XLY","beta_5_year"),"") | M34: =IFERROR(ycps("XLY","dividend_yield"),"") | N34: =IFERROR(ycps("XLY","forward_pe_ratio"),"") | O34: =IFERROR(ycps("XLY","one_month_return"),"") | P34: =IFERROR(ycps("XLY","three_month_return"),"") | Q34: =IFERROR(ycps("XLY","six_month_return"),"") | R34: =IFERROR(ycps("XLY","one_year_return"),"") | S34: =IFERROR(MIN(100,MAX(0,ROUND(50+(O34*0.4+P34*0.3+Q34*0.2+R34*0.1)*200,0))),0) -> 0 | T34: =IFERROR(MIN(100,MAX(0,ROUND(50+R34*150+IF(F34>0,15,0)+IF(L34>0,5,-5),0))),0) -> 0 | U34: =IFERROR(MIN(100,MAX(0,ROUND(50+O34*200+IF(AND(O34>0,P34>0),10,-5)+IF(I34<0.2,10,-5),0))),0) -> 0 | V34: =IFERROR(MIN(100,MAX(0,ROUND(30+IF(I34>0,F34/I34,0)*40+IF(ABS(L34)<0.5,15,0)+IF(F34>0.08,10,0),0))),0) -> 0 | W34: =IFERROR(ROUND(T34*'Data Input'!$B$29+U34*'Data Input'!$B$30+V34*'Data Input'!$B$31+S34*'Data Input'!$B$32,0),0) -> 0 | X34: =IFERROR(IF(AND(W34>=70,IF(T34>=60,1,0)+IF(U34>=60,1,0)+IF(V34>=60,1,0)+IF(S34>=60,1,0)>=3),"STRONG BUY",IF(AND(W34>=60,IF(T34>=60,1,0)+IF(U34>=60,1,0)+IF(V34>=60,1,0)+IF(S34>=60,1,0)>=2),"BUY",IF(W34<35,"STRONG SELL",IF(AND(W34<45,IF(T34>=60,1,0)+IF(U34>=60,1,0)+IF(V34>=60,1,0)+IF(S34>=60,1,0)<=1),"SELL","HOLD")))),"") -> STRONG SELL | Y34: =IFERROR(IF(OR(X34="STRONG BUY",X34="STRONG SELL"),"HIGH",IF(OR(X34="BUY",X34="SELL"),"MEDIUM","NEUTRAL")),"") -> HIGH | Z34: =IFERROR(IF(COUNTIF('Asset Analysis'!$A$4:$A$27,A34)>0,"YES","NO"),"") -> NO | AA34: =IFERROR(IF(AND(Z34="NO",W34>=$B$7,J34>=$B$5,S34>=$B$6,I34<=$B$8,F34>=$B$9),"→ ADD TO PORTFOLIO",IF(AND(Z34="YES",OR(J34<=$B$10,S34<=$B$11,W34<=$B$12,K34<=-$B$13)),"→ DELETE FROM PORTFOLIO",IF(AND(Z34="YES",X34="HOLD"),"HOLD — MONITOR",IF(AND(Z34="YES",OR(X34="BUY",X34="STRONG BUY")),"HOLD — STRONG",IF(Z34="NO","NOT QUALIFIED","REVIEW"))))),"") -> NOT QUALIFIED | AB34: =IFERROR(IF(AA34="→ ADD TO PORTFOLIO",IF(W34>=70,"P1 — IMMEDIATE",IF(W34>=60,"P2 — THIS WEEK","P3 — NEXT REBALANCE")),IF(AA34="→ DELETE FROM PORTFOLIO","P1 — IMMEDIATE","—")),"") -> —
A35: XLC | B35: Communication Svcs | C35: Sector | D35: Communication | E35: =IFERROR(ycps("XLC","price"),"") | F35: =IFERROR(ycps("XLC","one_year_return"),"") | G35: =IFERROR(ycps("XLC","three_year_annualized_return"),"") | H35: =IFERROR(ycps("XLC","five_year_annualized_return"),"") | I35: =IFERROR(ycps("XLC","one_year_volatility"),"") | J35: =IFERROR(IF(I35=0,0,(F35-'Data Input'!$B$4)/I35),0) -> 0 | K35: =IFERROR(ycps("XLC","max_drawdown_3_year"),"") | L35: =IFERROR(ycps("XLC","beta_5_year"),"") | M35: =IFERROR(ycps("XLC","dividend_yield"),"") | N35: =IFERROR(ycps("XLC","forward_pe_ratio"),"") | O35: =IFERROR(ycps("XLC","one_month_return"),"") | P35: =IFERROR(ycps("XLC","three_month_return"),"") | Q35: =IFERROR(ycps("XLC","six_month_return"),"") | R35: =IFERROR(ycps("XLC","one_year_return"),"") | S35: =IFERROR(MIN(100,MAX(0,ROUND(50+(O35*0.4+P35*0.3+Q35*0.2+R35*0.1)*200,0))),0) -> 0 | T35: =IFERROR(MIN(100,MAX(0,ROUND(50+R35*150+IF(F35>0,15,0)+IF(L35>0,5,-5),0))),0) -> 0 | U35: =IFERROR(MIN(100,MAX(0,ROUND(50+O35*200+IF(AND(O35>0,P35>0),10,-5)+IF(I35<0.2,10,-5),0))),0) -> 0 | V35: =IFERROR(MIN(100,MAX(0,ROUND(30+IF(I35>0,F35/I35,0)*40+IF(ABS(L35)<0.5,15,0)+IF(F35>0.08,10,0),0))),0) -> 0 | W35: =IFERROR(ROUND(T35*'Data Input'!$B$29+U35*'Data Input'!$B$30+V35*'Data Input'!$B$31+S35*'Data Input'!$B$32,0),0) -> 0 | X35: =IFERROR(IF(AND(W35>=70,IF(T35>=60,1,0)+IF(U35>=60,1,0)+IF(V35>=60,1,0)+IF(S35>=60,1,0)>=3),"STRONG BUY",IF(AND(W35>=60,IF(T35>=60,1,0)+IF(U35>=60,1,0)+IF(V35>=60,1,0)+IF(S35>=60,1,0)>=2),"BUY",IF(W35<35,"STRONG SELL",IF(AND(W35<45,IF(T35>=60,1,0)+IF(U35>=60,1,0)+IF(V35>=60,1,0)+IF(S35>=60,1,0)<=1),"SELL","HOLD")))),"") -> STRONG SELL | Y35: =IFERROR(IF(OR(X35="STRONG BUY",X35="STRONG SELL"),"HIGH",IF(OR(X35="BUY",X35="SELL"),"MEDIUM","NEUTRAL")),"") -> HIGH | Z35: =IFERROR(IF(COUNTIF('Asset Analysis'!$A$4:$A$27,A35)>0,"YES","NO"),"") -> NO | AA35: =IFERROR(IF(AND(Z35="NO",W35>=$B$7,J35>=$B$5,S35>=$B$6,I35<=$B$8,F35>=$B$9),"→ ADD TO PORTFOLIO",IF(AND(Z35="YES",OR(J35<=$B$10,S35<=$B$11,W35<=$B$12,K35<=-$B$13)),"→ DELETE FROM PORTFOLIO",IF(AND(Z35="YES",X35="HOLD"),"HOLD — MONITOR",IF(AND(Z35="YES",OR(X35="BUY",X35="STRONG BUY")),"HOLD — STRONG",IF(Z35="NO","NOT QUALIFIED","REVIEW"))))),"") -> NOT QUALIFIED | AB35: =IFERROR(IF(AA35="→ ADD TO PORTFOLIO",IF(W35>=70,"P1 — IMMEDIATE",IF(W35>=60,"P2 — THIS WEEK","P3 — NEXT REBALANCE")),IF(AA35="→ DELETE FROM PORTFOLIO","P1 — IMMEDIATE","—")),"") -> —
A36: XLRE | B36: Real Estate Select | C36: Sector | D36: Real Estate | E36: =IFERROR(ycps("XLRE","price"),"") | F36: =IFERROR(ycps("XLRE","one_year_return"),"") | G36: =IFERROR(ycps("XLRE","three_year_annualized_return"),"") | H36: =IFERROR(ycps("XLRE","five_year_annualized_return"),"") | I36: =IFERROR(ycps("XLRE","one_year_volatility"),"") | J36: =IFERROR(IF(I36=0,0,(F36-'Data Input'!$B$4)/I36),0) -> 0 | K36: =IFERROR(ycps("XLRE","max_drawdown_3_year"),"") | L36: =IFERROR(ycps("XLRE","beta_5_year"),"") | M36: =IFERROR(ycps("XLRE","dividend_yield"),"") | N36: =IFERROR(ycps("XLRE","forward_pe_ratio"),"") | O36: =IFERROR(ycps("XLRE","one_month_return"),"") | P36: =IFERROR(ycps("XLRE","three_month_return"),"") | Q36: =IFERROR(ycps("XLRE","six_month_return"),"") | R36: =IFERROR(ycps("XLRE","one_year_return"),"") | S36: =IFERROR(MIN(100,MAX(0,ROUND(50+(O36*0.4+P36*0.3+Q36*0.2+R36*0.1)*200,0))),0) -> 0 | T36: =IFERROR(MIN(100,MAX(0,ROUND(50+R36*150+IF(F36>0,15,0)+IF(L36>0,5,-5),0))),0) -> 0 | U36: =IFERROR(MIN(100,MAX(0,ROUND(50+O36*200+IF(AND(O36>0,P36>0),10,-5)+IF(I36<0.2,10,-5),0))),0) -> 0 | V36: =IFERROR(MIN(100,MAX(0,ROUND(30+IF(I36>0,F36/I36,0)*40+IF(ABS(L36)<0.5,15,0)+IF(F36>0.08,10,0),0))),0) -> 0 | W36: =IFERROR(ROUND(T36*'Data Input'!$B$29+U36*'Data Input'!$B$30+V36*'Data Input'!$B$31+S36*'Data Input'!$B$32,0),0) -> 0 | X36: =IFERROR(IF(AND(W36>=70,IF(T36>=60,1,0)+IF(U36>=60,1,0)+IF(V36>=60,1,0)+IF(S36>=60,1,0)>=3),"STRONG BUY",IF(AND(W36>=60,IF(T36>=60,1,0)+IF(U36>=60,1,0)+IF(V36>=60,1,0)+IF(S36>=60,1,0)>=2),"BUY",IF(W36<35,"STRONG SELL",IF(AND(W36<45,IF(T36>=60,1,0)+IF(U36>=60,1,0)+IF(V36>=60,1,0)+IF(S36>=60,1,0)<=1),"SELL","HOLD")))),"") -> STRONG SELL | Y36: =IFERROR(IF(OR(X36="STRONG BUY",X36="STRONG SELL"),"HIGH",IF(OR(X36="BUY",X36="SELL"),"MEDIUM","NEUTRAL")),"") -> HIGH | Z36: =IFERROR(IF(COUNTIF('Asset Analysis'!$A$4:$A$27,A36)>0,"YES","NO"),"") -> NO | AA36: =IFERROR(IF(AND(Z36="NO",W36>=$B$7,J36>=$B$5,S36>=$B$6,I36<=$B$8,F36>=$B$9),"→ ADD TO PORTFOLIO",IF(AND(Z36="YES",OR(J36<=$B$10,S36<=$B$11,W36<=$B$12,K36<=-$B$13)),"→ DELETE FROM PORTFOLIO",IF(AND(Z36="YES",X36="HOLD"),"HOLD — MONITOR",IF(AND(Z36="YES",OR(X36="BUY",X36="STRONG BUY")),"HOLD — STRONG",IF(Z36="NO","NOT QUALIFIED","REVIEW"))))),"") -> NOT QUALIFIED | AB36: =IFERROR(IF(AA36="→ ADD TO PORTFOLIO",IF(W36>=70,"P1 — IMMEDIATE",IF(W36>=60,"P2 — THIS WEEK","P3 — NEXT REBALANCE")),IF(AA36="→ DELETE FROM PORTFOLIO","P1 — IMMEDIATE","—")),"") -> —
A37: IWM | B37: iShares Russell 2000 | C37: US Equity | D37: Small Cap | E37: =IFERROR(ycps("IWM","price"),"") | F37: =IFERROR(ycps("IWM","one_year_return"),"") | G37: =IFERROR(ycps("IWM","three_year_annualized_return"),"") | H37: =IFERROR(ycps("IWM","five_year_annualized_return"),"") | I37: =IFERROR(ycps("IWM","one_year_volatility"),"") | J37: =IFERROR(IF(I37=0,0,(F37-'Data Input'!$B$4)/I37),0) -> 0 | K37: =IFERROR(ycps("IWM","max_drawdown_3_year"),"") | L37: =IFERROR(ycps("IWM","beta_5_year"),"") | M37: =IFERROR(ycps("IWM","dividend_yield"),"") | N37: =IFERROR(ycps("IWM","forward_pe_ratio"),"") | O37: =IFERROR(ycps("IWM","one_month_return"),"") | P37: =IFERROR(ycps("IWM","three_month_return"),"") | Q37: =IFERROR(ycps("IWM","six_month_return"),"") | R37: =IFERROR(ycps("IWM","one_year_return"),"") | S37: =IFERROR(MIN(100,MAX(0,ROUND(50+(O37*0.4+P37*0.3+Q37*0.2+R37*0.1)*200,0))),0) -> 0 | T37: =IFERROR(MIN(100,MAX(0,ROUND(50+R37*150+IF(F37>0,15,0)+IF(L37>0,5,-5),0))),0) -> 0 | U37: =IFERROR(MIN(100,MAX(0,ROUND(50+O37*200+IF(AND(O37>0,P37>0),10,-5)+IF(I37<0.2,10,-5),0))),0) -> 0 | V37: =IFERROR(MIN(100,MAX(0,ROUND(30+IF(I37>0,F37/I37,0)*40+IF(ABS(L37)<0.5,15,0)+IF(F37>0.08,10,0),0))),0) -> 0 | W37: =IFERROR(ROUND(T37*'Data Input'!$B$29+U37*'Data Input'!$B$30+V37*'Data Input'!$B$31+S37*'Data Input'!$B$32,0),0) -> 0 | X37: =IFERROR(IF(AND(W37>=70,IF(T37>=60,1,0)+IF(U37>=60,1,0)+IF(V37>=60,1,0)+IF(S37>=60,1,0)>=3),"STRONG BUY",IF(AND(W37>=60,IF(T37>=60,1,0)+IF(U37>=60,1,0)+IF(V37>=60,1,0)+IF(S37>=60,1,0)>=2),"BUY",IF(W37<35,"STRONG SELL",IF(AND(W37<45,IF(T37>=60,1,0)+IF(U37>=60,1,0)+IF(V37>=60,1,0)+IF(S37>=60,1,0)<=1),"SELL","HOLD")))),"") -> STRONG SELL | Y37: =IFERROR(IF(OR(X37="STRONG BUY",X37="STRONG SELL"),"HIGH",IF(OR(X37="BUY",X37="SELL"),"MEDIUM","NEUTRAL")),"") -> HIGH | Z37: =IFERROR(IF(COUNTIF('Asset Analysis'!$A$4:$A$27,A37)>0,"YES","NO"),"") -> YES | AA37: =IFERROR(IF(AND(Z37="NO",W37>=$B$7,J37>=$B$5,S37>=$B$6,I37<=$B$8,F37>=$B$9),"→ ADD TO PORTFOLIO",IF(AND(Z37="YES",OR(J37<=$B$10,S37<=$B$11,W37<=$B$12,K37<=-$B$13)),"→ DELETE FROM PORTFOLIO",IF(AND(Z37="YES",X37="HOLD"),"HOLD — MONITOR",IF(AND(Z37="YES",OR(X37="BUY",X37="STRONG BUY")),"HOLD — STRONG",IF(Z37="NO","NOT QUALIFIED","REVIEW"))))),"") -> → DELETE FROM PORTFOLIO | AB37: =IFERROR(IF(AA37="→ ADD TO PORTFOLIO",IF(W37>=70,"P1 — IMMEDIATE",IF(W37>=60,"P2 — THIS WEEK","P3 — NEXT REBALANCE")),IF(AA37="→ DELETE FROM PORTFOLIO","P1 — IMMEDIATE","—")),"") -> P1 — IMMEDIATE
A38: IJR | B38: iShares Core S&P Small | C38: US Equity | D38: Small Cap | E38: =IFERROR(ycps("IJR","price"),"") | F38: =IFERROR(ycps("IJR","one_year_return"),"") | G38: =IFERROR(ycps("IJR","three_year_annualized_return"),"") | H38: =IFERROR(ycps("IJR","five_year_annualized_return"),"") | I38: =IFERROR(ycps("IJR","one_year_volatility"),"") | J38: =IFERROR(IF(I38=0,0,(F38-'Data Input'!$B$4)/I38),0) -> 0 | K38: =IFERROR(ycps("IJR","max_drawdown_3_year"),"") | L38: =IFERROR(ycps("IJR","beta_5_year"),"") | M38: =IFERROR(ycps("IJR","dividend_yield"),"") | N38: =IFERROR(ycps("IJR","forward_pe_ratio"),"") | O38: =IFERROR(ycps("IJR","one_month_return"),"") | P38: =IFERROR(ycps("IJR","three_month_return"),"") | Q38: =IFERROR(ycps("IJR","six_month_return"),"") | R38: =IFERROR(ycps("IJR","one_year_return"),"") | S38: =IFERROR(MIN(100,MAX(0,ROUND(50+(O38*0.4+P38*0.3+Q38*0.2+R38*0.1)*200,0))),0) -> 0 | T38: =IFERROR(MIN(100,MAX(0,ROUND(50+R38*150+IF(F38>0,15,0)+IF(L38>0,5,-5),0))),0) -> 0 | U38: =IFERROR(MIN(100,MAX(0,ROUND(50+O38*200+IF(AND(O38>0,P38>0),10,-5)+IF(I38<0.2,10,-5),0))),0) -> 0 | V38: =IFERROR(MIN(100,MAX(0,ROUND(30+IF(I38>0,F38/I38,0)*40+IF(ABS(L38)<0.5,15,0)+IF(F38>0.08,10,0),0))),0) -> 0 | W38: =IFERROR(ROUND(T38*'Data Input'!$B$29+U38*'Data Input'!$B$30+V38*'Data Input'!$B$31+S38*'Data Input'!$B$32,0),0) -> 0 | X38: =IFERROR(IF(AND(W38>=70,IF(T38>=60,1,0)+IF(U38>=60,1,0)+IF(V38>=60,1,0)+IF(S38>=60,1,0)>=3),"STRONG BUY",IF(AND(W38>=60,IF(T38>=60,1,0)+IF(U38>=60,1,0)+IF(V38>=60,1,0)+IF(S38>=60,1,0)>=2),"BUY",IF(W38<35,"STRONG SELL",IF(AND(W38<45,IF(T38>=60,1,0)+IF(U38>=60,1,0)+IF(V38>=60,1,0)+IF(S38>=60,1,0)<=1),"SELL","HOLD")))),"") -> STRONG SELL | Y38: =IFERROR(IF(OR(X38="STRONG BUY",X38="STRONG SELL"),"HIGH",IF(OR(X38="BUY",X38="SELL"),"MEDIUM","NEUTRAL")),"") -> HIGH | Z38: =IFERROR(IF(COUNTIF('Asset Analysis'!$A$4:$A$27,A38)>0,"YES","NO"),"") -> NO | AA38: =IFERROR(IF(AND(Z38="NO",W38>=$B$7,J38>=$B$5,S38>=$B$6,I38<=$B$8,F38>=$B$9),"→ ADD TO PORTFOLIO",IF(AND(Z38="YES",OR(J38<=$B$10,S38<=$B$11,W38<=$B$12,K38<=-$B$13)),"→ DELETE FROM PORTFOLIO",IF(AND(Z38="YES",X38="HOLD"),"HOLD — MONITOR",IF(AND(Z38="YES",OR(X38="BUY",X38="STRONG BUY")),"HOLD — STRONG",IF(Z38="NO","NOT QUALIFIED","REVIEW"))))),"") -> NOT QUALIFIED | AB38: =IFERROR(IF(AA38="→ ADD TO PORTFOLIO",IF(W38>=70,"P1 — IMMEDIATE",IF(W38>=60,"P2 — THIS WEEK","P3 — NEXT REBALANCE")),IF(AA38="→ DELETE FROM PORTFOLIO","P1 — IMMEDIATE","—")),"") -> —
A39: MDY | B39: SPDR S&P MidCap 400 | C39: US Equity | D39: Mid Cap | E39: =IFERROR(ycps("MDY","price"),"") | F39: =IFERROR(ycps("MDY","one_year_return"),"") | G39: =IFERROR(ycps("MDY","three_year_annualized_return"),"") | H39: =IFERROR(ycps("MDY","five_year_annualized_return"),"") | I39: =IFERROR(ycps("MDY","one_year_volatility"),"") | J39: =IFERROR(IF(I39=0,0,(F39-'Data Input'!$B$4)/I39),0) -> 0 | K39: =IFERROR(ycps("MDY","max_drawdown_3_year"),"") | L39: =IFERROR(ycps("MDY","beta_5_year"),"") | M39: =IFERROR(ycps("MDY","dividend_yield"),"") | N39: =IFERROR(ycps("MDY","forward_pe_ratio"),"") | O39: =IFERROR(ycps("MDY","one_month_return"),"") | P39: =IFERROR(ycps("MDY","three_month_return"),"") | Q39: =IFERROR(ycps("MDY","six_month_return"),"") | R39: =IFERROR(ycps("MDY","one_year_return"),"") | S39: =IFERROR(MIN(100,MAX(0,ROUND(50+(O39*0.4+P39*0.3+Q39*0.2+R39*0.1)*200,0))),0) -> 0 | T39: =IFERROR(MIN(100,MAX(0,ROUND(50+R39*150+IF(F39>0,15,0)+IF(L39>0,5,-5),0))),0) -> 0 | U39: =IFERROR(MIN(100,MAX(0,ROUND(50+O39*200+IF(AND(O39>0,P39>0),10,-5)+IF(I39<0.2,10,-5),0))),0) -> 0 | V39: =IFERROR(MIN(100,MAX(0,ROUND(30+IF(I39>0,F39/I39,0)*40+IF(ABS(L39)<0.5,15,0)+IF(F39>0.08,10,0),0))),0) -> 0 | W39: =IFERROR(ROUND(T39*'Data Input'!$B$29+U39*'Data Input'!$B$30+V39*'Data Input'!$B$31+S39*'Data Input'!$B$32,0),0) -> 0 | X39: =IFERROR(IF(AND(W39>=70,IF(T39>=60,1,0)+IF(U39>=60,1,0)+IF(V39>=60,1,0)+IF(S39>=60,1,0)>=3),"STRONG BUY",IF(AND(W39>=60,IF(T39>=60,1,0)+IF(U39>=60,1,0)+IF(V39>=60,1,0)+IF(S39>=60,1,0)>=2),"BUY",IF(W39<35,"STRONG SELL",IF(AND(W39<45,IF(T39>=60,1,0)+IF(U39>=60,1,0)+IF(V39>=60,1,0)+IF(S39>=60,1,0)<=1),"SELL","HOLD")))),"") -> STRONG SELL | Y39: =IFERROR(IF(OR(X39="STRONG BUY",X39="STRONG SELL"),"HIGH",IF(OR(X39="BUY",X39="SELL"),"MEDIUM","NEUTRAL")),"") -> HIGH | Z39: =IFERROR(IF(COUNTIF('Asset Analysis'!$A$4:$A$27,A39)>0,"YES","NO"),"") -> NO | AA39: =IFERROR(IF(AND(Z39="NO",W39>=$B$7,J39>=$B$5,S39>=$B$6,I39<=$B$8,F39>=$B$9),"→ ADD TO PORTFOLIO",IF(AND(Z39="YES",OR(J39<=$B$10,S39<=$B$11,W39<=$B$12,K39<=-$B$13)),"→ DELETE FROM PORTFOLIO",IF(AND(Z39="YES",X39="HOLD"),"HOLD — MONITOR",IF(AND(Z39="YES",OR(X39="BUY",X39="STRONG BUY")),"HOLD — STRONG",IF(Z39="NO","NOT QUALIFIED","REVIEW"))))),"") -> NOT QUALIFIED | AB39: =IFERROR(IF(AA39="→ ADD TO PORTFOLIO",IF(W39>=70,"P1 — IMMEDIATE",IF(W39>=60,"P2 — THIS WEEK","P3 — NEXT REBALANCE")),IF(AA39="→ DELETE FROM PORTFOLIO","P1 — IMMEDIATE","—")),"") -> —
A40: VB | B40: Vanguard Small Cap | C40: US Equity | D40: Small Cap | E40: =IFERROR(ycps("VB","price"),"") | F40: =IFERROR(ycps("VB","one_year_return"),"") | G40: =IFERROR(ycps("VB","three_year_annualized_return"),"") | H40: =IFERROR(ycps("VB","five_year_annualized_return"),"") | I40: =IFERROR(ycps("VB","one_year_volatility"),"") | J40: =IFERROR(IF(I40=0,0,(F40-'Data Input'!$B$4)/I40),0) -> 0 | K40: =IFERROR(ycps("VB","max_drawdown_3_year"),"") | L40: =IFERROR(ycps("VB","beta_5_year"),"") | M40: =IFERROR(ycps("VB","dividend_yield"),"") | N40: =IFERROR(ycps("VB","forward_pe_ratio"),"") | O40: =IFERROR(ycps("VB","one_month_return"),"") | P40: =IFERROR(ycps("VB","three_month_return"),"") | Q40: =IFERROR(ycps("VB","six_month_return"),"") | R40: =IFERROR(ycps("VB","one_year_return"),"") | S40: =IFERROR(MIN(100,MAX(0,ROUND(50+(O40*0.4+P40*0.3+Q40*0.2+R40*0.1)*200,0))),0) -> 0 | T40: =IFERROR(MIN(100,MAX(0,ROUND(50+R40*150+IF(F40>0,15,0)+IF(L40>0,5,-5),0))),0) -> 0 | U40: =IFERROR(MIN(100,MAX(0,ROUND(50+O40*200+IF(AND(O40>0,P40>0),10,-5)+IF(I40<0.2,10,-5),0))),0) -> 0 | V40: =IFERROR(MIN(100,MAX(0,ROUND(30+IF(I40>0,F40/I40,0)*40+IF(ABS(L40)<0.5,15,0)+IF(F40>0.08,10,0),0))),0) -> 0 | W40: =IFERROR(ROUND(T40*'Data Input'!$B$29+U40*'Data Input'!$B$30+V40*'Data Input'!$B$31+S40*'Data Input'!$B$32,0),0) -> 0 | X40: =IFERROR(IF(AND(W40>=70,IF(T40>=60,1,0)+IF(U40>=60,1,0)+IF(V40>=60,1,0)+IF(S40>=60,1,0)>=3),"STRONG BUY",IF(AND(W40>=60,IF(T40>=60,1,0)+IF(U40>=60,1,0)+IF(V40>=60,1,0)+IF(S40>=60,1,0)>=2),"BUY",IF(W40<35,"STRONG SELL",IF(AND(W40<45,IF(T40>=60,1,0)+IF(U40>=60,1,0)+IF(V40>=60,1,0)+IF(S40>=60,1,0)<=1),"SELL","HOLD")))),"") -> STRONG SELL | Y40: =IFERROR(IF(OR(X40="STRONG BUY",X40="STRONG SELL"),"HIGH",IF(OR(X40="BUY",X40="SELL"),"MEDIUM","NEUTRAL")),"") -> HIGH | Z40: =IFERROR(IF(COUNTIF('Asset Analysis'!$A$4:$A$27,A40)>0,"YES","NO"),"") -> NO | AA40: =IFERROR(IF(AND(Z40="NO",W40>=$B$7,J40>=$B$5,S40>=$B$6,I40<=$B$8,F40>=$B$9),"→ ADD TO PORTFOLIO",IF(AND(Z40="YES",OR(J40<=$B$10,S40<=$B$11,W40<=$B$12,K40<=-$B$13)),"→ DELETE FROM PORTFOLIO",IF(AND(Z40="YES",X40="HOLD"),"HOLD — MONITOR",IF(AND(Z40="YES",OR(X40="BUY",X40="STRONG BUY")),"HOLD — STRONG",IF(Z40="NO","NOT QUALIFIED","REVIEW"))))),"") -> NOT QUALIFIED | AB40: =IFERROR(IF(AA40="→ ADD TO PORTFOLIO",IF(W40>=70,"P1 — IMMEDIATE",IF(W40>=60,"P2 — THIS WEEK","P3 — NEXT REBALANCE")),IF(AA40="→ DELETE FROM PORTFOLIO","P1 — IMMEDIATE","—")),"") -> —
A41: VO | B41: Vanguard Mid-Cap | C41: US Equity | D41: Mid Cap | E41: =IFERROR(ycps("VO","price"),"") | F41: =IFERROR(ycps("VO","one_year_return"),"") | G41: =IFERROR(ycps("VO","three_year_annualized_return"),"") | H41: =IFERROR(ycps("VO","five_year_annualized_return"),"") | I41: =IFERROR(ycps("VO","one_year_volatility"),"") | J41: =IFERROR(IF(I41=0,0,(F41-'Data Input'!$B$4)/I41),0) -> 0 | K41: =IFERROR(ycps("VO","max_drawdown_3_year"),"") | L41: =IFERROR(ycps("VO","beta_5_year"),"") | M41: =IFERROR(ycps("VO","dividend_yield"),"") | N41: =IFERROR(ycps("VO","forward_pe_ratio"),"") | O41: =IFERROR(ycps("VO","one_month_return"),"") | P41: =IFERROR(ycps("VO","three_month_return"),"") | Q41: =IFERROR(ycps("VO","six_month_return"),"") | R41: =IFERROR(ycps("VO","one_year_return"),"") | S41: =IFERROR(MIN(100,MAX(0,ROUND(50+(O41*0.4+P41*0.3+Q41*0.2+R41*0.1)*200,0))),0) -> 0 | T41: =IFERROR(MIN(100,MAX(0,ROUND(50+R41*150+IF(F41>0,15,0)+IF(L41>0,5,-5),0))),0) -> 0 | U41: =IFERROR(MIN(100,MAX(0,ROUND(50+O41*200+IF(AND(O41>0,P41>0),10,-5)+IF(I41<0.2,10,-5),0))),0) -> 0 | V41: =IFERROR(MIN(100,MAX(0,ROUND(30+IF(I41>0,F41/I41,0)*40+IF(ABS(L41)<0.5,15,0)+IF(F41>0.08,10,0),0))),0) -> 0 | W41: =IFERROR(ROUND(T41*'Data Input'!$B$29+U41*'Data Input'!$B$30+V41*'Data Input'!$B$31+S41*'Data Input'!$B$32,0),0) -> 0 | X41: =IFERROR(IF(AND(W41>=70,IF(T41>=60,1,0)+IF(U41>=60,1,0)+IF(V41>=60,1,0)+IF(S41>=60,1,0)>=3),"STRONG BUY",IF(AND(W41>=60,IF(T41>=60,1,0)+IF(U41>=60,1,0)+IF(V41>=60,1,0)+IF(S41>=60,1,0)>=2),"BUY",IF(W41<35,"STRONG SELL",IF(AND(W41<45,IF(T41>=60,1,0)+IF(U41>=60,1,0)+IF(V41>=60,1,0)+IF(S41>=60,1,0)<=1),"SELL","HOLD")))),"") -> STRONG SELL | Y41: =IFERROR(IF(OR(X41="STRONG BUY",X41="STRONG SELL"),"HIGH",IF(OR(X41="BUY",X41="SELL"),"MEDIUM","NEUTRAL")),"") -> HIGH | Z41: =IFERROR(IF(COUNTIF('Asset Analysis'!$A$4:$A$27,A41)>0,"YES","NO"),"") -> NO | AA41: =IFERROR(IF(AND(Z41="NO",W41>=$B$7,J41>=$B$5,S41>=$B$6,I41<=$B$8,F41>=$B$9),"→ ADD TO PORTFOLIO",IF(AND(Z41="YES",OR(J41<=$B$10,S41<=$B$11,W41<=$B$12,K41<=-$B$13)),"→ DELETE FROM PORTFOLIO",IF(AND(Z41="YES",X41="HOLD"),"HOLD — MONITOR",IF(AND(Z41="YES",OR(X41="BUY",X41="STRONG BUY")),"HOLD — STRONG",IF(Z41="NO","NOT QUALIFIED","REVIEW"))))),"") -> NOT QUALIFIED | AB41: =IFERROR(IF(AA41="→ ADD TO PORTFOLIO",IF(W41>=70,"P1 — IMMEDIATE",IF(W41>=60,"P2 — THIS WEEK","P3 — NEXT REBALANCE")),IF(AA41="→ DELETE FROM PORTFOLIO","P1 — IMMEDIATE","—")),"") -> —
A42: EFA | B42: iShares MSCI EAFE | C42: Intl Equity | D42: Developed | E42: =IFERROR(ycps("EFA","price"),"") | F42: =IFERROR(ycps("EFA","one_year_return"),"") | G42: =IFERROR(ycps("EFA","three_year_annualized_return"),"") | H42: =IFERROR(ycps("EFA","five_year_annualized_return"),"") | I42: =IFERROR(ycps("EFA","one_year_volatility"),"") | J42: =IFERROR(IF(I42=0,0,(F42-'Data Input'!$B$4)/I42),0) -> 0 | K42: =IFERROR(ycps("EFA","max_drawdown_3_year"),"") | L42: =IFERROR(ycps("EFA","beta_5_year"),"") | M42: =IFERROR(ycps("EFA","dividend_yield"),"") | N42: =IFERROR(ycps("EFA","forward_pe_ratio"),"") | O42: =IFERROR(ycps("EFA","one_month_return"),"") | P42: =IFERROR(ycps("EFA","three_month_return"),"") | Q42: =IFERROR(ycps("EFA","six_month_return"),"") | R42: =IFERROR(ycps("EFA","one_year_return"),"") | S42: =IFERROR(MIN(100,MAX(0,ROUND(50+(O42*0.4+P42*0.3+Q42*0.2+R42*0.1)*200,0))),0) -> 0 | T42: =IFERROR(MIN(100,MAX(0,ROUND(50+R42*150+IF(F42>0,15,0)+IF(L42>0,5,-5),0))),0) -> 0 | U42: =IFERROR(MIN(100,MAX(0,ROUND(50+O42*200+IF(AND(O42>0,P42>0),10,-5)+IF(I42<0.2,10,-5),0))),0) -> 0 | V42: =IFERROR(MIN(100,MAX(0,ROUND(30+IF(I42>0,F42/I42,0)*40+IF(ABS(L42)<0.5,15,0)+IF(F42>0.08,10,0),0))),0) -> 0 | W42: =IFERROR(ROUND(T42*'Data Input'!$B$29+U42*'Data Input'!$B$30+V42*'Data Input'!$B$31+S42*'Data Input'!$B$32,0),0) -> 0 | X42: =IFERROR(IF(AND(W42>=70,IF(T42>=60,1,0)+IF(U42>=60,1,0)+IF(V42>=60,1,0)+IF(S42>=60,1,0)>=3),"STRONG BUY",IF(AND(W42>=60,IF(T42>=60,1,0)+IF(U42>=60,1,0)+IF(V42>=60,1,0)+IF(S42>=60,1,0)>=2),"BUY",IF(W42<35,"STRONG SELL",IF(AND(W42<45,IF(T42>=60,1,0)+IF(U42>=60,1,0)+IF(V42>=60,1,0)+IF(S42>=60,1,0)<=1),"SELL","HOLD")))),"") -> STRONG SELL | Y42: =IFERROR(IF(OR(X42="STRONG BUY",X42="STRONG SELL"),"HIGH",IF(OR(X42="BUY",X42="SELL"),"MEDIUM","NEUTRAL")),"") -> HIGH | Z42: =IFERROR(IF(COUNTIF('Asset Analysis'!$A$4:$A$27,A42)>0,"YES","NO"),"") -> YES | AA42: =IFERROR(IF(AND(Z42="NO",W42>=$B$7,J42>=$B$5,S42>=$B$6,I42<=$B$8,F42>=$B$9),"→ ADD TO PORTFOLIO",IF(AND(Z42="YES",OR(J42<=$B$10,S42<=$B$11,W42<=$B$12,K42<=-$B$13)),"→ DELETE FROM PORTFOLIO",IF(AND(Z42="YES",X42="HOLD"),"HOLD — MONITOR",IF(AND(Z42="YES",OR(X42="BUY",X42="STRONG BUY")),"HOLD — STRONG",IF(Z42="NO","NOT QUALIFIED","REVIEW"))))),"") -> → DELETE FROM PORTFOLIO | AB42: =IFERROR(IF(AA42="→ ADD TO PORTFOLIO",IF(W42>=70,"P1 — IMMEDIATE",IF(W42>=60,"P2 — THIS WEEK","P3 — NEXT REBALANCE")),IF(AA42="→ DELETE FROM PORTFOLIO","P1 — IMMEDIATE","—")),"") -> P1 — IMMEDIATE
A43: VEA | B43: Vanguard FTSE Developed | C43: Intl Equity | D43: Developed | E43: =IFERROR(ycps("VEA","price"),"") | F43: =IFERROR(ycps("VEA","one_year_return"),"") | G43: =IFERROR(ycps("VEA","three_year_annualized_return"),"") | H43: =IFERROR(ycps("VEA","five_year_annualized_return"),"") | I43: =IFERROR(ycps("VEA","one_year_volatility"),"") | J43: =IFERROR(IF(I43=0,0,(F43-'Data Input'!$B$4)/I43),0) -> 0 | K43: =IFERROR(ycps("VEA","max_drawdown_3_year"),"") | L43: =IFERROR(ycps("VEA","beta_5_year"),"") | M43: =IFERROR(ycps("VEA","dividend_yield"),"") | N43: =IFERROR(ycps("VEA","forward_pe_ratio"),"") | O43: =IFERROR(ycps("VEA","one_month_return"),"") | P43: =IFERROR(ycps("VEA","three_month_return"),"") | Q43: =IFERROR(ycps("VEA","six_month_return"),"") | R43: =IFERROR(ycps("VEA","one_year_return"),"") | S43: =IFERROR(MIN(100,MAX(0,ROUND(50+(O43*0.4+P43*0.3+Q43*0.2+R43*0.1)*200,0))),0) -> 0 | T43: =IFERROR(MIN(100,MAX(0,ROUND(50+R43*150+IF(F43>0,15,0)+IF(L43>0,5,-5),0))),0) -> 0 | U43: =IFERROR(MIN(100,MAX(0,ROUND(50+O43*200+IF(AND(O43>0,P43>0),10,-5)+IF(I43<0.2,10,-5),0))),0) -> 0 | V43: =IFERROR(MIN(100,MAX(0,ROUND(30+IF(I43>0,F43/I43,0)*40+IF(ABS(L43)<0.5,15,0)+IF(F43>0.08,10,0),0))),0) -> 0 | W43: =IFERROR(ROUND(T43*'Data Input'!$B$29+U43*'Data Input'!$B$30+V43*'Data Input'!$B$31+S43*'Data Input'!$B$32,0),0) -> 0 | X43: =IFERROR(IF(AND(W43>=70,IF(T43>=60,1,0)+IF(U43>=60,1,0)+IF(V43>=60,1,0)+IF(S43>=60,1,0)>=3),"STRONG BUY",IF(AND(W43>=60,IF(T43>=60,1,0)+IF(U43>=60,1,0)+IF(V43>=60,1,0)+IF(S43>=60,1,0)>=2),"BUY",IF(W43<35,"STRONG SELL",IF(AND(W43<45,IF(T43>=60,1,0)+IF(U43>=60,1,0)+IF(V43>=60,1,0)+IF(S43>=60,1,0)<=1),"SELL","HOLD")))),"") -> STRONG SELL | Y43: =IFERROR(IF(OR(X43="STRONG BUY",X43="STRONG SELL"),"HIGH",IF(OR(X43="BUY",X43="SELL"),"MEDIUM","NEUTRAL")),"") -> HIGH | Z43: =IFERROR(IF(COUNTIF('Asset Analysis'!$A$4:$A$27,A43)>0,"YES","NO"),"") -> NO | AA43: =IFERROR(IF(AND(Z43="NO",W43>=$B$7,J43>=$B$5,S43>=$B$6,I43<=$B$8,F43>=$B$9),"→ ADD TO PORTFOLIO",IF(AND(Z43="YES",OR(J43<=$B$10,S43<=$B$11,W43<=$B$12,K43<=-$B$13)),"→ DELETE FROM PORTFOLIO",IF(AND(Z43="YES",X43="HOLD"),"HOLD — MONITOR",IF(AND(Z43="YES",OR(X43="BUY",X43="STRONG BUY")),"HOLD — STRONG",IF(Z43="NO","NOT QUALIFIED","REVIEW"))))),"") -> NOT QUALIFIED | AB43: =IFERROR(IF(AA43="→ ADD TO PORTFOLIO",IF(W43>=70,"P1 — IMMEDIATE",IF(W43>=60,"P2 — THIS WEEK","P3 — NEXT REBALANCE")),IF(AA43="→ DELETE FROM PORTFOLIO","P1 — IMMEDIATE","—")),"") -> —
A44: EEM | B44: iShares MSCI EM | C44: Intl Equity | D44: Emerging | E44: =IFERROR(ycps("EEM","price"),"") | F44: =IFERROR(ycps("EEM","one_year_return"),"") | G44: =IFERROR(ycps("EEM","three_year_annualized_return"),"") | H44: =IFERROR(ycps("EEM","five_year_annualized_return"),"") | I44: =IFERROR(ycps("EEM","one_year_volatility"),"") | J44: =IFERROR(IF(I44=0,0,(F44-'Data Input'!$B$4)/I44),0) -> 0 | K44: =IFERROR(ycps("EEM","max_drawdown_3_year"),"") | L44: =IFERROR(ycps("EEM","beta_5_year"),"") | M44: =IFERROR(ycps("EEM","dividend_yield"),"") | N44: =IFERROR(ycps("EEM","forward_pe_ratio"),"") | O44: =IFERROR(ycps("EEM","one_month_return"),"") | P44: =IFERROR(ycps("EEM","three_month_return"),"") | Q44: =IFERROR(ycps("EEM","six_month_return"),"") | R44: =IFERROR(ycps("EEM","one_year_return"),"") | S44: =IFERROR(MIN(100,MAX(0,ROUND(50+(O44*0.4+P44*0.3+Q44*0.2+R44*0.1)*200,0))),0) -> 0 | T44: =IFERROR(MIN(100,MAX(0,ROUND(50+R44*150+IF(F44>0,15,0)+IF(L44>0,5,-5),0))),0) -> 0 | U44: =IFERROR(MIN(100,MAX(0,ROUND(50+O44*200+IF(AND(O44>0,P44>0),10,-5)+IF(I44<0.2,10,-5),0))),0) -> 0 | V44: =IFERROR(MIN(100,MAX(0,ROUND(30+IF(I44>0,F44/I44,0)*40+IF(ABS(L44)<0.5,15,0)+IF(F44>0.08,10,0),0))),0) -> 0 | W44: =IFERROR(ROUND(T44*'Data Input'!$B$29+U44*'Data Input'!$B$30+V44*'Data Input'!$B$31+S44*'Data Input'!$B$32,0),0) -> 0 | X44: =IFERROR(IF(AND(W44>=70,IF(T44>=60,1,0)+IF(U44>=60,1,0)+IF(V44>=60,1,0)+IF(S44>=60,1,0)>=3),"STRONG BUY",IF(AND(W44>=60,IF(T44>=60,1,0)+IF(U44>=60,1,0)+IF(V44>=60,1,0)+IF(S44>=60,1,0)>=2),"BUY",IF(W44<35,"STRONG SELL",IF(AND(W44<45,IF(T44>=60,1,0)+IF(U44>=60,1,0)+IF(V44>=60,1,0)+IF(S44>=60,1,0)<=1),"SELL","HOLD")))),"") -> STRONG SELL | Y44: =IFERROR(IF(OR(X44="STRONG BUY",X44="STRONG SELL"),"HIGH",IF(OR(X44="BUY",X44="SELL"),"MEDIUM","NEUTRAL")),"") -> HIGH | Z44: =IFERROR(IF(COUNTIF('Asset Analysis'!$A$4:$A$27,A44)>0,"YES","NO"),"") -> YES | AA44: =IFERROR(IF(AND(Z44="NO",W44>=$B$7,J44>=$B$5,S44>=$B$6,I44<=$B$8,F44>=$B$9),"→ ADD TO PORTFOLIO",IF(AND(Z44="YES",OR(J44<=$B$10,S44<=$B$11,W44<=$B$12,K44<=-$B$13)),"→ DELETE FROM PORTFOLIO",IF(AND(Z44="YES",X44="HOLD"),"HOLD — MONITOR",IF(AND(Z44="YES",OR(X44="BUY",X44="STRONG BUY")),"HOLD — STRONG",IF(Z44="NO","NOT QUALIFIED","REVIEW"))))),"") -> → DELETE FROM PORTFOLIO | AB44: =IFERROR(IF(AA44="→ ADD TO PORTFOLIO",IF(W44>=70,"P1 — IMMEDIATE",IF(W44>=60,"P2 — THIS WEEK","P3 — NEXT REBALANCE")),IF(AA44="→ DELETE FROM PORTFOLIO","P1 — IMMEDIATE","—")),"") -> P1 — IMMEDIATE
A45: VWO | B45: Vanguard FTSE EM | C45: Intl Equity | D45: Emerging | E45: =IFERROR(ycps("VWO","price"),"") | F45: =IFERROR(ycps("VWO","one_year_return"),"") | G45: =IFERROR(ycps("VWO","three_year_annualized_return"),"") | H45: =IFERROR(ycps("VWO","five_year_annualized_return"),"") | I45: =IFERROR(ycps("VWO","one_year_volatility"),"") | J45: =IFERROR(IF(I45=0,0,(F45-'Data Input'!$B$4)/I45),0) -> 0 | K45: =IFERROR(ycps("VWO","max_drawdown_3_year"),"") | L45: =IFERROR(ycps("VWO","beta_5_year"),"") | M45: =IFERROR(ycps("VWO","dividend_yield"),"") | N45: =IFERROR(ycps("VWO","forward_pe_ratio"),"") | O45: =IFERROR(ycps("VWO","one_month_return"),"") | P45: =IFERROR(ycps("VWO","three_month_return"),"") | Q45: =IFERROR(ycps("VWO","six_month_return"),"") | R45: =IFERROR(ycps("VWO","one_year_return"),"") | S45: =IFERROR(MIN(100,MAX(0,ROUND(50+(O45*0.4+P45*0.3+Q45*0.2+R45*0.1)*200,0))),0) -> 0 | T45: =IFERROR(MIN(100,MAX(0,ROUND(50+R45*150+IF(F45>0,15,0)+IF(L45>0,5,-5),0))),0) -> 0 | U45: =IFERROR(MIN(100,MAX(0,ROUND(50+O45*200+IF(AND(O45>0,P45>0),10,-5)+IF(I45<0.2,10,-5),0))),0) -> 0 | V45: =IFERROR(MIN(100,MAX(0,ROUND(30+IF(I45>0,F45/I45,0)*40+IF(ABS(L45)<0.5,15,0)+IF(F45>0.08,10,0),0))),0) -> 0 | W45: =IFERROR(ROUND(T45*'Data Input'!$B$29+U45*'Data Input'!$B$30+V45*'Data Input'!$B$31+S45*'Data Input'!$B$32,0),0) -> 0 | X45: =IFERROR(IF(AND(W45>=70,IF(T45>=60,1,0)+IF(U45>=60,1,0)+IF(V45>=60,1,0)+IF(S45>=60,1,0)>=3),"STRONG BUY",IF(AND(W45>=60,IF(T45>=60,1,0)+IF(U45>=60,1,0)+IF(V45>=60,1,0)+IF(S45>=60,1,0)>=2),"BUY",IF(W45<35,"STRONG SELL",IF(AND(W45<45,IF(T45>=60,1,0)+IF(U45>=60,1,0)+IF(V45>=60,1,0)+IF(S45>=60,1,0)<=1),"SELL","HOLD")))),"") -> STRONG SELL | Y45: =IFERROR(IF(OR(X45="STRONG BUY",X45="STRONG SELL"),"HIGH",IF(OR(X45="BUY",X45="SELL"),"MEDIUM","NEUTRAL")),"") -> HIGH | Z45: =IFERROR(IF(COUNTIF('Asset Analysis'!$A$4:$A$27,A45)>0,"YES","NO"),"") -> NO | AA45: =IFERROR(IF(AND(Z45="NO",W45>=$B$7,J45>=$B$5,S45>=$B$6,I45<=$B$8,F45>=$B$9),"→ ADD TO PORTFOLIO",IF(AND(Z45="YES",OR(J45<=$B$10,S45<=$B$11,W45<=$B$12,K45<=-$B$13)),"→ DELETE FROM PORTFOLIO",IF(AND(Z45="YES",X45="HOLD"),"HOLD — MONITOR",IF(AND(Z45="YES",OR(X45="BUY",X45="STRONG BUY")),"HOLD — STRONG",IF(Z45="NO","NOT QUALIFIED","REVIEW"))))),"") -> NOT QUALIFIED | AB45: =IFERROR(IF(AA45="→ ADD TO PORTFOLIO",IF(W45>=70,"P1 — IMMEDIATE",IF(W45>=60,"P2 — THIS WEEK","P3 — NEXT REBALANCE")),IF(AA45="→ DELETE FROM PORTFOLIO","P1 — IMMEDIATE","—")),"") -> —
A46: IXUS | B46: iShares Core Intl | C46: Intl Equity | D46: All-World ex US | E46: =IFERROR(ycps("IXUS","price"),"") | F46: =IFERROR(ycps("IXUS","one_year_return"),"") | G46: =IFERROR(ycps("IXUS","three_year_annualized_return"),"") | H46: =IFERROR(ycps("IXUS","five_year_annualized_return"),"") | I46: =IFERROR(ycps("IXUS","one_year_volatility"),"") | J46: =IFERROR(IF(I46=0,0,(F46-'Data Input'!$B$4)/I46),0) -> 0 | K46: =IFERROR(ycps("IXUS","max_drawdown_3_year"),"") | L46: =IFERROR(ycps("IXUS","beta_5_year"),"") | M46: =IFERROR(ycps("IXUS","dividend_yield"),"") | N46: =IFERROR(ycps("IXUS","forward_pe_ratio"),"") | O46: =IFERROR(ycps("IXUS","one_month_return"),"") | P46: =IFERROR(ycps("IXUS","three_month_return"),"") | Q46: =IFERROR(ycps("IXUS","six_month_return"),"") | R46: =IFERROR(ycps("IXUS","one_year_return"),"") | S46: =IFERROR(MIN(100,MAX(0,ROUND(50+(O46*0.4+P46*0.3+Q46*0.2+R46*0.1)*200,0))),0) -> 0 | T46: =IFERROR(MIN(100,MAX(0,ROUND(50+R46*150+IF(F46>0,15,0)+IF(L46>0,5,-5),0))),0) -> 0 | U46: =IFERROR(MIN(100,MAX(0,ROUND(50+O46*200+IF(AND(O46>0,P46>0),10,-5)+IF(I46<0.2,10,-5),0))),0) -> 0 | V46: =IFERROR(MIN(100,MAX(0,ROUND(30+IF(I46>0,F46/I46,0)*40+IF(ABS(L46)<0.5,15,0)+IF(F46>0.08,10,0),0))),0) -> 0 | W46: =IFERROR(ROUND(T46*'Data Input'!$B$29+U46*'Data Input'!$B$30+V46*'Data Input'!$B$31+S46*'Data Input'!$B$32,0),0) -> 0 | X46: =IFERROR(IF(AND(W46>=70,IF(T46>=60,1,0)+IF(U46>=60,1,0)+IF(V46>=60,1,0)+IF(S46>=60,1,0)>=3),"STRONG BUY",IF(AND(W46>=60,IF(T46>=60,1,0)+IF(U46>=60,1,0)+IF(V46>=60,1,0)+IF(S46>=60,1,0)>=2),"BUY",IF(W46<35,"STRONG SELL",IF(AND(W46<45,IF(T46>=60,1,0)+IF(U46>=60,1,0)+IF(V46>=60,1,0)+IF(S46>=60,1,0)<=1),"SELL","HOLD")))),"") -> STRONG SELL | Y46: =IFERROR(IF(OR(X46="STRONG BUY",X46="STRONG SELL"),"HIGH",IF(OR(X46="BUY",X46="SELL"),"MEDIUM","NEUTRAL")),"") -> HIGH | Z46: =IFERROR(IF(COUNTIF('Asset Analysis'!$A$4:$A$27,A46)>0,"YES","NO"),"") -> NO | AA46: =IFERROR(IF(AND(Z46="NO",W46>=$B$7,J46>=$B$5,S46>=$B$6,I46<=$B$8,F46>=$B$9),"→ ADD TO PORTFOLIO",IF(AND(Z46="YES",OR(J46<=$B$10,S46<=$B$11,W46<=$B$12,K46<=-$B$13)),"→ DELETE FROM PORTFOLIO",IF(AND(Z46="YES",X46="HOLD"),"HOLD — MONITOR",IF(AND(Z46="YES",OR(X46="BUY",X46="STRONG BUY")),"HOLD — STRONG",IF(Z46="NO","NOT QUALIFIED","REVIEW"))))),"") -> NOT QUALIFIED | AB46: =IFERROR(IF(AA46="→ ADD TO PORTFOLIO",IF(W46>=70,"P1 — IMMEDIATE",IF(W46>=60,"P2 — THIS WEEK","P3 — NEXT REBALANCE")),IF(AA46="→ DELETE FROM PORTFOLIO","P1 — IMMEDIATE","—")),"") -> —
A47: IEFA | B47: iShares Core EAFE | C47: Intl Equity | D47: Developed | E47: =IFERROR(ycps("IEFA","price"),"") | F47: =IFERROR(ycps("IEFA","one_year_return"),"") | G47: =IFERROR(ycps("IEFA","three_year_annualized_return"),"") | H47: =IFERROR(ycps("IEFA","five_year_annualized_return"),"") | I47: =IFERROR(ycps("IEFA","one_year_volatility"),"") | J47: =IFERROR(IF(I47=0,0,(F47-'Data Input'!$B$4)/I47),0) -> 0 | K47: =IFERROR(ycps("IEFA","max_drawdown_3_year"),"") | L47: =IFERROR(ycps("IEFA","beta_5_year"),"") | M47: =IFERROR(ycps("IEFA","dividend_yield"),"") | N47: =IFERROR(ycps("IEFA","forward_pe_ratio"),"") | O47: =IFERROR(ycps("IEFA","one_month_return"),"") | P47: =IFERROR(ycps("IEFA","three_month_return"),"") | Q47: =IFERROR(ycps("IEFA","six_month_return"),"") | R47: =IFERROR(ycps("IEFA","one_year_return"),"") | S47: =IFERROR(MIN(100,MAX(0,ROUND(50+(O47*0.4+P47*0.3+Q47*0.2+R47*0.1)*200,0))),0) -> 0 | T47: =IFERROR(MIN(100,MAX(0,ROUND(50+R47*150+IF(F47>0,15,0)+IF(L47>0,5,-5),0))),0) -> 0 | U47: =IFERROR(MIN(100,MAX(0,ROUND(50+O47*200+IF(AND(O47>0,P47>0),10,-5)+IF(I47<0.2,10,-5),0))),0) -> 0 | V47: =IFERROR(MIN(100,MAX(0,ROUND(30+IF(I47>0,F47/I47,0)*40+IF(ABS(L47)<0.5,15,0)+IF(F47>0.08,10,0),0))),0) -> 0 | W47: =IFERROR(ROUND(T47*'Data Input'!$B$29+U47*'Data Input'!$B$30+V47*'Data Input'!$B$31+S47*'Data Input'!$B$32,0),0) -> 0 | X47: =IFERROR(IF(AND(W47>=70,IF(T47>=60,1,0)+IF(U47>=60,1,0)+IF(V47>=60,1,0)+IF(S47>=60,1,0)>=3),"STRONG BUY",IF(AND(W47>=60,IF(T47>=60,1,0)+IF(U47>=60,1,0)+IF(V47>=60,1,0)+IF(S47>=60,1,0)>=2),"BUY",IF(W47<35,"STRONG SELL",IF(AND(W47<45,IF(T47>=60,1,0)+IF(U47>=60,1,0)+IF(V47>=60,1,0)+IF(S47>=60,1,0)<=1),"SELL","HOLD")))),"") -> STRONG SELL | Y47: =IFERROR(IF(OR(X47="STRONG BUY",X47="STRONG SELL"),"HIGH",IF(OR(X47="BUY",X47="SELL"),"MEDIUM","NEUTRAL")),"") -> HIGH | Z47: =IFERROR(IF(COUNTIF('Asset Analysis'!$A$4:$A$27,A47)>0,"YES","NO"),"") -> NO | AA47: =IFERROR(IF(AND(Z47="NO",W47>=$B$7,J47>=$B$5,S47>=$B$6,I47<=$B$8,F47>=$B$9),"→ ADD TO PORTFOLIO",IF(AND(Z47="YES",OR(J47<=$B$10,S47<=$B$11,W47<=$B$12,K47<=-$B$13)),"→ DELETE FROM PORTFOLIO",IF(AND(Z47="YES",X47="HOLD"),"HOLD — MONITOR",IF(AND(Z47="YES",OR(X47="BUY",X47="STRONG BUY")),"HOLD — STRONG",IF(Z47="NO","NOT QUALIFIED","REVIEW"))))),"") -> NOT QUALIFIED | AB47: =IFERROR(IF(AA47="→ ADD TO PORTFOLIO",IF(W47>=70,"P1 — IMMEDIATE",IF(W47>=60,"P2 — THIS WEEK","P3 — NEXT REBALANCE")),IF(AA47="→ DELETE FROM PORTFOLIO","P1 — IMMEDIATE","—")),"") -> —
A48: EWJ | B48: iShares MSCI Japan | C48: Intl Equity | D48: Japan | E48: =IFERROR(ycps("EWJ","price"),"") | F48: =IFERROR(ycps("EWJ","one_year_return"),"") | G48: =IFERROR(ycps("EWJ","three_year_annualized_return"),"") | H48: =IFERROR(ycps("EWJ","five_year_annualized_return"),"") | I48: =IFERROR(ycps("EWJ","one_year_volatility"),"") | J48: =IFERROR(IF(I48=0,0,(F48-'Data Input'!$B$4)/I48),0) -> 0 | K48: =IFERROR(ycps("EWJ","max_drawdown_3_year"),"") | L48: =IFERROR(ycps("EWJ","beta_5_year"),"") | M48: =IFERROR(ycps("EWJ","dividend_yield"),"") | N48: =IFERROR(ycps("EWJ","forward_pe_ratio"),"") | O48: =IFERROR(ycps("EWJ","one_month_return"),"") | P48: =IFERROR(ycps("EWJ","three_month_return"),"") | Q48: =IFERROR(ycps("EWJ","six_month_return"),"") | R48: =IFERROR(ycps("EWJ","one_year_return"),"") | S48: =IFERROR(MIN(100,MAX(0,ROUND(50+(O48*0.4+P48*0.3+Q48*0.2+R48*0.1)*200,0))),0) -> 0 | T48: =IFERROR(MIN(100,MAX(0,ROUND(50+R48*150+IF(F48>0,15,0)+IF(L48>0,5,-5),0))),0) -> 0 | U48: =IFERROR(MIN(100,MAX(0,ROUND(50+O48*200+IF(AND(O48>0,P48>0),10,-5)+IF(I48<0.2,10,-5),0))),0) -> 0 | V48: =IFERROR(MIN(100,MAX(0,ROUND(30+IF(I48>0,F48/I48,0)*40+IF(ABS(L48)<0.5,15,0)+IF(F48>0.08,10,0),0))),0) -> 0 | W48: =IFERROR(ROUND(T48*'Data Input'!$B$29+U48*'Data Input'!$B$30+V48*'Data Input'!$B$31+S48*'Data Input'!$B$32,0),0) -> 0 | X48: =IFERROR(IF(AND(W48>=70,IF(T48>=60,1,0)+IF(U48>=60,1,0)+IF(V48>=60,1,0)+IF(S48>=60,1,0)>=3),"STRONG BUY",IF(AND(W48>=60,IF(T48>=60,1,0)+IF(U48>=60,1,0)+IF(V48>=60,1,0)+IF(S48>=60,1,0)>=2),"BUY",IF(W48<35,"STRONG SELL",IF(AND(W48<45,IF(T48>=60,1,0)+IF(U48>=60,1,0)+IF(V48>=60,1,0)+IF(S48>=60,1,0)<=1),"SELL","HOLD")))),"") -> STRONG SELL | Y48: =IFERROR(IF(OR(X48="STRONG BUY",X48="STRONG SELL"),"HIGH",IF(OR(X48="BUY",X48="SELL"),"MEDIUM","NEUTRAL")),"") -> HIGH | Z48: =IFERROR(IF(COUNTIF('Asset Analysis'!$A$4:$A$27,A48)>0,"YES","NO"),"") -> NO | AA48: =IFERROR(IF(AND(Z48="NO",W48>=$B$7,J48>=$B$5,S48>=$B$6,I48<=$B$8,F48>=$B$9),"→ ADD TO PORTFOLIO",IF(AND(Z48="YES",OR(J48<=$B$10,S48<=$B$11,W48<=$B$12,K48<=-$B$13)),"→ DELETE FROM PORTFOLIO",IF(AND(Z48="YES",X48="HOLD"),"HOLD — MONITOR",IF(AND(Z48="YES",OR(X48="BUY",X48="STRONG BUY")),"HOLD — STRONG",IF(Z48="NO","NOT QUALIFIED","REVIEW"))))),"") -> NOT QUALIFIED | AB48: =IFERROR(IF(AA48="→ ADD TO PORTFOLIO",IF(W48>=70,"P1 — IMMEDIATE",IF(W48>=60,"P2 — THIS WEEK","P3 — NEXT REBALANCE")),IF(AA48="→ DELETE FROM PORTFOLIO","P1 — IMMEDIATE","—")),"") -> —
A49: FXI | B49: iShares China Large | C49: Intl Equity | D49: China | E49: =IFERROR(ycps("FXI","price"),"") | F49: =IFERROR(ycps("FXI","one_year_return"),"") | G49: =IFERROR(ycps("FXI","three_year_annualized_return"),"") | H49: =IFERROR(ycps("FXI","five_year_annualized_return"),"") | I49: =IFERROR(ycps("FXI","one_year_volatility"),"") | J49: =IFERROR(IF(I49=0,0,(F49-'Data Input'!$B$4)/I49),0) -> 0 | K49: =IFERROR(ycps("FXI","max_drawdown_3_year"),"") | L49: =IFERROR(ycps("FXI","beta_5_year"),"") | M49: =IFERROR(ycps("FXI","dividend_yield"),"") | N49: =IFERROR(ycps("FXI","forward_pe_ratio"),"") | O49: =IFERROR(ycps("FXI","one_month_return"),"") | P49: =IFERROR(ycps("FXI","three_month_return"),"") | Q49: =IFERROR(ycps("FXI","six_month_return"),"") | R49: =IFERROR(ycps("FXI","one_year_return"),"") | S49: =IFERROR(MIN(100,MAX(0,ROUND(50+(O49*0.4+P49*0.3+Q49*0.2+R49*0.1)*200,0))),0) -> 0 | T49: =IFERROR(MIN(100,MAX(0,ROUND(50+R49*150+IF(F49>0,15,0)+IF(L49>0,5,-5),0))),0) -> 0 | U49: =IFERROR(MIN(100,MAX(0,ROUND(50+O49*200+IF(AND(O49>0,P49>0),10,-5)+IF(I49<0.2,10,-5),0))),0) -> 0 | V49: =IFERROR(MIN(100,MAX(0,ROUND(30+IF(I49>0,F49/I49,0)*40+IF(ABS(L49)<0.5,15,0)+IF(F49>0.08,10,0),0))),0) -> 0 | W49: =IFERROR(ROUND(T49*'Data Input'!$B$29+U49*'Data Input'!$B$30+V49*'Data Input'!$B$31+S49*'Data Input'!$B$32,0),0) -> 0 | X49: =IFERROR(IF(AND(W49>=70,IF(T49>=60,1,0)+IF(U49>=60,1,0)+IF(V49>=60,1,0)+IF(S49>=60,1,0)>=3),"STRONG BUY",IF(AND(W49>=60,IF(T49>=60,1,0)+IF(U49>=60,1,0)+IF(V49>=60,1,0)+IF(S49>=60,1,0)>=2),"BUY",IF(W49<35,"STRONG SELL",IF(AND(W49<45,IF(T49>=60,1,0)+IF(U49>=60,1,0)+IF(V49>=60,1,0)+IF(S49>=60,1,0)<=1),"SELL","HOLD")))),"") -> STRONG SELL | Y49: =IFERROR(IF(OR(X49="STRONG BUY",X49="STRONG SELL"),"HIGH",IF(OR(X49="BUY",X49="SELL"),"MEDIUM","NEUTRAL")),"") -> HIGH | Z49: =IFERROR(IF(COUNTIF('Asset Analysis'!$A$4:$A$27,A49)>0,"YES","NO"),"") -> NO | AA49: =IFERROR(IF(AND(Z49="NO",W49>=$B$7,J49>=$B$5,S49>=$B$6,I49<=$B$8,F49>=$B$9),"→ ADD TO PORTFOLIO",IF(AND(Z49="YES",OR(J49<=$B$10,S49<=$B$11,W49<=$B$12,K49<=-$B$13)),"→ DELETE FROM PORTFOLIO",IF(AND(Z49="YES",X49="HOLD"),"HOLD — MONITOR",IF(AND(Z49="YES",OR(X49="BUY",X49="STRONG BUY")),"HOLD — STRONG",IF(Z49="NO","NOT QUALIFIED","REVIEW"))))),"") -> NOT QUALIFIED | AB49: =IFERROR(IF(AA49="→ ADD TO PORTFOLIO",IF(W49>=70,"P1 — IMMEDIATE",IF(W49>=60,"P2 — THIS WEEK","P3 — NEXT REBALANCE")),IF(AA49="→ DELETE FROM PORTFOLIO","P1 — IMMEDIATE","—")),"") -> —
A50: AGG | B50: iShares Core US Agg | C50: Fixed Income | D50: Core Bond | E50: =IFERROR(ycps("AGG","price"),"") | F50: =IFERROR(ycps("AGG","one_year_return"),"") | G50: =IFERROR(ycps("AGG","three_year_annualized_return"),"") | H50: =IFERROR(ycps("AGG","five_year_annualized_return"),"") | I50: =IFERROR(ycps("AGG","one_year_volatility"),"") | J50: =IFERROR(IF(I50=0,0,(F50-'Data Input'!$B$4)/I50),0) -> 0 | K50: =IFERROR(ycps("AGG","max_drawdown_3_year"),"") | L50: =IFERROR(ycps("AGG","beta_5_year"),"") | M50: =IFERROR(ycps("AGG","dividend_yield"),"") | N50: =IFERROR(ycps("AGG","forward_pe_ratio"),"") | O50: =IFERROR(ycps("AGG","one_month_return"),"") | P50: =IFERROR(ycps("AGG","three_month_return"),"") | Q50: =IFERROR(ycps("AGG","six_month_return"),"") | R50: =IFERROR(ycps("AGG","one_year_return"),"") | S50: =IFERROR(MIN(100,MAX(0,ROUND(50+(O50*0.4+P50*0.3+Q50*0.2+R50*0.1)*200,0))),0) -> 0 | T50: =IFERROR(MIN(100,MAX(0,ROUND(50+R50*150+IF(F50>0,15,0)+IF(L50>0,5,-5),0))),0) -> 0 | U50: =IFERROR(MIN(100,MAX(0,ROUND(50+O50*200+IF(AND(O50>0,P50>0),10,-5)+IF(I50<0.2,10,-5),0))),0) -> 0 | V50: =IFERROR(MIN(100,MAX(0,ROUND(30+IF(I50>0,F50/I50,0)*40+IF(ABS(L50)<0.5,15,0)+IF(F50>0.08,10,0),0))),0) -> 0 | W50: =IFERROR(ROUND(T50*'Data Input'!$B$29+U50*'Data Input'!$B$30+V50*'Data Input'!$B$31+S50*'Data Input'!$B$32,0),0) -> 0 | X50: =IFERROR(IF(AND(W50>=70,IF(T50>=60,1,0)+IF(U50>=60,1,0)+IF(V50>=60,1,0)+IF(S50>=60,1,0)>=3),"STRONG BUY",IF(AND(W50>=60,IF(T50>=60,1,0)+IF(U50>=60,1,0)+IF(V50>=60,1,0)+IF(S50>=60,1,0)>=2),"BUY",IF(W50<35,"STRONG SELL",IF(AND(W50<45,IF(T50>=60,1,0)+IF(U50>=60,1,0)+IF(V50>=60,1,0)+IF(S50>=60,1,0)<=1),"SELL","HOLD")))),"") -> STRONG SELL | Y50: =IFERROR(IF(OR(X50="STRONG BUY",X50="STRONG SELL"),"HIGH",IF(OR(X50="BUY",X50="SELL"),"MEDIUM","NEUTRAL")),"") -> HIGH | Z50: =IFERROR(IF(COUNTIF('Asset Analysis'!$A$4:$A$27,A50)>0,"YES","NO"),"") -> YES | AA50: =IFERROR(IF(AND(Z50="NO",W50>=$B$7,J50>=$B$5,S50>=$B$6,I50<=$B$8,F50>=$B$9),"→ ADD TO PORTFOLIO",IF(AND(Z50="YES",OR(J50<=$B$10,S50<=$B$11,W50<=$B$12,K50<=-$B$13)),"→ DELETE FROM PORTFOLIO",IF(AND(Z50="YES",X50="HOLD"),"HOLD — MONITOR",IF(AND(Z50="YES",OR(X50="BUY",X50="STRONG BUY")),"HOLD — STRONG",IF(Z50="NO","NOT QUALIFIED","REVIEW"))))),"") -> → DELETE FROM PORTFOLIO | AB50: =IFERROR(IF(AA50="→ ADD TO PORTFOLIO",IF(W50>=70,"P1 — IMMEDIATE",IF(W50>=60,"P2 — THIS WEEK","P3 — NEXT REBALANCE")),IF(AA50="→ DELETE FROM PORTFOLIO","P1 — IMMEDIATE","—")),"") -> P1 — IMMEDIATE
A51: BND | B51: Vanguard Total Bond | C51: Fixed Income | D51: Core Bond | E51: =IFERROR(ycps("BND","price"),"") | F51: =IFERROR(ycps("BND","one_year_return"),"") | G51: =IFERROR(ycps("BND","three_year_annualized_return"),"") | H51: =IFERROR(ycps("BND","five_year_annualized_return"),"") | I51: =IFERROR(ycps("BND","one_year_volatility"),"") | J51: =IFERROR(IF(I51=0,0,(F51-'Data Input'!$B$4)/I51),0) -> 0 | K51: =IFERROR(ycps("BND","max_drawdown_3_year"),"") | L51: =IFERROR(ycps("BND","beta_5_year"),"") | M51: =IFERROR(ycps("BND","dividend_yield"),"") | N51: =IFERROR(ycps("BND","forward_pe_ratio"),"") | O51: =IFERROR(ycps("BND","one_month_return"),"") | P51: =IFERROR(ycps("BND","three_month_return"),"") | Q51: =IFERROR(ycps("BND","six_month_return"),"") | R51: =IFERROR(ycps("BND","one_year_return"),"") | S51: =IFERROR(MIN(100,MAX(0,ROUND(50+(O51*0.4+P51*0.3+Q51*0.2+R51*0.1)*200,0))),0) -> 0 | T51: =IFERROR(MIN(100,MAX(0,ROUND(50+R51*150+IF(F51>0,15,0)+IF(L51>0,5,-5),0))),0) -> 0 | U51: =IFERROR(MIN(100,MAX(0,ROUND(50+O51*200+IF(AND(O51>0,P51>0),10,-5)+IF(I51<0.2,10,-5),0))),0) -> 0 | V51: =IFERROR(MIN(100,MAX(0,ROUND(30+IF(I51>0,F51/I51,0)*40+IF(ABS(L51)<0.5,15,0)+IF(F51>0.08,10,0),0))),0) -> 0 | W51: =IFERROR(ROUND(T51*'Data Input'!$B$29+U51*'Data Input'!$B$30+V51*'Data Input'!$B$31+S51*'Data Input'!$B$32,0),0) -> 0 | X51: =IFERROR(IF(AND(W51>=70,IF(T51>=60,1,0)+IF(U51>=60,1,0)+IF(V51>=60,1,0)+IF(S51>=60,1,0)>=3),"STRONG BUY",IF(AND(W51>=60,IF(T51>=60,1,0)+IF(U51>=60,1,0)+IF(V51>=60,1,0)+IF(S51>=60,1,0)>=2),"BUY",IF(W51<35,"STRONG SELL",IF(AND(W51<45,IF(T51>=60,1,0)+IF(U51>=60,1,0)+IF(V51>=60,1,0)+IF(S51>=60,1,0)<=1),"SELL","HOLD")))),"") -> STRONG SELL | Y51: =IFERROR(IF(OR(X51="STRONG BUY",X51="STRONG SELL"),"HIGH",IF(OR(X51="BUY",X51="SELL"),"MEDIUM","NEUTRAL")),"") -> HIGH | Z51: =IFERROR(IF(COUNTIF('Asset Analysis'!$A$4:$A$27,A51)>0,"YES","NO"),"") -> NO | AA51: =IFERROR(IF(AND(Z51="NO",W51>=$B$7,J51>=$B$5,S51>=$B$6,I51<=$B$8,F51>=$B$9),"→ ADD TO PORTFOLIO",IF(AND(Z51="YES",OR(J51<=$B$10,S51<=$B$11,W51<=$B$12,K51<=-$B$13)),"→ DELETE FROM PORTFOLIO",IF(AND(Z51="YES",X51="HOLD"),"HOLD — MONITOR",IF(AND(Z51="YES",OR(X51="BUY",X51="STRONG BUY")),"HOLD — STRONG",IF(Z51="NO","NOT QUALIFIED","REVIEW"))))),"") -> NOT QUALIFIED | AB51: =IFERROR(IF(AA51="→ ADD TO PORTFOLIO",IF(W51>=70,"P1 — IMMEDIATE",IF(W51>=60,"P2 — THIS WEEK","P3 — NEXT REBALANCE")),IF(AA51="→ DELETE FROM PORTFOLIO","P1 — IMMEDIATE","—")),"") -> —
A52: TLT | B52: iShares 20+ Yr Treasury | C52: Fixed Income | D52: Long Treasury | E52: =IFERROR(ycps("TLT","price"),"") | F52: =IFERROR(ycps("TLT","one_year_return"),"") | G52: =IFERROR(ycps("TLT","three_year_annualized_return"),"") | H52: =IFERROR(ycps("TLT","five_year_annualized_return"),"") | I52: =IFERROR(ycps("TLT","one_year_volatility"),"") | J52: =IFERROR(IF(I52=0,0,(F52-'Data Input'!$B$4)/I52),0) -> 0 | K52: =IFERROR(ycps("TLT","max_drawdown_3_year"),"") | L52: =IFERROR(ycps("TLT","beta_5_year"),"") | M52: =IFERROR(ycps("TLT","dividend_yield"),"") | N52: =IFERROR(ycps("TLT","forward_pe_ratio"),"") | O52: =IFERROR(ycps("TLT","one_month_return"),"") | P52: =IFERROR(ycps("TLT","three_month_return"),"") | Q52: =IFERROR(ycps("TLT","six_month_return"),"") | R52: =IFERROR(ycps("TLT","one_year_return"),"") | S52: =IFERROR(MIN(100,MAX(0,ROUND(50+(O52*0.4+P52*0.3+Q52*0.2+R52*0.1)*200,0))),0) -> 0 | T52: =IFERROR(MIN(100,MAX(0,ROUND(50+R52*150+IF(F52>0,15,0)+IF(L52>0,5,-5),0))),0) -> 0 | U52: =IFERROR(MIN(100,MAX(0,ROUND(50+O52*200+IF(AND(O52>0,P52>0),10,-5)+IF(I52<0.2,10,-5),0))),0) -> 0 | V52: =IFERROR(MIN(100,MAX(0,ROUND(30+IF(I52>0,F52/I52,0)*40+IF(ABS(L52)<0.5,15,0)+IF(F52>0.08,10,0),0))),0) -> 0 | W52: =IFERROR(ROUND(T52*'Data Input'!$B$29+U52*'Data Input'!$B$30+V52*'Data Input'!$B$31+S52*'Data Input'!$B$32,0),0) -> 0 | X52: =IFERROR(IF(AND(W52>=70,IF(T52>=60,1,0)+IF(U52>=60,1,0)+IF(V52>=60,1,0)+IF(S52>=60,1,0)>=3),"STRONG BUY",IF(AND(W52>=60,IF(T52>=60,1,0)+IF(U52>=60,1,0)+IF(V52>=60,1,0)+IF(S52>=60,1,0)>=2),"BUY",IF(W52<35,"STRONG SELL",IF(AND(W52<45,IF(T52>=60,1,0)+IF(U52>=60,1,0)+IF(V52>=60,1,0)+IF(S52>=60,1,0)<=1),"SELL","HOLD")))),"") -> STRONG SELL | Y52: =IFERROR(IF(OR(X52="STRONG BUY",X52="STRONG SELL"),"HIGH",IF(OR(X52="BUY",X52="SELL"),"MEDIUM","NEUTRAL")),"") -> HIGH | Z52: =IFERROR(IF(COUNTIF('Asset Analysis'!$A$4:$A$27,A52)>0,"YES","NO"),"") -> YES | AA52: =IFERROR(IF(AND(Z52="NO",W52>=$B$7,J52>=$B$5,S52>=$B$6,I52<=$B$8,F52>=$B$9),"→ ADD TO PORTFOLIO",IF(AND(Z52="YES",OR(J52<=$B$10,S52<=$B$11,W52<=$B$12,K52<=-$B$13)),"→ DELETE FROM PORTFOLIO",IF(AND(Z52="YES",X52="HOLD"),"HOLD — MONITOR",IF(AND(Z52="YES",OR(X52="BUY",X52="STRONG BUY")),"HOLD — STRONG",IF(Z52="NO","NOT QUALIFIED","REVIEW"))))),"") -> → DELETE FROM PORTFOLIO | AB52: =IFERROR(IF(AA52="→ ADD TO PORTFOLIO",IF(W52>=70,"P1 — IMMEDIATE",IF(W52>=60,"P2 — THIS WEEK","P3 — NEXT REBALANCE")),IF(AA52="→ DELETE FROM PORTFOLIO","P1 — IMMEDIATE","—")),"") -> P1 — IMMEDIATE
A53: IEF | B53: iShares 7-10 Yr Treasury | C53: Fixed Income | D53: Interm Treasury | E53: =IFERROR(ycps("IEF","price"),"") | F53: =IFERROR(ycps("IEF","one_year_return"),"") | G53: =IFERROR(ycps("IEF","three_year_annualized_return"),"") | H53: =IFERROR(ycps("IEF","five_year_annualized_return"),"") | I53: =IFERROR(ycps("IEF","one_year_volatility"),"") | J53: =IFERROR(IF(I53=0,0,(F53-'Data Input'!$B$4)/I53),0) -> 0 | K53: =IFERROR(ycps("IEF","max_drawdown_3_year"),"") | L53: =IFERROR(ycps("IEF","beta_5_year"),"") | M53: =IFERROR(ycps("IEF","dividend_yield"),"") | N53: =IFERROR(ycps("IEF","forward_pe_ratio"),"") | O53: =IFERROR(ycps("IEF","one_month_return"),"") | P53: =IFERROR(ycps("IEF","three_month_return"),"") | Q53: =IFERROR(ycps("IEF","six_month_return"),"") | R53: =IFERROR(ycps("IEF","one_year_return"),"") | S53: =IFERROR(MIN(100,MAX(0,ROUND(50+(O53*0.4+P53*0.3+Q53*0.2+R53*0.1)*200,0))),0) -> 0 | T53: =IFERROR(MIN(100,MAX(0,ROUND(50+R53*150+IF(F53>0,15,0)+IF(L53>0,5,-5),0))),0) -> 0 | U53: =IFERROR(MIN(100,MAX(0,ROUND(50+O53*200+IF(AND(O53>0,P53>0),10,-5)+IF(I53<0.2,10,-5),0))),0) -> 0 | V53: =IFERROR(MIN(100,MAX(0,ROUND(30+IF(I53>0,F53/I53,0)*40+IF(ABS(L53)<0.5,15,0)+IF(F53>0.08,10,0),0))),0) -> 0 | W53: =IFERROR(ROUND(T53*'Data Input'!$B$29+U53*'Data Input'!$B$30+V53*'Data Input'!$B$31+S53*'Data Input'!$B$32,0),0) -> 0 | X53: =IFERROR(IF(AND(W53>=70,IF(T53>=60,1,0)+IF(U53>=60,1,0)+IF(V53>=60,1,0)+IF(S53>=60,1,0)>=3),"STRONG BUY",IF(AND(W53>=60,IF(T53>=60,1,0)+IF(U53>=60,1,0)+IF(V53>=60,1,0)+IF(S53>=60,1,0)>=2),"BUY",IF(W53<35,"STRONG SELL",IF(AND(W53<45,IF(T53>=60,1,0)+IF(U53>=60,1,0)+IF(V53>=60,1,0)+IF(S53>=60,1,0)<=1),"SELL","HOLD")))),"") -> STRONG SELL | Y53: =IFERROR(IF(OR(X53="STRONG BUY",X53="STRONG SELL"),"HIGH",IF(OR(X53="BUY",X53="SELL"),"MEDIUM","NEUTRAL")),"") -> HIGH | Z53: =IFERROR(IF(COUNTIF('Asset Analysis'!$A$4:$A$27,A53)>0,"YES","NO"),"") -> NO | AA53: =IFERROR(IF(AND(Z53="NO",W53>=$B$7,J53>=$B$5,S53>=$B$6,I53<=$B$8,F53>=$B$9),"→ ADD TO PORTFOLIO",IF(AND(Z53="YES",OR(J53<=$B$10,S53<=$B$11,W53<=$B$12,K53<=-$B$13)),"→ DELETE FROM PORTFOLIO",IF(AND(Z53="YES",X53="HOLD"),"HOLD — MONITOR",IF(AND(Z53="YES",OR(X53="BUY",X53="STRONG BUY")),"HOLD — STRONG",IF(Z53="NO","NOT QUALIFIED","REVIEW"))))),"") -> NOT QUALIFIED | AB53: =IFERROR(IF(AA53="→ ADD TO PORTFOLIO",IF(W53>=70,"P1 — IMMEDIATE",IF(W53>=60,"P2 — THIS WEEK","P3 — NEXT REBALANCE")),IF(AA53="→ DELETE FROM PORTFOLIO","P1 — IMMEDIATE","—")),"") -> —
A54: SHY | B54: iShares 1-3 Yr Treasury | C54: Fixed Income | D54: Short Treasury | E54: =IFERROR(ycps("SHY","price"),"") | F54: =IFERROR(ycps("SHY","one_year_return"),"") | G54: =IFERROR(ycps("SHY","three_year_annualized_return"),"") | H54: =IFERROR(ycps("SHY","five_year_annualized_return"),"") | I54: =IFERROR(ycps("SHY","one_year_volatility"),"") | J54: =IFERROR(IF(I54=0,0,(F54-'Data Input'!$B$4)/I54),0) -> 0 | K54: =IFERROR(ycps("SHY","max_drawdown_3_year"),"") | L54: =IFERROR(ycps("SHY","beta_5_year"),"") | M54: =IFERROR(ycps("SHY","dividend_yield"),"") | N54: =IFERROR(ycps("SHY","forward_pe_ratio"),"") | O54: =IFERROR(ycps("SHY","one_month_return"),"") | P54: =IFERROR(ycps("SHY","three_month_return"),"") | Q54: =IFERROR(ycps("SHY","six_month_return"),"") | R54: =IFERROR(ycps("SHY","one_year_return"),"") | S54: =IFERROR(MIN(100,MAX(0,ROUND(50+(O54*0.4+P54*0.3+Q54*0.2+R54*0.1)*200,0))),0) -> 0 | T54: =IFERROR(MIN(100,MAX(0,ROUND(50+R54*150+IF(F54>0,15,0)+IF(L54>0,5,-5),0))),0) -> 0 | U54: =IFERROR(MIN(100,MAX(0,ROUND(50+O54*200+IF(AND(O54>0,P54>0),10,-5)+IF(I54<0.2,10,-5),0))),0) -> 0 | V54: =IFERROR(MIN(100,MAX(0,ROUND(30+IF(I54>0,F54/I54,0)*40+IF(ABS(L54)<0.5,15,0)+IF(F54>0.08,10,0),0))),0) -> 0 | W54: =IFERROR(ROUND(T54*'Data Input'!$B$29+U54*'Data Input'!$B$30+V54*'Data Input'!$B$31+S54*'Data Input'!$B$32,0),0) -> 0 | X54: =IFERROR(IF(AND(W54>=70,IF(T54>=60,1,0)+IF(U54>=60,1,0)+IF(V54>=60,1,0)+IF(S54>=60,1,0)>=3),"STRONG BUY",IF(AND(W54>=60,IF(T54>=60,1,0)+IF(U54>=60,1,0)+IF(V54>=60,1,0)+IF(S54>=60,1,0)>=2),"BUY",IF(W54<35,"STRONG SELL",IF(AND(W54<45,IF(T54>=60,1,0)+IF(U54>=60,1,0)+IF(V54>=60,1,0)+IF(S54>=60,1,0)<=1),"SELL","HOLD")))),"") -> STRONG SELL | Y54: =IFERROR(IF(OR(X54="STRONG BUY",X54="STRONG SELL"),"HIGH",IF(OR(X54="BUY",X54="SELL"),"MEDIUM","NEUTRAL")),"") -> HIGH | Z54: =IFERROR(IF(COUNTIF('Asset Analysis'!$A$4:$A$27,A54)>0,"YES","NO"),"") -> NO | AA54: =IFERROR(IF(AND(Z54="NO",W54>=$B$7,J54>=$B$5,S54>=$B$6,I54<=$B$8,F54>=$B$9),"→ ADD TO PORTFOLIO",IF(AND(Z54="YES",OR(J54<=$B$10,S54<=$B$11,W54<=$B$12,K54<=-$B$13)),"→ DELETE FROM PORTFOLIO",IF(AND(Z54="YES",X54="HOLD"),"HOLD — MONITOR",IF(AND(Z54="YES",OR(X54="BUY",X54="STRONG BUY")),"HOLD — STRONG",IF(Z54="NO","NOT QUALIFIED","REVIEW"))))),"") -> NOT QUALIFIED | AB54: =IFERROR(IF(AA54="→ ADD TO PORTFOLIO",IF(W54>=70,"P1 — IMMEDIATE",IF(W54>=60,"P2 — THIS WEEK","P3 — NEXT REBALANCE")),IF(AA54="→ DELETE FROM PORTFOLIO","P1 — IMMEDIATE","—")),"") -> —
A55: VCIT | B55: Vanguard Interm Corp | C55: Fixed Income | D55: IG Corp | E55: =IFERROR(ycps("VCIT","price"),"") | F55: =IFERROR(ycps("VCIT","one_year_return"),"") | G55: =IFERROR(ycps("VCIT","three_year_annualized_return"),"") | H55: =IFERROR(ycps("VCIT","five_year_annualized_return"),"") | I55: =IFERROR(ycps("VCIT","one_year_volatility"),"") | J55: =IFERROR(IF(I55=0,0,(F55-'Data Input'!$B$4)/I55),0) -> 0 | K55: =IFERROR(ycps("VCIT","max_drawdown_3_year"),"") | L55: =IFERROR(ycps("VCIT","beta_5_year"),"") | M55: =IFERROR(ycps("VCIT","dividend_yield"),"") | N55: =IFERROR(ycps("VCIT","forward_pe_ratio"),"") | O55: =IFERROR(ycps("VCIT","one_month_return"),"") | P55: =IFERROR(ycps("VCIT","three_month_return"),"") | Q55: =IFERROR(ycps("VCIT","six_month_return"),"") | R55: =IFERROR(ycps("VCIT","one_year_return"),"") | S55: =IFERROR(MIN(100,MAX(0,ROUND(50+(O55*0.4+P55*0.3+Q55*0.2+R55*0.1)*200,0))),0) -> 0 | T55: =IFERROR(MIN(100,MAX(0,ROUND(50+R55*150+IF(F55>0,15,0)+IF(L55>0,5,-5),0))),0) -> 0 | U55: =IFERROR(MIN(100,MAX(0,ROUND(50+O55*200+IF(AND(O55>0,P55>0),10,-5)+IF(I55<0.2,10,-5),0))),0) -> 0 | V55: =IFERROR(MIN(100,MAX(0,ROUND(30+IF(I55>0,F55/I55,0)*40+IF(ABS(L55)<0.5,15,0)+IF(F55>0.08,10,0),0))),0) -> 0 | W55: =IFERROR(ROUND(T55*'Data Input'!$B$29+U55*'Data Input'!$B$30+V55*'Data Input'!$B$31+S55*'Data Input'!$B$32,0),0) -> 0 | X55: =IFERROR(IF(AND(W55>=70,IF(T55>=60,1,0)+IF(U55>=60,1,0)+IF(V55>=60,1,0)+IF(S55>=60,1,0)>=3),"STRONG BUY",IF(AND(W55>=60,IF(T55>=60,1,0)+IF(U55>=60,1,0)+IF(V55>=60,1,0)+IF(S55>=60,1,0)>=2),"BUY",IF(W55<35,"STRONG SELL",IF(AND(W55<45,IF(T55>=60,1,0)+IF(U55>=60,1,0)+IF(V55>=60,1,0)+IF(S55>=60,1,0)<=1),"SELL","HOLD")))),"") -> STRONG SELL | Y55: =IFERROR(IF(OR(X55="STRONG BUY",X55="STRONG SELL"),"HIGH",IF(OR(X55="BUY",X55="SELL"),"MEDIUM","NEUTRAL")),"") -> HIGH | Z55: =IFERROR(IF(COUNTIF('Asset Analysis'!$A$4:$A$27,A55)>0,"YES","NO"),"") -> NO | AA55: =IFERROR(IF(AND(Z55="NO",W55>=$B$7,J55>=$B$5,S55>=$B$6,I55<=$B$8,F55>=$B$9),"→ ADD TO PORTFOLIO",IF(AND(Z55="YES",OR(J55<=$B$10,S55<=$B$11,W55<=$B$12,K55<=-$B$13)),"→ DELETE FROM PORTFOLIO",IF(AND(Z55="YES",X55="HOLD"),"HOLD — MONITOR",IF(AND(Z55="YES",OR(X55="BUY",X55="STRONG BUY")),"HOLD — STRONG",IF(Z55="NO","NOT QUALIFIED","REVIEW"))))),"") -> NOT QUALIFIED | AB55: =IFERROR(IF(AA55="→ ADD TO PORTFOLIO",IF(W55>=70,"P1 — IMMEDIATE",IF(W55>=60,"P2 — THIS WEEK","P3 — NEXT REBALANCE")),IF(AA55="→ DELETE FROM PORTFOLIO","P1 — IMMEDIATE","—")),"") -> —
A56: LQD | B56: iShares IG Corporate | C56: Fixed Income | D56: IG Corp | E56: =IFERROR(ycps("LQD","price"),"") | F56: =IFERROR(ycps("LQD","one_year_return"),"") | G56: =IFERROR(ycps("LQD","three_year_annualized_return"),"") | H56: =IFERROR(ycps("LQD","five_year_annualized_return"),"") | I56: =IFERROR(ycps("LQD","one_year_volatility"),"") | J56: =IFERROR(IF(I56=0,0,(F56-'Data Input'!$B$4)/I56),0) -> 0 | K56: =IFERROR(ycps("LQD","max_drawdown_3_year"),"") | L56: =IFERROR(ycps("LQD","beta_5_year"),"") | M56: =IFERROR(ycps("LQD","dividend_yield"),"") | N56: =IFERROR(ycps("LQD","forward_pe_ratio"),"") | O56: =IFERROR(ycps("LQD","one_month_return"),"") | P56: =IFERROR(ycps("LQD","three_month_return"),"") | Q56: =IFERROR(ycps("LQD","six_month_return"),"") | R56: =IFERROR(ycps("LQD","one_year_return"),"") | S56: =IFERROR(MIN(100,MAX(0,ROUND(50+(O56*0.4+P56*0.3+Q56*0.2+R56*0.1)*200,0))),0) -> 0 | T56: =IFERROR(MIN(100,MAX(0,ROUND(50+R56*150+IF(F56>0,15,0)+IF(L56>0,5,-5),0))),0) -> 0 | U56: =IFERROR(MIN(100,MAX(0,ROUND(50+O56*200+IF(AND(O56>0,P56>0),10,-5)+IF(I56<0.2,10,-5),0))),0) -> 0 | V56: =IFERROR(MIN(100,MAX(0,ROUND(30+IF(I56>0,F56/I56,0)*40+IF(ABS(L56)<0.5,15,0)+IF(F56>0.08,10,0),0))),0) -> 0 | W56: =IFERROR(ROUND(T56*'Data Input'!$B$29+U56*'Data Input'!$B$30+V56*'Data Input'!$B$31+S56*'Data Input'!$B$32,0),0) -> 0 | X56: =IFERROR(IF(AND(W56>=70,IF(T56>=60,1,0)+IF(U56>=60,1,0)+IF(V56>=60,1,0)+IF(S56>=60,1,0)>=3),"STRONG BUY",IF(AND(W56>=60,IF(T56>=60,1,0)+IF(U56>=60,1,0)+IF(V56>=60,1,0)+IF(S56>=60,1,0)>=2),"BUY",IF(W56<35,"STRONG SELL",IF(AND(W56<45,IF(T56>=60,1,0)+IF(U56>=60,1,0)+IF(V56>=60,1,0)+IF(S56>=60,1,0)<=1),"SELL","HOLD")))),"") -> STRONG SELL | Y56: =IFERROR(IF(OR(X56="STRONG BUY",X56="STRONG SELL"),"HIGH",IF(OR(X56="BUY",X56="SELL"),"MEDIUM","NEUTRAL")),"") -> HIGH | Z56: =IFERROR(IF(COUNTIF('Asset Analysis'!$A$4:$A$27,A56)>0,"YES","NO"),"") -> NO | AA56: =IFERROR(IF(AND(Z56="NO",W56>=$B$7,J56>=$B$5,S56>=$B$6,I56<=$B$8,F56>=$B$9),"→ ADD TO PORTFOLIO",IF(AND(Z56="YES",OR(J56<=$B$10,S56<=$B$11,W56<=$B$12,K56<=-$B$13)),"→ DELETE FROM PORTFOLIO",IF(AND(Z56="YES",X56="HOLD"),"HOLD — MONITOR",IF(AND(Z56="YES",OR(X56="BUY",X56="STRONG BUY")),"HOLD — STRONG",IF(Z56="NO","NOT QUALIFIED","REVIEW"))))),"") -> NOT QUALIFIED | AB56: =IFERROR(IF(AA56="→ ADD TO PORTFOLIO",IF(W56>=70,"P1 — IMMEDIATE",IF(W56>=60,"P2 — THIS WEEK","P3 — NEXT REBALANCE")),IF(AA56="→ DELETE FROM PORTFOLIO","P1 — IMMEDIATE","—")),"") -> —
A57: HYG | B57: iShares High Yield | C57: Fixed Income | D57: High Yield | E57: =IFERROR(ycps("HYG","price"),"") | F57: =IFERROR(ycps("HYG","one_year_return"),"") | G57: =IFERROR(ycps("HYG","three_year_annualized_return"),"") | H57: =IFERROR(ycps("HYG","five_year_annualized_return"),"") | I57: =IFERROR(ycps("HYG","one_year_volatility"),"") | J57: =IFERROR(IF(I57=0,0,(F57-'Data Input'!$B$4)/I57),0) -> 0 | K57: =IFERROR(ycps("HYG","max_drawdown_3_year"),"") | L57: =IFERROR(ycps("HYG","beta_5_year"),"") | M57: =IFERROR(ycps("HYG","dividend_yield"),"") | N57: =IFERROR(ycps("HYG","forward_pe_ratio"),"") | O57: =IFERROR(ycps("HYG","one_month_return"),"") | P57: =IFERROR(ycps("HYG","three_month_return"),"") | Q57: =IFERROR(ycps("HYG","six_month_return"),"") | R57: =IFERROR(ycps("HYG","one_year_return"),"") | S57: =IFERROR(MIN(100,MAX(0,ROUND(50+(O57*0.4+P57*0.3+Q57*0.2+R57*0.1)*200,0))),0) -> 0 | T57: =IFERROR(MIN(100,MAX(0,ROUND(50+R57*150+IF(F57>0,15,0)+IF(L57>0,5,-5),0))),0) -> 0 | U57: =IFERROR(MIN(100,MAX(0,ROUND(50+O57*200+IF(AND(O57>0,P57>0),10,-5)+IF(I57<0.2,10,-5),0))),0) -> 0 | V57: =IFERROR(MIN(100,MAX(0,ROUND(30+IF(I57>0,F57/I57,0)*40+IF(ABS(L57)<0.5,15,0)+IF(F57>0.08,10,0),0))),0) -> 0 | W57: =IFERROR(ROUND(T57*'Data Input'!$B$29+U57*'Data Input'!$B$30+V57*'Data Input'!$B$31+S57*'Data Input'!$B$32,0),0) -> 0 | X57: =IFERROR(IF(AND(W57>=70,IF(T57>=60,1,0)+IF(U57>=60,1,0)+IF(V57>=60,1,0)+IF(S57>=60,1,0)>=3),"STRONG BUY",IF(AND(W57>=60,IF(T57>=60,1,0)+IF(U57>=60,1,0)+IF(V57>=60,1,0)+IF(S57>=60,1,0)>=2),"BUY",IF(W57<35,"STRONG SELL",IF(AND(W57<45,IF(T57>=60,1,0)+IF(U57>=60,1,0)+IF(V57>=60,1,0)+IF(S57>=60,1,0)<=1),"SELL","HOLD")))),"") -> STRONG SELL | Y57: =IFERROR(IF(OR(X57="STRONG BUY",X57="STRONG SELL"),"HIGH",IF(OR(X57="BUY",X57="SELL"),"MEDIUM","NEUTRAL")),"") -> HIGH | Z57: =IFERROR(IF(COUNTIF('Asset Analysis'!$A$4:$A$27,A57)>0,"YES","NO"),"") -> NO | AA57: =IFERROR(IF(AND(Z57="NO",W57>=$B$7,J57>=$B$5,S57>=$B$6,I57<=$B$8,F57>=$B$9),"→ ADD TO PORTFOLIO",IF(AND(Z57="YES",OR(J57<=$B$10,S57<=$B$11,W57<=$B$12,K57<=-$B$13)),"→ DELETE FROM PORTFOLIO",IF(AND(Z57="YES",X57="HOLD"),"HOLD — MONITOR",IF(AND(Z57="YES",OR(X57="BUY",X57="STRONG BUY")),"HOLD — STRONG",IF(Z57="NO","NOT QUALIFIED","REVIEW"))))),"") -> NOT QUALIFIED | AB57: =IFERROR(IF(AA57="→ ADD TO PORTFOLIO",IF(W57>=70,"P1 — IMMEDIATE",IF(W57>=60,"P2 — THIS WEEK","P3 — NEXT REBALANCE")),IF(AA57="→ DELETE FROM PORTFOLIO","P1 — IMMEDIATE","—")),"") -> —
A58: TIP | B58: iShares TIPS Bond | C58: Fixed Income | D58: Inflation | E58: =IFERROR(ycps("TIP","price"),"") | F58: =IFERROR(ycps("TIP","one_year_return"),"") | G58: =IFERROR(ycps("TIP","three_year_annualized_return"),"") | H58: =IFERROR(ycps("TIP","five_year_annualized_return"),"") | I58: =IFERROR(ycps("TIP","one_year_volatility"),"") | J58: =IFERROR(IF(I58=0,0,(F58-'Data Input'!$B$4)/I58),0) -> 0 | K58: =IFERROR(ycps("TIP","max_drawdown_3_year"),"") | L58: =IFERROR(ycps("TIP","beta_5_year"),"") | M58: =IFERROR(ycps("TIP","dividend_yield"),"") | N58: =IFERROR(ycps("TIP","forward_pe_ratio"),"") | O58: =IFERROR(ycps("TIP","one_month_return"),"") | P58: =IFERROR(ycps("TIP","three_month_return"),"") | Q58: =IFERROR(ycps("TIP","six_month_return"),"") | R58: =IFERROR(ycps("TIP","one_year_return"),"") | S58: =IFERROR(MIN(100,MAX(0,ROUND(50+(O58*0.4+P58*0.3+Q58*0.2+R58*0.1)*200,0))),0) -> 0 | T58: =IFERROR(MIN(100,MAX(0,ROUND(50+R58*150+IF(F58>0,15,0)+IF(L58>0,5,-5),0))),0) -> 0 | U58: =IFERROR(MIN(100,MAX(0,ROUND(50+O58*200+IF(AND(O58>0,P58>0),10,-5)+IF(I58<0.2,10,-5),0))),0) -> 0 | V58: =IFERROR(MIN(100,MAX(0,ROUND(30+IF(I58>0,F58/I58,0)*40+IF(ABS(L58)<0.5,15,0)+IF(F58>0.08,10,0),0))),0) -> 0 | W58: =IFERROR(ROUND(T58*'Data Input'!$B$29+U58*'Data Input'!$B$30+V58*'Data Input'!$B$31+S58*'Data Input'!$B$32,0),0) -> 0 | X58: =IFERROR(IF(AND(W58>=70,IF(T58>=60,1,0)+IF(U58>=60,1,0)+IF(V58>=60,1,0)+IF(S58>=60,1,0)>=3),"STRONG BUY",IF(AND(W58>=60,IF(T58>=60,1,0)+IF(U58>=60,1,0)+IF(V58>=60,1,0)+IF(S58>=60,1,0)>=2),"BUY",IF(W58<35,"STRONG SELL",IF(AND(W58<45,IF(T58>=60,1,0)+IF(U58>=60,1,0)+IF(V58>=60,1,0)+IF(S58>=60,1,0)<=1),"SELL","HOLD")))),"") -> STRONG SELL | Y58: =IFERROR(IF(OR(X58="STRONG BUY",X58="STRONG SELL"),"HIGH",IF(OR(X58="BUY",X58="SELL"),"MEDIUM","NEUTRAL")),"") -> HIGH | Z58: =IFERROR(IF(COUNTIF('Asset Analysis'!$A$4:$A$27,A58)>0,"YES","NO"),"") -> NO | AA58: =IFERROR(IF(AND(Z58="NO",W58>=$B$7,J58>=$B$5,S58>=$B$6,I58<=$B$8,F58>=$B$9),"→ ADD TO PORTFOLIO",IF(AND(Z58="YES",OR(J58<=$B$10,S58<=$B$11,W58<=$B$12,K58<=-$B$13)),"→ DELETE FROM PORTFOLIO",IF(AND(Z58="YES",X58="HOLD"),"HOLD — MONITOR",IF(AND(Z58="YES",OR(X58="BUY",X58="STRONG BUY")),"HOLD — STRONG",IF(Z58="NO","NOT QUALIFIED","REVIEW"))))),"") -> NOT QUALIFIED | AB58: =IFERROR(IF(AA58="→ ADD TO PORTFOLIO",IF(W58>=70,"P1 — IMMEDIATE",IF(W58>=60,"P2 — THIS WEEK","P3 — NEXT REBALANCE")),IF(AA58="→ DELETE FROM PORTFOLIO","P1 — IMMEDIATE","—")),"") -> —
A59: VGSH | B59: Vanguard Short Treasury | C59: Fixed Income | D59: Cash Proxy | E59: =IFERROR(ycps("VGSH","price"),"") | F59: =IFERROR(ycps("VGSH","one_year_return"),"") | G59: =IFERROR(ycps("VGSH","three_year_annualized_return"),"") | H59: =IFERROR(ycps("VGSH","five_year_annualized_return"),"") | I59: =IFERROR(ycps("VGSH","one_year_volatility"),"") | J59: =IFERROR(IF(I59=0,0,(F59-'Data Input'!$B$4)/I59),0) -> 0 | K59: =IFERROR(ycps("VGSH","max_drawdown_3_year"),"") | L59: =IFERROR(ycps("VGSH","beta_5_year"),"") | M59: =IFERROR(ycps("VGSH","dividend_yield"),"") | N59: =IFERROR(ycps("VGSH","forward_pe_ratio"),"") | O59: =IFERROR(ycps("VGSH","one_month_return"),"") | P59: =IFERROR(ycps("VGSH","three_month_return"),"") | Q59: =IFERROR(ycps("VGSH","six_month_return"),"") | R59: =IFERROR(ycps("VGSH","one_year_return"),"") | S59: =IFERROR(MIN(100,MAX(0,ROUND(50+(O59*0.4+P59*0.3+Q59*0.2+R59*0.1)*200,0))),0) -> 0 | T59: =IFERROR(MIN(100,MAX(0,ROUND(50+R59*150+IF(F59>0,15,0)+IF(L59>0,5,-5),0))),0) -> 0 | U59: =IFERROR(MIN(100,MAX(0,ROUND(50+O59*200+IF(AND(O59>0,P59>0),10,-5)+IF(I59<0.2,10,-5),0))),0) -> 0 | V59: =IFERROR(MIN(100,MAX(0,ROUND(30+IF(I59>0,F59/I59,0)*40+IF(ABS(L59)<0.5,15,0)+IF(F59>0.08,10,0),0))),0) -> 0 | W59: =IFERROR(ROUND(T59*'Data Input'!$B$29+U59*'Data Input'!$B$30+V59*'Data Input'!$B$31+S59*'Data Input'!$B$32,0),0) -> 0 | X59: =IFERROR(IF(AND(W59>=70,IF(T59>=60,1,0)+IF(U59>=60,1,0)+IF(V59>=60,1,0)+IF(S59>=60,1,0)>=3),"STRONG BUY",IF(AND(W59>=60,IF(T59>=60,1,0)+IF(U59>=60,1,0)+IF(V59>=60,1,0)+IF(S59>=60,1,0)>=2),"BUY",IF(W59<35,"STRONG SELL",IF(AND(W59<45,IF(T59>=60,1,0)+IF(U59>=60,1,0)+IF(V59>=60,1,0)+IF(S59>=60,1,0)<=1),"SELL","HOLD")))),"") -> STRONG SELL | Y59: =IFERROR(IF(OR(X59="STRONG BUY",X59="STRONG SELL"),"HIGH",IF(OR(X59="BUY",X59="SELL"),"MEDIUM","NEUTRAL")),"") -> HIGH | Z59: =IFERROR(IF(COUNTIF('Asset Analysis'!$A$4:$A$27,A59)>0,"YES","NO"),"") -> NO | AA59: =IFERROR(IF(AND(Z59="NO",W59>=$B$7,J59>=$B$5,S59>=$B$6,I59<=$B$8,F59>=$B$9),"→ ADD TO PORTFOLIO",IF(AND(Z59="YES",OR(J59<=$B$10,S59<=$B$11,W59<=$B$12,K59<=-$B$13)),"→ DELETE FROM PORTFOLIO",IF(AND(Z59="YES",X59="HOLD"),"HOLD — MONITOR",IF(AND(Z59="YES",OR(X59="BUY",X59="STRONG BUY")),"HOLD — STRONG",IF(Z59="NO","NOT QUALIFIED","REVIEW"))))),"") -> NOT QUALIFIED | AB59: =IFERROR(IF(AA59="→ ADD TO PORTFOLIO",IF(W59>=70,"P1 — IMMEDIATE",IF(W59>=60,"P2 — THIS WEEK","P3 — NEXT REBALANCE")),IF(AA59="→ DELETE FROM PORTFOLIO","P1 — IMMEDIATE","—")),"") -> —
A60: GLD | B60: SPDR Gold Shares | C60: Alternatives | D60: Gold | E60: =IFERROR(ycps("GLD","price"),"") | F60: =IFERROR(ycps("GLD","one_year_return"),"") | G60: =IFERROR(ycps("GLD","three_year_annualized_return"),"") | H60: =IFERROR(ycps("GLD","five_year_annualized_return"),"") | I60: =IFERROR(ycps("GLD","one_year_volatility"),"") | J60: =IFERROR(IF(I60=0,0,(F60-'Data Input'!$B$4)/I60),0) -> 0 | K60: =IFERROR(ycps("GLD","max_drawdown_3_year"),"") | L60: =IFERROR(ycps("GLD","beta_5_year"),"") | M60: =IFERROR(ycps("GLD","dividend_yield"),"") | N60: =IFERROR(ycps("GLD","forward_pe_ratio"),"") | O60: =IFERROR(ycps("GLD","one_month_return"),"") | P60: =IFERROR(ycps("GLD","three_month_return"),"") | Q60: =IFERROR(ycps("GLD","six_month_return"),"") | R60: =IFERROR(ycps("GLD","one_year_return"),"") | S60: =IFERROR(MIN(100,MAX(0,ROUND(50+(O60*0.4+P60*0.3+Q60*0.2+R60*0.1)*200,0))),0) -> 0 | T60: =IFERROR(MIN(100,MAX(0,ROUND(50+R60*150+IF(F60>0,15,0)+IF(L60>0,5,-5),0))),0) -> 0 | U60: =IFERROR(MIN(100,MAX(0,ROUND(50+O60*200+IF(AND(O60>0,P60>0),10,-5)+IF(I60<0.2,10,-5),0))),0) -> 0 | V60: =IFERROR(MIN(100,MAX(0,ROUND(30+IF(I60>0,F60/I60,0)*40+IF(ABS(L60)<0.5,15,0)+IF(F60>0.08,10,0),0))),0) -> 0 | W60: =IFERROR(ROUND(T60*'Data Input'!$B$29+U60*'Data Input'!$B$30+V60*'Data Input'!$B$31+S60*'Data Input'!$B$32,0),0) -> 0 | X60: =IFERROR(IF(AND(W60>=70,IF(T60>=60,1,0)+IF(U60>=60,1,0)+IF(V60>=60,1,0)+IF(S60>=60,1,0)>=3),"STRONG BUY",IF(AND(W60>=60,IF(T60>=60,1,0)+IF(U60>=60,1,0)+IF(V60>=60,1,0)+IF(S60>=60,1,0)>=2),"BUY",IF(W60<35,"STRONG SELL",IF(AND(W60<45,IF(T60>=60,1,0)+IF(U60>=60,1,0)+IF(V60>=60,1,0)+IF(S60>=60,1,0)<=1),"SELL","HOLD")))),"") -> STRONG SELL | Y60: =IFERROR(IF(OR(X60="STRONG BUY",X60="STRONG SELL"),"HIGH",IF(OR(X60="BUY",X60="SELL"),"MEDIUM","NEUTRAL")),"") -> HIGH | Z60: =IFERROR(IF(COUNTIF('Asset Analysis'!$A$4:$A$27,A60)>0,"YES","NO"),"") -> YES | AA60: =IFERROR(IF(AND(Z60="NO",W60>=$B$7,J60>=$B$5,S60>=$B$6,I60<=$B$8,F60>=$B$9),"→ ADD TO PORTFOLIO",IF(AND(Z60="YES",OR(J60<=$B$10,S60<=$B$11,W60<=$B$12,K60<=-$B$13)),"→ DELETE FROM PORTFOLIO",IF(AND(Z60="YES",X60="HOLD"),"HOLD — MONITOR",IF(AND(Z60="YES",OR(X60="BUY",X60="STRONG BUY")),"HOLD — STRONG",IF(Z60="NO","NOT QUALIFIED","REVIEW"))))),"") -> → DELETE FROM PORTFOLIO | AB60: =IFERROR(IF(AA60="→ ADD TO PORTFOLIO",IF(W60>=70,"P1 — IMMEDIATE",IF(W60>=60,"P2 — THIS WEEK","P3 — NEXT REBALANCE")),IF(AA60="→ DELETE FROM PORTFOLIO","P1 — IMMEDIATE","—")),"") -> P1 — IMMEDIATE
A61: IAU | B61: iShares Gold Trust | C61: Alternatives | D61: Gold | E61: =IFERROR(ycps("IAU","price"),"") | F61: =IFERROR(ycps("IAU","one_year_return"),"") | G61: =IFERROR(ycps("IAU","three_year_annualized_return"),"") | H61: =IFERROR(ycps("IAU","five_year_annualized_return"),"") | I61: =IFERROR(ycps("IAU","one_year_volatility"),"") | J61: =IFERROR(IF(I61=0,0,(F61-'Data Input'!$B$4)/I61),0) -> 0 | K61: =IFERROR(ycps("IAU","max_drawdown_3_year"),"") | L61: =IFERROR(ycps("IAU","beta_5_year"),"") | M61: =IFERROR(ycps("IAU","dividend_yield"),"") | N61: =IFERROR(ycps("IAU","forward_pe_ratio"),"") | O61: =IFERROR(ycps("IAU","one_month_return"),"") | P61: =IFERROR(ycps("IAU","three_month_return"),"") | Q61: =IFERROR(ycps("IAU","six_month_return"),"") | R61: =IFERROR(ycps("IAU","one_year_return"),"") | S61: =IFERROR(MIN(100,MAX(0,ROUND(50+(O61*0.4+P61*0.3+Q61*0.2+R61*0.1)*200,0))),0) -> 0 | T61: =IFERROR(MIN(100,MAX(0,ROUND(50+R61*150+IF(F61>0,15,0)+IF(L61>0,5,-5),0))),0) -> 0 | U61: =IFERROR(MIN(100,MAX(0,ROUND(50+O61*200+IF(AND(O61>0,P61>0),10,-5)+IF(I61<0.2,10,-5),0))),0) -> 0 | V61: =IFERROR(MIN(100,MAX(0,ROUND(30+IF(I61>0,F61/I61,0)*40+IF(ABS(L61)<0.5,15,0)+IF(F61>0.08,10,0),0))),0) -> 0 | W61: =IFERROR(ROUND(T61*'Data Input'!$B$29+U61*'Data Input'!$B$30+V61*'Data Input'!$B$31+S61*'Data Input'!$B$32,0),0) -> 0 | X61: =IFERROR(IF(AND(W61>=70,IF(T61>=60,1,0)+IF(U61>=60,1,0)+IF(V61>=60,1,0)+IF(S61>=60,1,0)>=3),"STRONG BUY",IF(AND(W61>=60,IF(T61>=60,1,0)+IF(U61>=60,1,0)+IF(V61>=60,1,0)+IF(S61>=60,1,0)>=2),"BUY",IF(W61<35,"STRONG SELL",IF(AND(W61<45,IF(T61>=60,1,0)+IF(U61>=60,1,0)+IF(V61>=60,1,0)+IF(S61>=60,1,0)<=1),"SELL","HOLD")))),"") -> STRONG SELL | Y61: =IFERROR(IF(OR(X61="STRONG BUY",X61="STRONG SELL"),"HIGH",IF(OR(X61="BUY",X61="SELL"),"MEDIUM","NEUTRAL")),"") -> HIGH | Z61: =IFERROR(IF(COUNTIF('Asset Analysis'!$A$4:$A$27,A61)>0,"YES","NO"),"") -> NO | AA61: =IFERROR(IF(AND(Z61="NO",W61>=$B$7,J61>=$B$5,S61>=$B$6,I61<=$B$8,F61>=$B$9),"→ ADD TO PORTFOLIO",IF(AND(Z61="YES",OR(J61<=$B$10,S61<=$B$11,W61<=$B$12,K61<=-$B$13)),"→ DELETE FROM PORTFOLIO",IF(AND(Z61="YES",X61="HOLD"),"HOLD — MONITOR",IF(AND(Z61="YES",OR(X61="BUY",X61="STRONG BUY")),"HOLD — STRONG",IF(Z61="NO","NOT QUALIFIED","REVIEW"))))),"") -> NOT QUALIFIED | AB61: =IFERROR(IF(AA61="→ ADD TO PORTFOLIO",IF(W61>=70,"P1 — IMMEDIATE",IF(W61>=60,"P2 — THIS WEEK","P3 — NEXT REBALANCE")),IF(AA61="→ DELETE FROM PORTFOLIO","P1 — IMMEDIATE","—")),"") -> —
A62: SLV | B62: iShares Silver Trust | C62: Alternatives | D62: Silver | E62: =IFERROR(ycps("SLV","price"),"") | F62: =IFERROR(ycps("SLV","one_year_return"),"") | G62: =IFERROR(ycps("SLV","three_year_annualized_return"),"") | H62: =IFERROR(ycps("SLV","five_year_annualized_return"),"") | I62: =IFERROR(ycps("SLV","one_year_volatility"),"") | J62: =IFERROR(IF(I62=0,0,(F62-'Data Input'!$B$4)/I62),0) -> 0 | K62: =IFERROR(ycps("SLV","max_drawdown_3_year"),"") | L62: =IFERROR(ycps("SLV","beta_5_year"),"") | M62: =IFERROR(ycps("SLV","dividend_yield"),"") | N62: =IFERROR(ycps("SLV","forward_pe_ratio"),"") | O62: =IFERROR(ycps("SLV","one_month_return"),"") | P62: =IFERROR(ycps("SLV","three_month_return"),"") | Q62: =IFERROR(ycps("SLV","six_month_return"),"") | R62: =IFERROR(ycps("SLV","one_year_return"),"") | S62: =IFERROR(MIN(100,MAX(0,ROUND(50+(O62*0.4+P62*0.3+Q62*0.2+R62*0.1)*200,0))),0) -> 0 | T62: =IFERROR(MIN(100,MAX(0,ROUND(50+R62*150+IF(F62>0,15,0)+IF(L62>0,5,-5),0))),0) -> 0 | U62: =IFERROR(MIN(100,MAX(0,ROUND(50+O62*200+IF(AND(O62>0,P62>0),10,-5)+IF(I62<0.2,10,-5),0))),0) -> 0 | V62: =IFERROR(MIN(100,MAX(0,ROUND(30+IF(I62>0,F62/I62,0)*40+IF(ABS(L62)<0.5,15,0)+IF(F62>0.08,10,0),0))),0) -> 0 | W62: =IFERROR(ROUND(T62*'Data Input'!$B$29+U62*'Data Input'!$B$30+V62*'Data Input'!$B$31+S62*'Data Input'!$B$32,0),0) -> 0 | X62: =IFERROR(IF(AND(W62>=70,IF(T62>=60,1,0)+IF(U62>=60,1,0)+IF(V62>=60,1,0)+IF(S62>=60,1,0)>=3),"STRONG BUY",IF(AND(W62>=60,IF(T62>=60,1,0)+IF(U62>=60,1,0)+IF(V62>=60,1,0)+IF(S62>=60,1,0)>=2),"BUY",IF(W62<35,"STRONG SELL",IF(AND(W62<45,IF(T62>=60,1,0)+IF(U62>=60,1,0)+IF(V62>=60,1,0)+IF(S62>=60,1,0)<=1),"SELL","HOLD")))),"") -> STRONG SELL | Y62: =IFERROR(IF(OR(X62="STRONG BUY",X62="STRONG SELL"),"HIGH",IF(OR(X62="BUY",X62="SELL"),"MEDIUM","NEUTRAL")),"") -> HIGH | Z62: =IFERROR(IF(COUNTIF('Asset Analysis'!$A$4:$A$27,A62)>0,"YES","NO"),"") -> NO | AA62: =IFERROR(IF(AND(Z62="NO",W62>=$B$7,J62>=$B$5,S62>=$B$6,I62<=$B$8,F62>=$B$9),"→ ADD TO PORTFOLIO",IF(AND(Z62="YES",OR(J62<=$B$10,S62<=$B$11,W62<=$B$12,K62<=-$B$13)),"→ DELETE FROM PORTFOLIO",IF(AND(Z62="YES",X62="HOLD"),"HOLD — MONITOR",IF(AND(Z62="YES",OR(X62="BUY",X62="STRONG BUY")),"HOLD — STRONG",IF(Z62="NO","NOT QUALIFIED","REVIEW"))))),"") -> NOT QUALIFIED | AB62: =IFERROR(IF(AA62="→ ADD TO PORTFOLIO",IF(W62>=70,"P1 — IMMEDIATE",IF(W62>=60,"P2 — THIS WEEK","P3 — NEXT REBALANCE")),IF(AA62="→ DELETE FROM PORTFOLIO","P1 — IMMEDIATE","—")),"") -> —
